{
  "source": {
    "name": "Airframes Project",
    "url": "https://github.com/airframesio",
    "email": "kevin@airframes.io"
  },
  "attribution": {
    "name": "NOAA NWS Aviation Weather Center",
    "url": "https://aviationweather.gov/data/cache/airsigmets.cache.xml.gz"
  },
  "resource_type": "airsigmets",
  "count": 15,
  "airsigmets": [
    {
      "raw_text": "WSUS31 KKCI 270455 SIGE CONVECTIVE SIGMET 28E VALID UNTIL 0655Z PA WV OH FROM 20NNW EWC-40ESE AIR-40SW AIR-50SE CLE-20NNW EWC AREA TS MOV FROM 27020KT. TOPS TO FL380. OUTLOOK VALID 270655-271055 FROM MSS-MPV-PVD-ECG-SPA-30NW BWG-40WSW MKG-MBS-30NE ECK-DXO-CLE-SYR-MSS WST ISSUANCES EXPD. REFER TO MOST RECENT ACUS01 KWNS FROM STORM PREDICTION CENTER FOR SYNOPSIS AND METEOROLOGICAL DETAILS.",
      "valid_time_from": "2025-07-27T04:55:00Z",
      "valid_time_to": "2025-07-27T06:55:00Z",
      "altitude": {
        "max_ft_msl": "38000"
      },
      "hazard": {
        "type": "CONVECTIVE",
        "severity": "SEV"
      },
      "airsigmet_type": "SIGMET",
      "area": [
        {
          "point": {
            "longitude": "-80.3789",
            "latitude": "41.137"
          }
        },
        {
          "point": {
            "longitude": "-80.021",
            "latitude": "39.7629"
          }
        },
        {
          "point": {
            "longitude": "-81.4296",
            "latitude": "39.5483"
          }
        },
        {
          "point": {
            "longitude": "-81.0693",
            "latitude": "40.8266"
          }
        },
        {
          "point": {
            "longitude": "-80.3789",
            "latitude": "41.137"
          }
        }
      ]
    },
    {
      "raw_text": "WSUS31 KKCI 270455 SIGE CONVECTIVE SIGMET 29E VALID UNTIL 0655Z OH FROM 50WSW CLE-40SSE APE-30E CVG-30ESE FWA-50WSW CLE AREA TS MOV FROM 27020KT. TOPS TO FL450. OUTLOOK VALID 270655-271055 FROM MSS-MPV-PVD-ECG-SPA-30NW BWG-40WSW MKG-MBS-30NE ECK-DXO-CLE-SYR-MSS WST ISSUANCES EXPD. REFER TO MOST RECENT ACUS01 KWNS FROM STORM PREDICTION CENTER FOR SYNOPSIS AND METEOROLOGICAL DETAILS.",
      "valid_time_from": "2025-07-27T04:55:00Z",
      "valid_time_to": "2025-07-27T06:55:00Z",
      "altitude": {
        "max_ft_msl": "45000"
      },
      "hazard": {
        "type": "CONVECTIVE",
        "severity": "SEV"
      },
      "airsigmet_type": "SIGMET",
      "area": [
        {
          "point": {
            "longitude": "-82.8742",
            "latitude": "41.0957"
          }
        },
        {
          "point": {
            "longitude": "-82.2602",
            "latitude": "39.5354"
          }
        },
        {
          "point": {
            "longitude": "-84.0525",
            "latitude": "39.0182"
          }
        },
        {
          "point": {
            "longitude": "-84.5762",
            "latitude": "40.7859"
          }
        },
        {
          "point": {
            "longitude": "-82.8742",
            "latitude": "41.0957"
          }
        }
      ]
    },
    {
      "raw_text": "WSUS32 KKCI 270455 SIGC CONVECTIVE SIGMET 48C VALID UNTIL 0655Z SD ND MT WY FROM 40S ISN-30SE DIK-80NE CZI-50NE SHR-40S ISN DMSHG AREA TS MOV FROM 22025KT. TOPS ABV FL450. OUTLOOK VALID 270655-271055 AREA 1...FROM 50WSW MKG-30NW BWG-FAM-30SW BUM-40E SLN-OVR-DBQ-50WSW MKG WST ISSUANCES POSS. REFER TO MOST RECENT ACUS01 KWNS FROM STORM PREDICTION CENTER FOR SYNOPSIS AND METEOROLOGICAL DETAILS. AREA 2...FROM 50NNW GGW-60WNW INL-80NNE DLH-MSP-30ESE FSD-70SSW OBH-LAA-30E DEN-BFF-80NW RAP-40W MLS-50NNW GGW REF WW 545 546 547. WST ISSUANCES EXPD. REFER TO MOST RECENT ACUS01 KWNS FROM STORM PREDICTION CENTER FOR SYNOPSIS AND METEOROLOGICAL DETAILS.",
      "valid_time_from": "2025-07-27T04:55:00Z",
      "valid_time_to": "2025-07-27T06:55:00Z",
      "altitude": {
        "max_ft_msl": "45000"
      },
      "hazard": {
        "type": "CONVECTIVE",
        "severity": "SEV"
      },
      "airsigmet_type": "SIGMET",
      "area": [
        {
          "point": {
            "longitude": "-103.63",
            "latitude": "47.5152"
          }
        },
        {
          "point": {
            "longitude": "-102.2532",
            "latitude": "46.5031"
          }
        },
        {
          "point": {
            "longitude": "-105.1121",
            "latitude": "44.9325"
          }
        },
        {
          "point": {
            "longitude": "-106.2183",
            "latitude": "45.4277"
          }
        },
        {
          "point": {
            "longitude": "-103.63",
            "latitude": "47.5152"
          }
        }
      ]
    },
    {
      "raw_text": "WSUS31 KKCI 270455 SIGE CONVECTIVE SIGMET 30E VALID UNTIL 0655Z VA NC WV TN FROM 30ESE EKN-20ESE LYH-10NNE CLT-50ESE VXV-30ESE HNN-30ESE EKN AREA TS MOV FROM 27015KT. TOPS ABV FL450. OUTLOOK VALID 270655-271055 FROM MSS-MPV-PVD-ECG-SPA-30NW BWG-40WSW MKG-MBS-30NE ECK-DXO-CLE-SYR-MSS WST ISSUANCES EXPD. REFER TO MOST RECENT ACUS01 KWNS FROM STORM PREDICTION CENTER FOR SYNOPSIS AND METEOROLOGICAL DETAILS.",
      "valid_time_from": "2025-07-27T04:55:00Z",
      "valid_time_to": "2025-07-27T06:55:00Z",
      "altitude": {
        "max_ft_msl": "45000"
      },
      "hazard": {
        "type": "CONVECTIVE",
        "severity": "SEV"
      },
      "airsigmet_type": "SIGMET",
      "area": [
        {
          "point": {
            "longitude": "-79.5043",
            "latitude": "38.726"
          }
        },
        {
          "point": {
            "longitude": "-78.8449",
            "latitude": "37.1222"
          }
        },
        {
          "point": {
            "longitude": "-80.8499",
            "latitude": "35.3777"
          }
        },
        {
          "point": {
            "longitude": "-82.941",
            "latitude": "35.5766"
          }
        },
        {
          "point": {
            "longitude": "-81.4357",
            "latitude": "38.556"
          }
        },
        {
          "point": {
            "longitude": "-79.5043",
            "latitude": "38.726"
          }
        }
      ]
    },
    {
      "raw_text": "WSUS32 KKCI 270455 SIGC CONVECTIVE SIGMET 49C VALID UNTIL 0655Z SD WY FROM 40NNW DPR-40SE DPR-10ESE RAP-70NW RAP-40NNW DPR AREA TS MOV FROM 24025KT. TOPS ABV FL450. OUTLOOK VALID 270655-271055 AREA 1...FROM 50WSW MKG-30NW BWG-FAM-30SW BUM-40E SLN-OVR-DBQ-50WSW MKG WST ISSUANCES POSS. REFER TO MOST RECENT ACUS01 KWNS FROM STORM PREDICTION CENTER FOR SYNOPSIS AND METEOROLOGICAL DETAILS. AREA 2...FROM 50NNW GGW-60WNW INL-80NNE DLH-MSP-30ESE FSD-70SSW OBH-LAA-30E DEN-BFF-80NW RAP-40W MLS-50NNW GGW REF WW 545 546 547. WST ISSUANCES EXPD. REFER TO MOST RECENT ACUS01 KWNS FROM STORM PREDICTION CENTER FOR SYNOPSIS AND METEOROLOGICAL DETAILS.",
      "valid_time_from": "2025-07-27T04:55:00Z",
      "valid_time_to": "2025-07-27T06:55:00Z",
      "altitude": {
        "max_ft_msl": "45000"
      },
      "hazard": {
        "type": "CONVECTIVE",
        "severity": "SEV"
      },
      "airsigmet_type": "SIGMET",
      "area": [
        {
          "point": {
            "longitude": "-102.0842",
            "latitude": "45.6936"
          }
        },
        {
          "point": {
            "longitude": "-101.0597",
            "latitude": "44.608"
          }
        },
        {
          "point": {
            "longitude": "-102.7911",
            "latitude": "43.9145"
          }
        },
        {
          "point": {
            "longitude": "-104.1738",
            "latitude": "44.7999"
          }
        },
        {
          "point": {
            "longitude": "-102.0842",
            "latitude": "45.6936"
          }
        }
      ]
    },
    {
      "raw_text": "WSUS31 KKCI 270455 SIGE CONVECTIVE SIGMET 31E VALID UNTIL 0655Z NY PA LO FROM 30WSW MSS-30ESE HNK-40ENE SLT-40NE BUF-30WSW MSS AREA TS MOV FROM 23010KT. TOPS TO FL320. OUTLOOK VALID 270655-271055 FROM MSS-MPV-PVD-ECG-SPA-30NW BWG-40WSW MKG-MBS-30NE ECK-DXO-CLE-SYR-MSS WST ISSUANCES EXPD. REFER TO MOST RECENT ACUS01 KWNS FROM STORM PREDICTION CENTER FOR SYNOPSIS AND METEOROLOGICAL DETAILS.",
      "valid_time_from": "2025-07-27T04:55:00Z",
      "valid_time_to": "2025-07-27T06:55:00Z",
      "altitude": {
        "max_ft_msl": "32000"
      },
      "hazard": {
        "type": "CONVECTIVE",
        "severity": "SEV"
      },
      "airsigmet_type": "SIGMET",
      "area": [
        {
          "point": {
            "longitude": "-75.374",
            "latitude": "44.7156"
          }
        },
        {
          "point": {
            "longitude": "-74.6959",
            "latitude": "41.8658"
          }
        },
        {
          "point": {
            "longitude": "-77.1466",
            "latitude": "41.7615"
          }
        },
        {
          "point": {
            "longitude": "-78.0031",
            "latitude": "43.3982"
          }
        },
        {
          "point": {
            "longitude": "-75.374",
            "latitude": "44.7156"
          }
        }
      ]
    },
    {
      "raw_text": "WSUS32 KKCI 270455 SIGC CONVECTIVE SIGMET 50C VALID UNTIL 0655Z IN IL FROM 40WSW GIJ-40NE BVT-20WSW BVT-50S JOT-40WSW GIJ AREA TS MOV FROM 27025KT. TOPS ABV FL450. OUTLOOK VALID 270655-271055 AREA 1...FROM 50WSW MKG-30NW BWG-FAM-30SW BUM-40E SLN-OVR-DBQ-50WSW MKG WST ISSUANCES POSS. REFER TO MOST RECENT ACUS01 KWNS FROM STORM PREDICTION CENTER FOR SYNOPSIS AND METEOROLOGICAL DETAILS. AREA 2...FROM 50NNW GGW-60WNW INL-80NNE DLH-MSP-30ESE FSD-70SSW OBH-LAA-30E DEN-BFF-80NW RAP-40W MLS-50NNW GGW REF WW 545 546 547. WST ISSUANCES EXPD. REFER TO MOST RECENT ACUS01 KWNS FROM STORM PREDICTION CENTER FOR SYNOPSIS AND METEOROLOGICAL DETAILS.",
      "valid_time_from": "2025-07-27T04:55:00Z",
      "valid_time_to": "2025-07-27T06:55:00Z",
      "altitude": {
        "max_ft_msl": "45000"
      },
      "hazard": {
        "type": "CONVECTIVE",
        "severity": "SEV"
      },
      "airsigmet_type": "SIGMET",
      "area": [
        {
          "point": {
            "longitude": "-87.1402",
            "latitude": "41.5127"
          }
        },
        {
          "point": {
            "longitude": "-86.4469",
            "latitude": "41.0284"
          }
        },
        {
          "point": {
            "longitude": "-87.4734",
            "latitude": "40.4321"
          }
        },
        {
          "point": {
            "longitude": "-88.32",
            "latitude": "40.7146"
          }
        },
        {
          "point": {
            "longitude": "-87.1402",
            "latitude": "41.5127"
          }
        }
      ]
    },
    {
      "raw_text": "WSUS31 KKCI 270455 SIGE CONVECTIVE SIGMET 32E VALID UNTIL 0655Z NJ PA DE MD VA DC WV FROM 50SW HNK-20NNW SAX-40NNW ORF-20SW RIC-20WNW CSN-50SW HNK AREA TS MOV FROM 27020KT. TOPS ABV FL450. OUTLOOK VALID 270655-271055 FROM MSS-MPV-PVD-ECG-SPA-30NW BWG-40WSW MKG-MBS-30NE ECK-DXO-CLE-SYR-MSS WST ISSUANCES EXPD. REFER TO MOST RECENT ACUS01 KWNS FROM STORM PREDICTION CENTER FOR SYNOPSIS AND METEOROLOGICAL DETAILS.",
      "valid_time_from": "2025-07-27T04:55:00Z",
      "valid_time_to": "2025-07-27T06:55:00Z",
      "altitude": {
        "max_ft_msl": "45000"
      },
      "hazard": {
        "type": "CONVECTIVE",
        "severity": "SEV"
      },
      "airsigmet_type": "SIGMET",
      "area": [
        {
          "point": {
            "longitude": "-76.1083",
            "latitude": "41.4665"
          }
        },
        {
          "point": {
            "longitude": "-74.7095",
            "latitude": "41.377"
          }
        },
        {
          "point": {
            "longitude": "-76.5207",
            "latitude": "37.5037"
          }
        },
        {
          "point": {
            "longitude": "-77.6153",
            "latitude": "37.2646"
          }
        },
        {
          "point": {
            "longitude": "-78.2638",
            "latitude": "38.7665"
          }
        },
        {
          "point": {
            "longitude": "-76.1083",
            "latitude": "41.4665"
          }
        }
      ]
    },
    {
      "raw_text": "WSUS32 KKCI 270455 SIGC CONVECTIVE SIGMET 51C VALID UNTIL 0655Z KS NE SD CO FROM 40NE ANW-40WNW OBH-40N GLD-10S AKO-70W ANW-40NE ANW AREA SEV TS MOV FROM 25025KT. TOPS ABV FL450. HAIL TO 1.5 IN...WIND GUSTS TO 50KT POSS. OUTLOOK VALID 270655-271055 AREA 1...FROM 50WSW MKG-30NW BWG-FAM-30SW BUM-40E SLN-OVR-DBQ-50WSW MKG WST ISSUANCES POSS. REFER TO MOST RECENT ACUS01 KWNS FROM STORM PREDICTION CENTER FOR SYNOPSIS AND METEOROLOGICAL DETAILS. AREA 2...FROM 50NNW GGW-60WNW INL-80NNE DLH-MSP-30ESE FSD-70SSW OBH-LAA-30E DEN-BFF-80NW RAP-40W MLS-50NNW GGW REF WW 545 546 547. WST ISSUANCES EXPD. REFER TO MOST RECENT ACUS01 KWNS FROM STORM PREDICTION CENTER FOR SYNOPSIS AND METEOROLOGICAL DETAILS.",
      "valid_time_from": "2025-07-27T04:55:00Z",
      "valid_time_to": "2025-07-27T06:55:00Z",
      "altitude": {
        "max_ft_msl": "45000"
      },
      "hazard": {
        "type": "CONVECTIVE",
        "severity": "SEV"
      },
      "airsigmet_type": "SIGMET",
      "area": [
        {
          "point": {
            "longitude": "-99.3469",
            "latitude": "43.0383"
          }
        },
        {
          "point": {
            "longitude": "-99.1717",
            "latitude": "41.6315"
          }
        },
        {
          "point": {
            "longitude": "-101.69",
            "latitude": "40.0548"
          }
        },
        {
          "point": {
            "longitude": "-103.18",
            "latitude": "39.9893"
          }
        },
        {
          "point": {
            "longitude": "-101.5755",
            "latitude": "42.5591"
          }
        },
        {
          "point": {
            "longitude": "-99.3469",
            "latitude": "43.0383"
          }
        }
      ]
    },
    {
      "raw_text": "WSUS32 KKCI 270455 SIGC CONVECTIVE SIGMET 52C VALID UNTIL 0655Z TX FROM 40SSE DLF-70N LRD-30ENE LRD-40SSE LRD-40SSE DLF AREA TS MOV FROM 18005KT. TOPS TO FL410. OUTLOOK VALID 270655-271055 AREA 1...FROM 50WSW MKG-30NW BWG-FAM-30SW BUM-40E SLN-OVR-DBQ-50WSW MKG WST ISSUANCES POSS. REFER TO MOST RECENT ACUS01 KWNS FROM STORM PREDICTION CENTER FOR SYNOPSIS AND METEOROLOGICAL DETAILS. AREA 2...FROM 50NNW GGW-60WNW INL-80NNE DLH-MSP-30ESE FSD-70SSW OBH-LAA-30E DEN-BFF-80NW RAP-40W MLS-50NNW GGW REF WW 545 546 547. WST ISSUANCES EXPD. REFER TO MOST RECENT ACUS01 KWNS FROM STORM PREDICTION CENTER FOR SYNOPSIS AND METEOROLOGICAL DETAILS.",
      "valid_time_from": "2025-07-27T04:55:00Z",
      "valid_time_to": "2025-07-27T06:55:00Z",
      "altitude": {
        "max_ft_msl": "41000"
      },
      "hazard": {
        "type": "CONVECTIVE",
        "severity": "SEV"
      },
      "airsigmet_type": "SIGMET",
      "area": [
        {
          "point": {
            "longitude": "-100.4799",
            "latitude": "28.7455"
          }
        },
        {
          "point": {
            "longitude": "-99.42",
            "latitude": "28.6478"
          }
        },
        {
          "point": {
            "longitude": "-98.8952",
            "latitude": "27.6715"
          }
        },
        {
          "point": {
            "longitude": "-99.1348",
            "latitude": "26.8656"
          }
        },
        {
          "point": {
            "longitude": "-100.4799",
            "latitude": "28.7455"
          }
        }
      ]
    },
    {
      "raw_text": "WSUS32 KKCI 270455 SIGC CONVECTIVE SIGMET 53C VALID UNTIL 0655Z SD ND FROM 80W GFK-30W FAR-50SE ABR-50E PIR-30WNW BIS-80W GFK AREA SEV TS MOV FROM 26020KT. TOPS ABV FL450. HAIL TO 1.75 IN...WIND GUSTS TO 50KT POSS. OUTLOOK VALID 270655-271055 AREA 1...FROM 50WSW MKG-30NW BWG-FAM-30SW BUM-40E SLN-OVR-DBQ-50WSW MKG WST ISSUANCES POSS. REFER TO MOST RECENT ACUS01 KWNS FROM STORM PREDICTION CENTER FOR SYNOPSIS AND METEOROLOGICAL DETAILS. AREA 2...FROM 50NNW GGW-60WNW INL-80NNE DLH-MSP-30ESE FSD-70SSW OBH-LAA-30E DEN-BFF-80NW RAP-40W MLS-50NNW GGW REF WW 545 546 547. WST ISSUANCES EXPD. REFER TO MOST RECENT ACUS01 KWNS FROM STORM PREDICTION CENTER FOR SYNOPSIS AND METEOROLOGICAL DETAILS.",
      "valid_time_from": "2025-07-27T04:55:00Z",
      "valid_time_to": "2025-07-27T06:55:00Z",
      "altitude": {
        "max_ft_msl": "45000"
      },
      "hazard": {
        "type": "CONVECTIVE",
        "severity": "SEV"
      },
      "airsigmet_type": "SIGMET",
      "area": [
        {
          "point": {
            "longitude": "-99.1746",
            "latitude": "47.9329"
          }
        },
        {
          "point": {
            "longitude": "-97.5842",
            "latitude": "46.7477"
          }
        },
        {
          "point": {
            "longitude": "-97.5371",
            "latitude": "44.8262"
          }
        },
        {
          "point": {
            "longitude": "-99.0008",
            "latitude": "44.394"
          }
        },
        {
          "point": {
            "longitude": "-101.351",
            "latitude": "46.9605"
          }
        },
        {
          "point": {
            "longitude": "-99.1746",
            "latitude": "47.9329"
          }
        }
      ]
    },
    {
      "raw_text": "WSUS32 KKCI 270455 SIGC CONVECTIVE SIGMET 54C VALID UNTIL 0655Z IL MO FROM 30NW AXC-40S AXC-20S STL-10SE COU-40NNE COU-30NW AXC AREA TS MOV FROM 27015KT. TOPS ABV FL450. OUTLOOK VALID 270655-271055 AREA 1...FROM 50WSW MKG-30NW BWG-FAM-30SW BUM-40E SLN-OVR-DBQ-50WSW MKG WST ISSUANCES POSS. REFER TO MOST RECENT ACUS01 KWNS FROM STORM PREDICTION CENTER FOR SYNOPSIS AND METEOROLOGICAL DETAILS. AREA 2...FROM 50NNW GGW-60WNW INL-80NNE DLH-MSP-30ESE FSD-70SSW OBH-LAA-30E DEN-BFF-80NW RAP-40W MLS-50NNW GGW REF WW 545 546 547. WST ISSUANCES EXPD. REFER TO MOST RECENT ACUS01 KWNS FROM STORM PREDICTION CENTER FOR SYNOPSIS AND METEOROLOGICAL DETAILS.",
      "valid_time_from": "2025-07-27T04:55:00Z",
      "valid_time_to": "2025-07-27T06:55:00Z",
      "altitude": {
        "max_ft_msl": "45000"
      },
      "hazard": {
        "type": "CONVECTIVE",
        "severity": "SEV"
      },
      "airsigmet_type": "SIGMET",
      "area": [
        {
          "point": {
            "longitude": "-89.3149",
            "latitude": "40.0848"
          }
        },
        {
          "point": {
            "longitude": "-88.85",
            "latitude": "39.0652"
          }
        },
        {
          "point": {
            "longitude": "-90.48",
            "latitude": "38.5276"
          }
        },
        {
          "point": {
            "longitude": "-92.0654",
            "latitude": "38.6992"
          }
        },
        {
          "point": {
            "longitude": "-91.8906",
            "latitude": "39.4337"
          }
        },
        {
          "point": {
            "longitude": "-89.3149",
            "latitude": "40.0848"
          }
        }
      ]
    },
    {
      "raw_text": "WSUS33 KKCI 270455 SIGW CONVECTIVE SIGMET 17W VALID UNTIL 0655Z OR FROM 90SW BKE-60WNW REO-20SE LKV-30N LKV-90SW BKE DMSHG AREA TS MOV LTL. TOPS TO FL320. OUTLOOK VALID 270655-271055 FROM 50SE YQL-50NNW GGW-40W MLS-60ESE HLN-30WNW DBS-70E REO-30WNW BAM-FMG-LKV-PDT-MLP-50SE YQL REF WW 545. WST ISSUANCES POSS. REFER TO MOST RECENT ACUS01 KWNS FROM STORM PREDICTION CENTER FOR SYNOPSIS AND METEOROLOGICAL DETAILS.",
      "valid_time_from": "2025-07-27T04:55:00Z",
      "valid_time_to": "2025-07-27T06:55:00Z",
      "altitude": {
        "max_ft_msl": "32000"
      },
      "hazard": {
        "type": "CONVECTIVE",
        "severity": "SEV"
      },
      "airsigmet_type": "SIGMET",
      "area": [
        {
          "point": {
            "longitude": "-119.279",
            "latitude": "43.7697"
          }
        },
        {
          "point": {
            "longitude": "-119.1289",
            "latitude": "42.9647"
          }
        },
        {
          "point": {
            "longitude": "-120.1925",
            "latitude": "42.2545"
          }
        },
        {
          "point": {
            "longitude": "-120.51",
            "latitude": "42.9931"
          }
        },
        {
          "point": {
            "longitude": "-119.279",
            "latitude": "43.7697"
          }
        }
      ]
    },
    {
      "raw_text": "WSUS33 KKCI 270455 SIGW CONVECTIVE SIGMET 18W VALID UNTIL 0655Z MT FROM 60NW ISN-50NE MLS-40NNE BIL-40N GTF-50SE YQL-60NW ISN AREA TS MOV FROM 27030KT. TOPS ABV FL450. OUTLOOK VALID 270655-271055 FROM 50SE YQL-50NNW GGW-40W MLS-60ESE HLN-30WNW DBS-70E REO-30WNW BAM-FMG-LKV-PDT-MLP-50SE YQL REF WW 545. WST ISSUANCES POSS. REFER TO MOST RECENT ACUS01 KWNS FROM STORM PREDICTION CENTER FOR SYNOPSIS AND METEOROLOGICAL DETAILS.",
      "valid_time_from": "2025-07-27T04:55:00Z",
      "valid_time_to": "2025-07-27T06:55:00Z",
      "altitude": {
        "max_ft_msl": "45000"
      },
      "hazard": {
        "type": "CONVECTIVE",
        "severity": "SEV"
      },
      "airsigmet_type": "SIGMET",
      "area": [
        {
          "point": {
            "longitude": "-104.7021",
            "latitude": "48.8801"
          }
        },
        {
          "point": {
            "longitude": "-105.0843",
            "latitude": "46.9675"
          }
        },
        {
          "point": {
            "longitude": "-108.261",
            "latitude": "46.4236"
          }
        },
        {
          "point": {
            "longitude": "-111.41",
            "latitude": "48.1148"
          }
        },
        {
          "point": {
            "longitude": "-111.8989",
            "latitude": "49.0357"
          }
        },
        {
          "point": {
            "longitude": "-104.7021",
            "latitude": "48.8801"
          }
        }
      ]
    },
    {
      "raw_text": "WSUS33 KKCI 270455 SIGW CONVECTIVE SIGMET 19W VALID UNTIL 0655Z ID OR WA FROM 80NNE BKE-50WNW LKT-20SSW BOI-20NNW REO-30W BKE-80NNE BKE AREA TS MOV FROM 24020KT. TOPS TO FL340. OUTLOOK VALID 270655-271055 FROM 50SE YQL-50NNW GGW-40W MLS-60ESE HLN-30WNW DBS-70E REO-30WNW BAM-FMG-LKV-PDT-MLP-50SE YQL REF WW 545. WST ISSUANCES POSS. REFER TO MOST RECENT ACUS01 KWNS FROM STORM PREDICTION CENTER FOR SYNOPSIS AND METEOROLOGICAL DETAILS.",
      "valid_time_from": "2025-07-27T04:55:00Z",
      "valid_time_to": "2025-07-27T06:55:00Z",
      "altitude": {
        "max_ft_msl": "34000"
      },
      "hazard": {
        "type": "CONVECTIVE",
        "severity": "SEV"
      },
      "airsigmet_type": "SIGMET",
      "area": [
        {
          "point": {
            "longitude": "-117.0768",
            "latitude": "46.066"
          }
        },
        {
          "point": {
            "longitude": "-115.178",
            "latitude": "45.3345"
          }
        },
        {
          "point": {
            "longitude": "-116.3646",
            "latitude": "43.2428"
          }
        },
        {
          "point": {
            "longitude": "-118.0436",
            "latitude": "42.8969"
          }
        },
        {
          "point": {
            "longitude": "-118.5194",
            "latitude": "44.8378"
          }
        },
        {
          "point": {
            "longitude": "-117.0768",
            "latitude": "46.066"
          }
        }
      ]
    }
  ]
}