{
  "source": {
    "name": "Airframes Project",
    "url": "https://github.com/airframesio",
    "email": "kevin@airframes.io"
  },
  "attribution": {
    "name": "NOAA NWS Aviation Weather Center",
    "url": "https://aviationweather.gov/data/cache/airsigmets.cache.xml.gz"
  },
  "resource_type": "airsigmets",
  "count": 14,
  "airsigmets": [
    {
      "raw_text": "WSUS32 KKCI 032255 SIGC CONVECTIVE SIGMET 45C VALID UNTIL 0055Z OH IN IL FROM 50WSW CLE-50WNW HNN-30ESE AXC-10ENE BVT-50WSW CLE AREA EMBD TS MOV FROM 23060KT. TOPS TO FL320. OUTLOOK VALID 040055-040455 AREA 1...FROM APE-ODF-40WNW CWK-30WSW COU-APE REF WW 107 108 109. WST ISSUANCES EXPD. REFER TO MOST RECENT ACUS01 KWNS FROM STORM PREDICTION CENTER FOR SYNOPSIS AND METEOROLOGICAL DETAILS. AREA 2...FROM AKO-40ESE MCK-TXO-50WSW TCC-AKO WST ISSUANCES EXPD. REFER TO MOST RECENT ACUS01 KWNS FROM STORM PREDICTION CENTER FOR SYNOPSIS AND METEOROLOGICAL DETAILS.",
      "valid_time_from": "2025-04-03T22:55:00Z",
      "valid_time_to": "2025-04-04T00:55:00Z",
      "altitude": {
        "max_ft_msl": "32000"
      },
      "hazard": {
        "type": "CONVECTIVE",
        "severity": "SEV"
      },
      "airsigmet_type": "SIGMET",
      "area": [
        {
          "point": {
            "longitude": "-82.8742",
            "latitude": "41.0957"
          }
        },
        {
          "point": {
            "longitude": "-83.0241",
            "latitude": "39.0655"
          }
        },
        {
          "point": {
            "longitude": "-88.2474",
            "latitude": "39.5359"
          }
        },
        {
          "point": {
            "longitude": "-86.8622",
            "latitude": "40.6251"
          }
        },
        {
          "point": {
            "longitude": "-82.8742",
            "latitude": "41.0957"
          }
        }
      ]
    },
    {
      "raw_text": "WSUS32 KKCI 032255 SIGC CONVECTIVE SIGMET 46C VALID UNTIL 0055Z VA OH TN KY IN AL IL MS LA MO AR TX OK FROM 10SE UIN-30WNW HNN-40WNW HMV-20SSW MSL-40WNW GGG-10SE UIN AREA SEV EMBD TS MOV FROM 23060KT. TOPS ABV FL450. TORNADOES...HAIL TO 2 IN...WIND GUSTS TO 60KT POSS. OUTLOOK VALID 040055-040455 AREA 1...FROM APE-ODF-40WNW CWK-30WSW COU-APE REF WW 107 108 109. WST ISSUANCES EXPD. REFER TO MOST RECENT ACUS01 KWNS FROM STORM PREDICTION CENTER FOR SYNOPSIS AND METEOROLOGICAL DETAILS. AREA 2...FROM AKO-40ESE MCK-TXO-50WSW TCC-AKO WST ISSUANCES EXPD. REFER TO MOST RECENT ACUS01 KWNS FROM STORM PREDICTION CENTER FOR SYNOPSIS AND METEOROLOGICAL DETAILS.",
      "valid_time_from": "2025-04-03T22:55:00Z",
      "valid_time_to": "2025-04-04T00:55:00Z",
      "altitude": {
        "max_ft_msl": "45000"
      },
      "hazard": {
        "type": "CONVECTIVE",
        "severity": "SEV"
      },
      "airsigmet_type": "SIGMET",
      "area": [
        {
          "point": {
            "longitude": "-91.1231",
            "latitude": "39.7292"
          }
        },
        {
          "point": {
            "longitude": "-82.6275",
            "latitude": "38.941"
          }
        },
        {
          "point": {
            "longitude": "-82.8959",
            "latitude": "36.6919"
          }
        },
        {
          "point": {
            "longitude": "-87.6341",
            "latitude": "34.3928"
          }
        },
        {
          "point": {
            "longitude": "-95.4796",
            "latitude": "32.6723"
          }
        },
        {
          "point": {
            "longitude": "-91.1231",
            "latitude": "39.7292"
          }
        }
      ]
    },
    {
      "raw_text": "WSUS32 KKCI 032255 SIGC CONVECTIVE SIGMET 47C VALID UNTIL 0055Z KS CO FROM 10SSE MCK-40ESE LAA-20NE TBE-40W GLD-10SSE MCK AREA EMBD TS MOV FROM 21030KT. TOPS TO FL280. OUTLOOK VALID 040055-040455 AREA 1...FROM APE-ODF-40WNW CWK-30WSW COU-APE REF WW 107 108 109. WST ISSUANCES EXPD. REFER TO MOST RECENT ACUS01 KWNS FROM STORM PREDICTION CENTER FOR SYNOPSIS AND METEOROLOGICAL DETAILS. AREA 2...FROM AKO-40ESE MCK-TXO-50WSW TCC-AKO WST ISSUANCES EXPD. REFER TO MOST RECENT ACUS01 KWNS FROM STORM PREDICTION CENTER FOR SYNOPSIS AND METEOROLOGICAL DETAILS.",
      "valid_time_from": "2025-04-03T22:55:00Z",
      "valid_time_to": "2025-04-04T00:55:00Z",
      "altitude": {
        "max_ft_msl": "28000"
      },
      "hazard": {
        "type": "CONVECTIVE",
        "severity": "SEV"
      },
      "airsigmet_type": "SIGMET",
      "area": [
        {
          "point": {
            "longitude": "-100.5047",
            "latitude": "40.0423"
          }
        },
        {
          "point": {
            "longitude": "-101.9112",
            "latitude": "37.943"
          }
        },
        {
          "point": {
            "longitude": "-103.3037",
            "latitude": "37.5047"
          }
        },
        {
          "point": {
            "longitude": "-102.5501",
            "latitude": "39.3868"
          }
        },
        {
          "point": {
            "longitude": "-100.5047",
            "latitude": "40.0423"
          }
        }
      ]
    },
    {
      "raw_text": "WSUS32 KKCI 032255 SIGC CONVECTIVE SIGMET 48C VALID UNTIL 0055Z TX OK CO NM FROM 50E TBE-40SW LBL-40NE TCC-40NNW TCC-50E TBE AREA EMBD TS MOV FROM 23030KT. TOPS TO FL280. OUTLOOK VALID 040055-040455 AREA 1...FROM APE-ODF-40WNW CWK-30WSW COU-APE REF WW 107 108 109. WST ISSUANCES EXPD. REFER TO MOST RECENT ACUS01 KWNS FROM STORM PREDICTION CENTER FOR SYNOPSIS AND METEOROLOGICAL DETAILS. AREA 2...FROM AKO-40ESE MCK-TXO-50WSW TCC-AKO WST ISSUANCES EXPD. REFER TO MOST RECENT ACUS01 KWNS FROM STORM PREDICTION CENTER FOR SYNOPSIS AND METEOROLOGICAL DETAILS.",
      "valid_time_from": "2025-04-03T22:55:00Z",
      "valid_time_to": "2025-04-04T00:55:00Z",
      "altitude": {
        "max_ft_msl": "28000"
      },
      "hazard": {
        "type": "CONVECTIVE",
        "severity": "SEV"
      },
      "airsigmet_type": "SIGMET",
      "area": [
        {
          "point": {
            "longitude": "-102.5502",
            "latitude": "37.2654"
          }
        },
        {
          "point": {
            "longitude": "-101.5553",
            "latitude": "36.5685"
          }
        },
        {
          "point": {
            "longitude": "-103.0216",
            "latitude": "35.6487"
          }
        },
        {
          "point": {
            "longitude": "-103.9136",
            "latitude": "35.7937"
          }
        },
        {
          "point": {
            "longitude": "-102.5502",
            "latitude": "37.2654"
          }
        }
      ]
    },
    {
      "raw_text": "WSUS32 KKCI 032255 SIGC CONVECTIVE SIGMET 49C VALID UNTIL 0055Z MO OK KS FROM 40SSW BUM-40W SGF-40ENE TUL-20N TUL-40SSW BUM AREA EMBD TS MOV FROM 23055KT. TOPS TO FL420. OUTLOOK VALID 040055-040455 AREA 1...FROM APE-ODF-40WNW CWK-30WSW COU-APE REF WW 107 108 109. WST ISSUANCES EXPD. REFER TO MOST RECENT ACUS01 KWNS FROM STORM PREDICTION CENTER FOR SYNOPSIS AND METEOROLOGICAL DETAILS. AREA 2...FROM AKO-40ESE MCK-TXO-50WSW TCC-AKO WST ISSUANCES EXPD. REFER TO MOST RECENT ACUS01 KWNS FROM STORM PREDICTION CENTER FOR SYNOPSIS AND METEOROLOGICAL DETAILS.",
      "valid_time_from": "2025-04-03T22:55:00Z",
      "valid_time_to": "2025-04-04T00:55:00Z",
      "altitude": {
        "max_ft_msl": "42000"
      },
      "hazard": {
        "type": "CONVECTIVE",
        "severity": "SEV"
      },
      "airsigmet_type": "SIGMET",
      "area": [
        {
          "point": {
            "longitude": "-94.8113",
            "latitude": "37.6554"
          }
        },
        {
          "point": {
            "longitude": "-94.1663",
            "latitude": "37.3571"
          }
        },
        {
          "point": {
            "longitude": "-95.0265",
            "latitude": "36.452"
          }
        },
        {
          "point": {
            "longitude": "-95.79",
            "latitude": "36.5324"
          }
        },
        {
          "point": {
            "longitude": "-94.8113",
            "latitude": "37.6554"
          }
        }
      ]
    },
    {
      "raw_text": "WSUS31 KKCI 032255 SIGE CONVECTIVE SIGMET 44E VALID UNTIL 0055Z VA WV OH KY FROM 30WNW HNN-40WNW CSN-40WNW LYH-40WNW HMV-30WNW HNN AREA SEV EMBD TS MOV FROM 23045KT. TOPS ABV FL450. TORNADOES...HAIL TO 1.5 IN...WIND GUSTS TO 60KT POSS. OUTLOOK VALID 040055-040455 FROM JFK-30SSW GSO-ODF-APE-JFK REF WW 107. WST ISSUANCES EXPD. REFER TO MOST RECENT ACUS01 KWNS FROM STORM PREDICTION CENTER FOR SYNOPSIS AND METEOROLOGICAL DETAILS.",
      "valid_time_from": "2025-04-03T22:55:00Z",
      "valid_time_to": "2025-04-04T00:55:00Z",
      "altitude": {
        "max_ft_msl": "45000"
      },
      "hazard": {
        "type": "CONVECTIVE",
        "severity": "SEV"
      },
      "airsigmet_type": "SIGMET",
      "area": [
        {
          "point": {
            "longitude": "-82.6275",
            "latitude": "38.941"
          }
        },
        {
          "point": {
            "longitude": "-78.6591",
            "latitude": "38.8917"
          }
        },
        {
          "point": {
            "longitude": "-80.0041",
            "latitude": "37.5019"
          }
        },
        {
          "point": {
            "longitude": "-82.8959",
            "latitude": "36.6919"
          }
        },
        {
          "point": {
            "longitude": "-82.6275",
            "latitude": "38.941"
          }
        }
      ]
    },
    {
      "raw_text": "WSUS31 KKCI 032255 SIGE CONVECTIVE SIGMET 45E VALID UNTIL 0055Z PA MD WV OH FROM 60WSW CLE-10NNW JST-40WNW CSN-50WNW HNN-60WSW CLE AREA SEV EMBD TS MOV FROM 25055KT. TOPS TO FL320. HAIL TO 1 IN...WIND GUSTS TO 50KT POSS. OUTLOOK VALID 040055-040455 FROM JFK-30SSW GSO-ODF-APE-JFK REF WW 107. WST ISSUANCES EXPD. REFER TO MOST RECENT ACUS01 KWNS FROM STORM PREDICTION CENTER FOR SYNOPSIS AND METEOROLOGICAL DETAILS.",
      "valid_time_from": "2025-04-03T22:55:00Z",
      "valid_time_to": "2025-04-04T00:55:00Z",
      "altitude": {
        "max_ft_msl": "32000"
      },
      "hazard": {
        "type": "CONVECTIVE",
        "severity": "SEV"
      },
      "airsigmet_type": "SIGMET",
      "area": [
        {
          "point": {
            "longitude": "-83.0713",
            "latitude": "41.0319"
          }
        },
        {
          "point": {
            "longitude": "-78.9159",
            "latitude": "40.4777"
          }
        },
        {
          "point": {
            "longitude": "-78.6591",
            "latitude": "38.8917"
          }
        },
        {
          "point": {
            "longitude": "-83.0241",
            "latitude": "39.0655"
          }
        },
        {
          "point": {
            "longitude": "-83.0713",
            "latitude": "41.0319"
          }
        }
      ]
    },
    {
      "raw_text": "WSUS33 KKCI 032255 SIGW CONVECTIVE SIGMET 25W VALID UNTIL 0055Z MT WY UT ID FROM 30SSE DLN-20WNW JAC-50SW MLD-60NNW TWF-30SSE DLN AREA EMBD TS MOV FROM 32010KT. TOPS TO FL240. OUTLOOK VALID 040055-040455 AREA 1...FROM 30N MLP-50ESE HLN-50WSW MLS-30WSW CZI-DBS-BKE-30N MLP WST ISSUANCES POSS. REFER TO MOST RECENT ACUS01 KWNS FROM STORM PREDICTION CENTER FOR SYNOPSIS AND METEOROLOGICAL DETAILS. AREA 2...FROM 50E SLC-30SSE CHE-50NNE RSK-50NE PHX-30W PGS-50E SLC WST ISSUANCES POSS. REFER TO MOST RECENT ACUS01 KWNS FROM STORM PREDICTION CENTER FOR SYNOPSIS AND METEOROLOGICAL DETAILS. AREA 3...FROM 50NW FMG-30S OAL-40ESE CZQ-40NNW SAC-50NW FMG WST ISSUANCES POSS. REFER TO MOST RECENT ACUS01 KWNS FROM STORM PREDICTION CENTER FOR SYNOPSIS AND METEOROLOGICAL DETAILS. AREA 4...FROM 40ENE EHF-30WNW BZA-MZB-30E RZS-40ENE EHF WST ISSUANCES POSS. REFER TO MOST RECENT ACUS01 KWNS FROM STORM PREDICTION CENTER FOR SYNOPSIS AND METEOROLOGICAL DETAILS.",
      "valid_time_from": "2025-04-03T22:55:00Z",
      "valid_time_to": "2025-04-04T00:55:00Z",
      "altitude": {
        "max_ft_msl": "24000"
      },
      "hazard": {
        "type": "CONVECTIVE",
        "severity": "SEV"
      },
      "airsigmet_type": "SIGMET",
      "area": [
        {
          "point": {
            "longitude": "-112.2788",
            "latitude": "44.7849"
          }
        },
        {
          "point": {
            "longitude": "-111.1551",
            "latitude": "43.7464"
          }
        },
        {
          "point": {
            "longitude": "-113.24",
            "latitude": "41.6065"
          }
        },
        {
          "point": {
            "longitude": "-115.0152",
            "latitude": "43.4"
          }
        },
        {
          "point": {
            "longitude": "-112.2788",
            "latitude": "44.7849"
          }
        }
      ]
    },
    {
      "raw_text": "WSUS33 KKCI 032255 SIGW CONVECTIVE SIGMET 26W VALID UNTIL 0055Z SD ND MT WY FROM 20SW ISN-50NW DPR-80SSW BIL-80SE HLN-20SW ISN AREA EMBD TS MOV FROM 24010KT. TOPS TO FL310. OUTLOOK VALID 040055-040455 AREA 1...FROM 30N MLP-50ESE HLN-50WSW MLS-30WSW CZI-DBS-BKE-30N MLP WST ISSUANCES POSS. REFER TO MOST RECENT ACUS01 KWNS FROM STORM PREDICTION CENTER FOR SYNOPSIS AND METEOROLOGICAL DETAILS. AREA 2...FROM 50E SLC-30SSE CHE-50NNE RSK-50NE PHX-30W PGS-50E SLC WST ISSUANCES POSS. REFER TO MOST RECENT ACUS01 KWNS FROM STORM PREDICTION CENTER FOR SYNOPSIS AND METEOROLOGICAL DETAILS. AREA 3...FROM 50NW FMG-30S OAL-40ESE CZQ-40NNW SAC-50NW FMG WST ISSUANCES POSS. REFER TO MOST RECENT ACUS01 KWNS FROM STORM PREDICTION CENTER FOR SYNOPSIS AND METEOROLOGICAL DETAILS. AREA 4...FROM 40ENE EHF-30WNW BZA-MZB-30E RZS-40ENE EHF WST ISSUANCES POSS. REFER TO MOST RECENT ACUS01 KWNS FROM STORM PREDICTION CENTER FOR SYNOPSIS AND METEOROLOGICAL DETAILS.",
      "valid_time_from": "2025-04-03T22:55:00Z",
      "valid_time_to": "2025-04-04T00:55:00Z",
      "altitude": {
        "max_ft_msl": "31000"
      },
      "hazard": {
        "type": "CONVECTIVE",
        "severity": "SEV"
      },
      "airsigmet_type": "SIGMET",
      "area": [
        {
          "point": {
            "longitude": "-103.9809",
            "latitude": "47.9444"
          }
        },
        {
          "point": {
            "longitude": "-102.5653",
            "latitude": "45.6676"
          }
        },
        {
          "point": {
            "longitude": "-109.3443",
            "latitude": "44.5794"
          }
        },
        {
          "point": {
            "longitude": "-110.6049",
            "latitude": "45.6619"
          }
        },
        {
          "point": {
            "longitude": "-103.9809",
            "latitude": "47.9444"
          }
        }
      ]
    },
    {
      "raw_text": "WSUS33 KKCI 032255 SIGW CONVECTIVE SIGMET 27W VALID UNTIL 0055Z CA FROM 60WNW FMG-70E EHF-30ESE EHF-50SE RBL-60WNW FMG AREA EMBD TS MOV LTL. TOPS TO FL260. OUTLOOK VALID 040055-040455 AREA 1...FROM 30N MLP-50ESE HLN-50WSW MLS-30WSW CZI-DBS-BKE-30N MLP WST ISSUANCES POSS. REFER TO MOST RECENT ACUS01 KWNS FROM STORM PREDICTION CENTER FOR SYNOPSIS AND METEOROLOGICAL DETAILS. AREA 2...FROM 50E SLC-30SSE CHE-50NNE RSK-50NE PHX-30W PGS-50E SLC WST ISSUANCES POSS. REFER TO MOST RECENT ACUS01 KWNS FROM STORM PREDICTION CENTER FOR SYNOPSIS AND METEOROLOGICAL DETAILS. AREA 3...FROM 50NW FMG-30S OAL-40ESE CZQ-40NNW SAC-50NW FMG WST ISSUANCES POSS. REFER TO MOST RECENT ACUS01 KWNS FROM STORM PREDICTION CENTER FOR SYNOPSIS AND METEOROLOGICAL DETAILS. AREA 4...FROM 40ENE EHF-30WNW BZA-MZB-30E RZS-40ENE EHF WST ISSUANCES POSS. REFER TO MOST RECENT ACUS01 KWNS FROM STORM PREDICTION CENTER FOR SYNOPSIS AND METEOROLOGICAL DETAILS.",
      "valid_time_from": "2025-04-03T22:55:00Z",
      "valid_time_to": "2025-04-04T00:55:00Z",
      "altitude": {
        "max_ft_msl": "26000"
      },
      "hazard": {
        "type": "CONVECTIVE",
        "severity": "SEV"
      },
      "airsigmet_type": "SIGMET",
      "area": [
        {
          "point": {
            "longitude": "-120.8609",
            "latitude": "39.9054"
          }
        },
        {
          "point": {
            "longitude": "-117.666",
            "latitude": "35.4715"
          }
        },
        {
          "point": {
            "longitude": "-118.5306",
            "latitude": "35.2862"
          }
        },
        {
          "point": {
            "longitude": "-121.4744",
            "latitude": "39.5067"
          }
        },
        {
          "point": {
            "longitude": "-120.8609",
            "latitude": "39.9054"
          }
        }
      ]
    },
    {
      "raw_text": "WSUS33 KKCI 032255 SIGW CONVECTIVE SIGMET 28W VALID UNTIL 0055Z CA AND CSTL WTRS FROM 40NNW RZS-50NE LAX-50E LAX-20SW RZS-40NNW RZS AREA EMBD TS MOV LTL. TOPS TO FL260. OUTLOOK VALID 040055-040455 AREA 1...FROM 30N MLP-50ESE HLN-50WSW MLS-30WSW CZI-DBS-BKE-30N MLP WST ISSUANCES POSS. REFER TO MOST RECENT ACUS01 KWNS FROM STORM PREDICTION CENTER FOR SYNOPSIS AND METEOROLOGICAL DETAILS. AREA 2...FROM 50E SLC-30SSE CHE-50NNE RSK-50NE PHX-30W PGS-50E SLC WST ISSUANCES POSS. REFER TO MOST RECENT ACUS01 KWNS FROM STORM PREDICTION CENTER FOR SYNOPSIS AND METEOROLOGICAL DETAILS. AREA 3...FROM 50NW FMG-30S OAL-40ESE CZQ-40NNW SAC-50NW FMG WST ISSUANCES POSS. REFER TO MOST RECENT ACUS01 KWNS FROM STORM PREDICTION CENTER FOR SYNOPSIS AND METEOROLOGICAL DETAILS. AREA 4...FROM 40ENE EHF-30WNW BZA-MZB-30E RZS-40ENE EHF WST ISSUANCES POSS. REFER TO MOST RECENT ACUS01 KWNS FROM STORM PREDICTION CENTER FOR SYNOPSIS AND METEOROLOGICAL DETAILS.",
      "valid_time_from": "2025-04-03T22:55:00Z",
      "valid_time_to": "2025-04-04T00:55:00Z",
      "altitude": {
        "max_ft_msl": "26000"
      },
      "hazard": {
        "type": "CONVECTIVE",
        "severity": "SEV"
      },
      "airsigmet_type": "SIGMET",
      "area": [
        {
          "point": {
            "longitude": "-120.081",
            "latitude": "35.1238"
          }
        },
        {
          "point": {
            "longitude": "-117.713",
            "latitude": "34.5187"
          }
        },
        {
          "point": {
            "longitude": "-117.4231",
            "latitude": "33.9259"
          }
        },
        {
          "point": {
            "longitude": "-120.0544",
            "latitude": "34.2746"
          }
        },
        {
          "point": {
            "longitude": "-120.081",
            "latitude": "35.1238"
          }
        }
      ]
    },
    {
      "raw_text": "WSUS33 KKCI 032255 SIGW CONVECTIVE SIGMET 29W VALID UNTIL 0055Z CA FROM 30SSW HEC-60W BZA-20ESE MZB-60SW HEC-30SSW HEC AREA EMBD TS MOV LTL. TOPS TO FL240. OUTLOOK VALID 040055-040455 AREA 1...FROM 30N MLP-50ESE HLN-50WSW MLS-30WSW CZI-DBS-BKE-30N MLP WST ISSUANCES POSS. REFER TO MOST RECENT ACUS01 KWNS FROM STORM PREDICTION CENTER FOR SYNOPSIS AND METEOROLOGICAL DETAILS. AREA 2...FROM 50E SLC-30SSE CHE-50NNE RSK-50NE PHX-30W PGS-50E SLC WST ISSUANCES POSS. REFER TO MOST RECENT ACUS01 KWNS FROM STORM PREDICTION CENTER FOR SYNOPSIS AND METEOROLOGICAL DETAILS. AREA 3...FROM 50NW FMG-30S OAL-40ESE CZQ-40NNW SAC-50NW FMG WST ISSUANCES POSS. REFER TO MOST RECENT ACUS01 KWNS FROM STORM PREDICTION CENTER FOR SYNOPSIS AND METEOROLOGICAL DETAILS. AREA 4...FROM 40ENE EHF-30WNW BZA-MZB-30E RZS-40ENE EHF WST ISSUANCES POSS. REFER TO MOST RECENT ACUS01 KWNS FROM STORM PREDICTION CENTER FOR SYNOPSIS AND METEOROLOGICAL DETAILS.",
      "valid_time_from": "2025-04-03T22:55:00Z",
      "valid_time_to": "2025-04-04T00:55:00Z",
      "altitude": {
        "max_ft_msl": "24000"
      },
      "hazard": {
        "type": "CONVECTIVE",
        "severity": "SEV"
      },
      "airsigmet_type": "SIGMET",
      "area": [
        {
          "point": {
            "longitude": "-116.6931",
            "latitude": "34.335"
          }
        },
        {
          "point": {
            "longitude": "-115.7858",
            "latitude": "32.7644"
          }
        },
        {
          "point": {
            "longitude": "-116.8653",
            "latitude": "32.6523"
          }
        },
        {
          "point": {
            "longitude": "-117.3114",
            "latitude": "34.092"
          }
        },
        {
          "point": {
            "longitude": "-116.6931",
            "latitude": "34.335"
          }
        }
      ]
    },
    {
      "raw_text": "WSUS33 KKCI 032255 SIGW CONVECTIVE SIGMET 30W VALID UNTIL 0055Z AZ UT NV CA FROM 30NW HVE-40NE INW-30WSW PHX-20E HEC-60NE BTY-30NW HVE AREA EMBD TS MOV LTL. TOPS TO FL310. OUTLOOK VALID 040055-040455 AREA 1...FROM 30N MLP-50ESE HLN-50WSW MLS-30WSW CZI-DBS-BKE-30N MLP WST ISSUANCES POSS. REFER TO MOST RECENT ACUS01 KWNS FROM STORM PREDICTION CENTER FOR SYNOPSIS AND METEOROLOGICAL DETAILS. AREA 2...FROM 50E SLC-30SSE CHE-50NNE RSK-50NE PHX-30W PGS-50E SLC WST ISSUANCES POSS. REFER TO MOST RECENT ACUS01 KWNS FROM STORM PREDICTION CENTER FOR SYNOPSIS AND METEOROLOGICAL DETAILS. AREA 3...FROM 50NW FMG-30S OAL-40ESE CZQ-40NNW SAC-50NW FMG WST ISSUANCES POSS. REFER TO MOST RECENT ACUS01 KWNS FROM STORM PREDICTION CENTER FOR SYNOPSIS AND METEOROLOGICAL DETAILS. AREA 4...FROM 40ENE EHF-30WNW BZA-MZB-30E RZS-40ENE EHF WST ISSUANCES POSS. REFER TO MOST RECENT ACUS01 KWNS FROM STORM PREDICTION CENTER FOR SYNOPSIS AND METEOROLOGICAL DETAILS.",
      "valid_time_from": "2025-04-03T22:55:00Z",
      "valid_time_to": "2025-04-04T00:55:00Z",
      "altitude": {
        "max_ft_msl": "31000"
      },
      "hazard": {
        "type": "CONVECTIVE",
        "severity": "SEV"
      },
      "airsigmet_type": "SIGMET",
      "area": [
        {
          "point": {
            "longitude": "-111.1563",
            "latitude": "38.7748"
          }
        },
        {
          "point": {
            "longitude": "-110.2224",
            "latitude": "35.5287"
          }
        },
        {
          "point": {
            "longitude": "-112.5757",
            "latitude": "33.2362"
          }
        },
        {
          "point": {
            "longitude": "-116.0552",
            "latitude": "34.7993"
          }
        },
        {
          "point": {
            "longitude": "-115.8613",
            "latitude": "37.5018"
          }
        },
        {
          "point": {
            "longitude": "-111.1563",
            "latitude": "38.7748"
          }
        }
      ]
    },
    {
      "raw_text": "WSUS33 KKCI 032255 SIGW CONVECTIVE SIGMET 31W VALID UNTIL 0055Z CO WY UT FROM 50ENE SLC-30SW AKO-40WNW TBE-40ESE DTA-50ENE SLC AREA EMBD TS MOV LTL. TOPS TO FL330. OUTLOOK VALID 040055-040455 AREA 1...FROM 30N MLP-50ESE HLN-50WSW MLS-30WSW CZI-DBS-BKE-30N MLP WST ISSUANCES POSS. REFER TO MOST RECENT ACUS01 KWNS FROM STORM PREDICTION CENTER FOR SYNOPSIS AND METEOROLOGICAL DETAILS. AREA 2...FROM 50E SLC-30SSE CHE-50NNE RSK-50NE PHX-30W PGS-50E SLC WST ISSUANCES POSS. REFER TO MOST RECENT ACUS01 KWNS FROM STORM PREDICTION CENTER FOR SYNOPSIS AND METEOROLOGICAL DETAILS. AREA 3...FROM 50NW FMG-30S OAL-40ESE CZQ-40NNW SAC-50NW FMG WST ISSUANCES POSS. REFER TO MOST RECENT ACUS01 KWNS FROM STORM PREDICTION CENTER FOR SYNOPSIS AND METEOROLOGICAL DETAILS. AREA 4...FROM 40ENE EHF-30WNW BZA-MZB-30E RZS-40ENE EHF WST ISSUANCES POSS. REFER TO MOST RECENT ACUS01 KWNS FROM STORM PREDICTION CENTER FOR SYNOPSIS AND METEOROLOGICAL DETAILS.",
      "valid_time_from": "2025-04-03T22:55:00Z",
      "valid_time_to": "2025-04-04T00:55:00Z",
      "altitude": {
        "max_ft_msl": "33000"
      },
      "hazard": {
        "type": "CONVECTIVE",
        "severity": "SEV"
      },
      "airsigmet_type": "SIGMET",
      "area": [
        {
          "point": {
            "longitude": "-110.9547",
            "latitude": "41.1652"
          }
        },
        {
          "point": {
            "longitude": "-103.643",
            "latitude": "39.8034"
          }
        },
        {
          "point": {
            "longitude": "-104.3744",
            "latitude": "37.5219"
          }
        },
        {
          "point": {
            "longitude": "-111.7192",
            "latitude": "39.0429"
          }
        },
        {
          "point": {
            "longitude": "-110.9547",
            "latitude": "41.1652"
          }
        }
      ]
    }
  ]
}