{
  "source": {
    "name": "Airframes Project",
    "url": "https://github.com/airframesio",
    "email": "kevin@airframes.io"
  },
  "attribution": {
    "name": "NOAA NWS Aviation Weather Center",
    "url": "https://aviationweather.gov/data/cache/airsigmets.cache.xml.gz"
  },
  "resource_type": "airsigmets",
  "count": 41,
  "airsigmets": [
    {
      "raw_text": "WSUS32 KKCI 291755 SIGC CONVECTIVE SIGMET 48C VALID UNTIL 1955Z MS LA TX AND CSTL WTRS FROM 40WSW MHZ-50E HRV-50S LEV-90SE PSX-30ESE PSX-40WSW MHZ AREA EMBD TS MOV FROM 28035KT. TOPS ABV FL450. REF INTL SIGMET ECHO SERIES. OUTLOOK VALID 291955-292355 AREA 1...FROM 40NW GIJ-BNA-210S CEW-80SE LEV-120SSW LCH-30SW FSM-40S STL-40NW GIJ WST ISSUANCES EXPD. REFER TO MOST RECENT ACUS01 KWNS FROM STORM PREDICTION CENTER FOR SYNOPSIS AND METEOROLOGICAL DETAILS. AREA 2...FROM 60SSW YQT-70N SAW-50WNW MKG-40NE DLL-40NNE EAU-60SSW YQT WST ISSUANCES EXPD. REFER TO MOST RECENT ACUS01 KWNS FROM STORM PREDICTION CENTER FOR SYNOPSIS AND METEOROLOGICAL DETAILS.",
      "valid_time_from": "2024-04-29T17:55:00Z",
      "valid_time_to": "2024-04-29T19:55:00Z",
      "altitude": {
        "max_ft_msl": "45000"
      },
      "hazard": {
        "type": "CONVECTIVE",
        "severity": "LT-MOD"
      },
      "airsigmet_type": "SIGMET",
      "area": [
        {
          "point": {
            "longitude": "-90.8256",
            "latitude": "32.1735"
          }
        },
        {
          "point": {
            "longitude": "-89.0368",
            "latitude": "29.8465"
          }
        },
        {
          "point": {
            "longitude": "-90.1",
            "latitude": "28.3446"
          }
        },
        {
          "point": {
            "longitude": "-95.112",
            "latitude": "27.6939"
          }
        },
        {
          "point": {
            "longitude": "-95.7808",
            "latitude": "28.5665"
          }
        },
        {
          "point": {
            "longitude": "-90.8256",
            "latitude": "32.1735"
          }
        }
      ]
    },
    {
      "raw_text": "WSUS32 KKCI 291755 SIGC CONVECTIVE SIGMET 49C VALID UNTIL 1955Z MS FROM 40ENE SQS-20NW IGB-30NNW SJI-50W SJI-30ESE MCB-40ENE SQS AREA EMBD TS MOV FROM 24035KT. TOPS TO FL380. OUTLOOK VALID 291955-292355 AREA 1...FROM 40NW GIJ-BNA-210S CEW-80SE LEV-120SSW LCH-30SW FSM-40S STL-40NW GIJ WST ISSUANCES EXPD. REFER TO MOST RECENT ACUS01 KWNS FROM STORM PREDICTION CENTER FOR SYNOPSIS AND METEOROLOGICAL DETAILS. AREA 2...FROM 60SSW YQT-70N SAW-50WNW MKG-40NE DLL-40NNE EAU-60SSW YQT WST ISSUANCES EXPD. REFER TO MOST RECENT ACUS01 KWNS FROM STORM PREDICTION CENTER FOR SYNOPSIS AND METEOROLOGICAL DETAILS.",
      "valid_time_from": "2024-04-29T17:55:00Z",
      "valid_time_to": "2024-04-29T19:55:00Z",
      "altitude": {
        "max_ft_msl": "38000"
      },
      "hazard": {
        "type": "CONVECTIVE",
        "severity": "LT-MOD"
      },
      "airsigmet_type": "SIGMET",
      "area": [
        {
          "point": {
            "longitude": "-89.5417",
            "latitude": "33.7122"
          }
        },
        {
          "point": {
            "longitude": "-88.8025",
            "latitude": "33.7147"
          }
        },
        {
          "point": {
            "longitude": "-88.585",
            "latitude": "31.1946"
          }
        },
        {
          "point": {
            "longitude": "-89.3319",
            "latitude": "30.7264"
          }
        },
        {
          "point": {
            "longitude": "-89.7172",
            "latitude": "31.1063"
          }
        },
        {
          "point": {
            "longitude": "-89.5417",
            "latitude": "33.7122"
          }
        }
      ]
    },
    {
      "raw_text": "WSUS32 KKCI 291755 SIGC CONVECTIVE SIGMET 50C VALID UNTIL 1955Z TN KY IN IL MO FROM 20NW BVT-20ENE BVT-40S TTH-30NE DYR-40N DYR-20NW BVT AREA EMBD TS MOV FROM 23035KT. TOPS TO FL340. OUTLOOK VALID 291955-292355 AREA 1...FROM 40NW GIJ-BNA-210S CEW-80SE LEV-120SSW LCH-30SW FSM-40S STL-40NW GIJ WST ISSUANCES EXPD. REFER TO MOST RECENT ACUS01 KWNS FROM STORM PREDICTION CENTER FOR SYNOPSIS AND METEOROLOGICAL DETAILS. AREA 2...FROM 60SSW YQT-70N SAW-50WNW MKG-40NE DLL-40NNE EAU-60SSW YQT WST ISSUANCES EXPD. REFER TO MOST RECENT ACUS01 KWNS FROM STORM PREDICTION CENTER FOR SYNOPSIS AND METEOROLOGICAL DETAILS.",
      "valid_time_from": "2024-04-29T17:55:00Z",
      "valid_time_to": "2024-04-29T19:55:00Z",
      "altitude": {
        "max_ft_msl": "34000"
      },
      "hazard": {
        "type": "CONVECTIVE",
        "severity": "LT-MOD"
      },
      "airsigmet_type": "SIGMET",
      "area": [
        {
          "point": {
            "longitude": "-87.3804",
            "latitude": "40.7946"
          }
        },
        {
          "point": {
            "longitude": "-86.665",
            "latitude": "40.6865"
          }
        },
        {
          "point": {
            "longitude": "-87.25",
            "latitude": "38.8252"
          }
        },
        {
          "point": {
            "longitude": "-88.8782",
            "latitude": "36.3749"
          }
        },
        {
          "point": {
            "longitude": "-89.32",
            "latitude": "36.6848"
          }
        },
        {
          "point": {
            "longitude": "-87.3804",
            "latitude": "40.7946"
          }
        }
      ]
    },
    {
      "raw_text": "WSUS33 KKCI 291755 SIGW CONVECTIVE SIGMET...NONE OUTLOOK VALID 291955-292355 FROM 50SSE YXC-60ESE MLP-LWT-40NE BPI-MLD-DBS-30SSW EUG-40ESE TOU-50SSE YXC WST ISSUANCES EXPD. REFER TO MOST RECENT ACUS01 KWNS FROM STORM PREDICTION CENTER FOR SYNOPSIS AND METEOROLOGICAL DETAILS.",
      "valid_time_from": "2024-04-29T17:55:00Z",
      "valid_time_to": "2024-04-29T19:55:00Z",
      "hazard": {
        "type": "CONVECTIVE"
      },
      "airsigmet_type": "SIGMET",
      "area": [
        {
          "point": {
            "longitude": "-122.77",
            "latitude": "49"
          }
        },
        {
          "point": {
            "longitude": "-123.12",
            "latitude": "48.96"
          }
        },
        {
          "point": {
            "longitude": "-123.02",
            "latitude": "48.6"
          }
        },
        {
          "point": {
            "longitude": "-123.16",
            "latitude": "48.3"
          }
        },
        {
          "point": {
            "longitude": "-123.69",
            "latitude": "48.2"
          }
        },
        {
          "point": {
            "longitude": "-124.35",
            "latitude": "48.36"
          }
        },
        {
          "point": {
            "longitude": "-124.73",
            "latitude": "48.39"
          }
        },
        {
          "point": {
            "longitude": "-124.72",
            "latitude": "48.38"
          }
        },
        {
          "point": {
            "longitude": "-125",
            "latitude": "48.49"
          }
        },
        {
          "point": {
            "longitude": "-125.96",
            "latitude": "48.4"
          }
        },
        {
          "point": {
            "longitude": "-127.03",
            "latitude": "48.41"
          }
        },
        {
          "point": {
            "longitude": "-128.01",
            "latitude": "48.33"
          }
        },
        {
          "point": {
            "longitude": "-127.49",
            "latitude": "47.48"
          }
        },
        {
          "point": {
            "longitude": "-127.01",
            "latitude": "46"
          }
        },
        {
          "point": {
            "longitude": "-126.52",
            "latitude": "44.98"
          }
        },
        {
          "point": {
            "longitude": "-126.51",
            "latitude": "44.01"
          }
        },
        {
          "point": {
            "longitude": "-126.72",
            "latitude": "42.97"
          }
        },
        {
          "point": {
            "longitude": "-127",
            "latitude": "40.01"
          }
        },
        {
          "point": {
            "longitude": "-123.01",
            "latitude": "34"
          }
        },
        {
          "point": {
            "longitude": "-122.01",
            "latitude": "32.99"
          }
        },
        {
          "point": {
            "longitude": "-121.66",
            "latitude": "31.99"
          }
        },
        {
          "point": {
            "longitude": "-121.01",
            "latitude": "30.98"
          }
        },
        {
          "point": {
            "longitude": "-120.65",
            "latitude": "30.67"
          }
        },
        {
          "point": {
            "longitude": "-120",
            "latitude": "31.1"
          }
        },
        {
          "point": {
            "longitude": "-118.97",
            "latitude": "31.62"
          }
        },
        {
          "point": {
            "longitude": "-117.1",
            "latitude": "32.4"
          }
        },
        {
          "point": {
            "longitude": "-117.09",
            "latitude": "32.4"
          }
        },
        {
          "point": {
            "longitude": "-117.12",
            "latitude": "32.53"
          }
        },
        {
          "point": {
            "longitude": "-114.72",
            "latitude": "32.72"
          }
        },
        {
          "point": {
            "longitude": "-114.81",
            "latitude": "32.5"
          }
        },
        {
          "point": {
            "longitude": "-111.08",
            "latitude": "31.33"
          }
        },
        {
          "point": {
            "longitude": "-108.2",
            "latitude": "31.33"
          }
        },
        {
          "point": {
            "longitude": "-108.2",
            "latitude": "31.78"
          }
        },
        {
          "point": {
            "longitude": "-107",
            "latitude": "31.78"
          }
        },
        {
          "point": {
            "longitude": "-107",
            "latitude": "49"
          }
        },
        {
          "point": {
            "longitude": "-122.77",
            "latitude": "49"
          }
        }
      ],
      "altitude": {
      }
    },
    {
      "raw_text": "WSUS31 KKCI 291755 SIGE CONVECTIVE SIGMET...NONE OUTLOOK VALID 291955-292355 AREA 1...FROM 40SSE SSM-60NNE ASP-ECK-DXO-40SW CLE-BNA-40NW GIJ-40SSE SSM WST ISSUANCES EXPD. REFER TO MOST RECENT ACUS01 KWNS FROM STORM PREDICTION CENTER FOR SYNOPSIS AND METEOROLOGICAL DETAILS. AREA 2...FROM ALB-30W BOS-30WNW CYN-40NNW ETX-ERI-BUF-60WSW SYR-ALB WST ISSUANCES EXPD. REFER TO MOST RECENT ACUS01 KWNS FROM STORM PREDICTION CENTER FOR SYNOPSIS AND METEOROLOGICAL DETAILS.",
      "valid_time_from": "2024-04-29T17:55:00Z",
      "valid_time_to": "2024-04-29T19:55:00Z",
      "hazard": {
        "type": "CONVECTIVE"
      },
      "airsigmet_type": "SIGMET",
      "area": [
        {
          "point": {
            "longitude": "-87",
            "latitude": "27.48"
          }
        },
        {
          "point": {
            "longitude": "-84.26",
            "latitude": "27.48"
          }
        },
        {
          "point": {
            "longitude": "-83.01",
            "latitude": "24"
          }
        },
        {
          "point": {
            "longitude": "-78.66",
            "latitude": "24"
          }
        },
        {
          "point": {
            "longitude": "-79",
            "latitude": "24.2"
          }
        },
        {
          "point": {
            "longitude": "-78.99",
            "latitude": "27"
          }
        },
        {
          "point": {
            "longitude": "-77",
            "latitude": "27.02"
          }
        },
        {
          "point": {
            "longitude": "-77",
            "latitude": "33"
          }
        },
        {
          "point": {
            "longitude": "-76.5",
            "latitude": "32.51"
          }
        },
        {
          "point": {
            "longitude": "-72.49",
            "latitude": "35.02"
          }
        },
        {
          "point": {
            "longitude": "-72.49",
            "latitude": "37.51"
          }
        },
        {
          "point": {
            "longitude": "-70.96",
            "latitude": "37.51"
          }
        },
        {
          "point": {
            "longitude": "-69.98",
            "latitude": "38.27"
          }
        },
        {
          "point": {
            "longitude": "-67",
            "latitude": "38.99"
          }
        },
        {
          "point": {
            "longitude": "-67.01",
            "latitude": "44.97"
          }
        },
        {
          "point": {
            "longitude": "-67.17",
            "latitude": "45.16"
          }
        },
        {
          "point": {
            "longitude": "-67.27",
            "latitude": "45.2"
          }
        },
        {
          "point": {
            "longitude": "-67.3",
            "latitude": "45.17"
          }
        },
        {
          "point": {
            "longitude": "-67.35",
            "latitude": "45.15"
          }
        },
        {
          "point": {
            "longitude": "-67.47",
            "latitude": "45.26"
          }
        },
        {
          "point": {
            "longitude": "-67.42",
            "latitude": "45.4"
          }
        },
        {
          "point": {
            "longitude": "-67.49",
            "latitude": "45.47"
          }
        },
        {
          "point": {
            "longitude": "-67.41",
            "latitude": "45.6"
          }
        },
        {
          "point": {
            "longitude": "-67.54",
            "latitude": "45.6"
          }
        },
        {
          "point": {
            "longitude": "-67.75",
            "latitude": "45.68"
          }
        },
        {
          "point": {
            "longitude": "-67.78",
            "latitude": "45.86"
          }
        },
        {
          "point": {
            "longitude": "-67.78",
            "latitude": "47.06"
          }
        },
        {
          "point": {
            "longitude": "-68.28",
            "latitude": "47.37"
          }
        },
        {
          "point": {
            "longitude": "-68.44",
            "latitude": "47.3"
          }
        },
        {
          "point": {
            "longitude": "-68.86",
            "latitude": "47.19"
          }
        },
        {
          "point": {
            "longitude": "-69.02",
            "latitude": "47.26"
          }
        },
        {
          "point": {
            "longitude": "-69.02",
            "latitude": "47.44"
          }
        },
        {
          "point": {
            "longitude": "-69.2",
            "latitude": "47.48"
          }
        },
        {
          "point": {
            "longitude": "-69.97",
            "latitude": "46.72"
          }
        },
        {
          "point": {
            "longitude": "-70.02",
            "latitude": "46.45"
          }
        },
        {
          "point": {
            "longitude": "-70.02",
            "latitude": "46.47"
          }
        },
        {
          "point": {
            "longitude": "-70.24",
            "latitude": "46.29"
          }
        },
        {
          "point": {
            "longitude": "-70.24",
            "latitude": "46.11"
          }
        },
        {
          "point": {
            "longitude": "-70.31",
            "latitude": "46.02"
          }
        },
        {
          "point": {
            "longitude": "-70.24",
            "latitude": "45.93"
          }
        },
        {
          "point": {
            "longitude": "-70.35",
            "latitude": "45.78"
          }
        },
        {
          "point": {
            "longitude": "-70.72",
            "latitude": "45.55"
          }
        },
        {
          "point": {
            "longitude": "-70.63",
            "latitude": "45.44"
          }
        },
        {
          "point": {
            "longitude": "-70.79",
            "latitude": "45.41"
          }
        },
        {
          "point": {
            "longitude": "-70.85",
            "latitude": "45.26"
          }
        },
        {
          "point": {
            "longitude": "-70.94",
            "latitude": "45.34"
          }
        },
        {
          "point": {
            "longitude": "-71.13",
            "latitude": "45.24"
          }
        },
        {
          "point": {
            "longitude": "-71.31",
            "latitude": "45.29"
          }
        },
        {
          "point": {
            "longitude": "-71.55",
            "latitude": "45"
          }
        },
        {
          "point": {
            "longitude": "-74.87",
            "latitude": "44.98"
          }
        },
        {
          "point": {
            "longitude": "-76.29",
            "latitude": "44.22"
          }
        },
        {
          "point": {
            "longitude": "-76.87",
            "latitude": "43.68"
          }
        },
        {
          "point": {
            "longitude": "-78.2",
            "latitude": "43.61"
          }
        },
        {
          "point": {
            "longitude": "-78.85",
            "latitude": "43.57"
          }
        },
        {
          "point": {
            "longitude": "-79.07",
            "latitude": "43.23"
          }
        },
        {
          "point": {
            "longitude": "-79.03",
            "latitude": "43.04"
          }
        },
        {
          "point": {
            "longitude": "-78.87",
            "latitude": "42.89"
          }
        },
        {
          "point": {
            "longitude": "-79.92",
            "latitude": "42.5"
          }
        },
        {
          "point": {
            "longitude": "-81.98",
            "latitude": "41.89"
          }
        },
        {
          "point": {
            "longitude": "-82.66",
            "latitude": "41.76"
          }
        },
        {
          "point": {
            "longitude": "-83.48",
            "latitude": "41.73"
          }
        },
        {
          "point": {
            "longitude": "-83.43",
            "latitude": "41.78"
          }
        },
        {
          "point": {
            "longitude": "-83.4",
            "latitude": "41.85"
          }
        },
        {
          "point": {
            "longitude": "-83.33",
            "latitude": "41.88"
          }
        },
        {
          "point": {
            "longitude": "-83.31",
            "latitude": "41.95"
          }
        },
        {
          "point": {
            "longitude": "-83.26",
            "latitude": "41.93"
          }
        },
        {
          "point": {
            "longitude": "-83.19",
            "latitude": "42.01"
          }
        },
        {
          "point": {
            "longitude": "-83.14",
            "latitude": "42.12"
          }
        },
        {
          "point": {
            "longitude": "-83.13",
            "latitude": "42.22"
          }
        },
        {
          "point": {
            "longitude": "-83.04",
            "latitude": "42.32"
          }
        },
        {
          "point": {
            "longitude": "-82.81",
            "latitude": "42.42"
          }
        },
        {
          "point": {
            "longitude": "-82.68",
            "latitude": "42.5"
          }
        },
        {
          "point": {
            "longitude": "-82.63",
            "latitude": "42.55"
          }
        },
        {
          "point": {
            "longitude": "-82.51",
            "latitude": "42.62"
          }
        },
        {
          "point": {
            "longitude": "-82.47",
            "latitude": "42.83"
          }
        },
        {
          "point": {
            "longitude": "-82.41",
            "latitude": "43.01"
          }
        },
        {
          "point": {
            "longitude": "-82.29",
            "latitude": "43.16"
          }
        },
        {
          "point": {
            "longitude": "-82.14",
            "latitude": "43.96"
          }
        },
        {
          "point": {
            "longitude": "-82.39",
            "latitude": "44.93"
          }
        },
        {
          "point": {
            "longitude": "-83.34",
            "latitude": "45.76"
          }
        },
        {
          "point": {
            "longitude": "-85.08",
            "latitude": "46.96"
          }
        },
        {
          "point": {
            "longitude": "-86.44",
            "latitude": "47.49"
          }
        },
        {
          "point": {
            "longitude": "-87",
            "latitude": "47.62"
          }
        },
        {
          "point": {
            "longitude": "-87",
            "latitude": "27.48"
          }
        }
      ],
      "altitude": {
      }
    },
    {
      "raw_text": "WAUS44 KKCI 291445 DFWT WA 291445 AIRMET TANGO UPDT 2 FOR TURB VALID UNTIL 292100 AIRMET TURB...OK TX AR TN LA MS AL NE KS IA MO IL IN KY FROM 30WNW DSM TO 40S HNN TO 40E VXV TO GQO TO 50SSE LGC TO 20W TLH TO SJI TO 40SSE IGB TO 40NE MLU TO 50E CWK TO 60ENE TTT TO 50ESE SLN TO 30WNW DSM MOD TURB BTN FL200 AND FL430. CONDS CONTG BYD 21Z THRU 03Z. OTLK VALID 2100-0300Z...TURB OK AR TN LA MS AL KS IA MO IL IN KY BOUNDED BY 40ESE DSM-CVG-20SSE BKW-40NW HMV-60W VXV-30SE MSL- 40NE HRV-20S LSU-20ESE TXK-20NW FSM-20ESE OSW-40NE MCI-30W IRK- 40ESE DSM MOD TURB BTN FL200 AND FL430. CONDS CONTG THRU 03Z.",
      "valid_time_from": "2024-04-29T14:45:00Z",
      "valid_time_to": "2024-04-29T21:00:00Z",
      "altitude": {
        "min_ft_msl": "20000",
        "max_ft_msl": "43000"
      },
      "hazard": {
        "type": "TURB",
        "severity": "MOD"
      },
      "airsigmet_type": "AIRMET",
      "area": [
        {
          "point": {
            "longitude": "-94.2718",
            "latitude": "41.6308"
          }
        },
        {
          "point": {
            "longitude": "-82.03",
            "latitude": "38.0852"
          }
        },
        {
          "point": {
            "longitude": "-83.0694",
            "latitude": "35.8972"
          }
        },
        {
          "point": {
            "longitude": "-85.15",
            "latitude": "34.96"
          }
        },
        {
          "point": {
            "longitude": "-84.8319",
            "latitude": "32.2776"
          }
        },
        {
          "point": {
            "longitude": "-84.756",
            "latitude": "30.5594"
          }
        },
        {
          "point": {
            "longitude": "-88.36",
            "latitude": "30.73"
          }
        },
        {
          "point": {
            "longitude": "-88.2171",
            "latitude": "32.8655"
          }
        },
        {
          "point": {
            "longitude": "-91.4696",
            "latitude": "32.9888"
          }
        },
        {
          "point": {
            "longitude": "-96.5616",
            "latitude": "30.3764"
          }
        },
        {
          "point": {
            "longitude": "-95.9385",
            "latitude": "33.2468"
          }
        },
        {
          "point": {
            "longitude": "-96.6323",
            "latitude": "38.6061"
          }
        },
        {
          "point": {
            "longitude": "-94.2718",
            "latitude": "41.6308"
          }
        }
      ]
    },
    {
      "raw_text": "WAUS45 KKCI 291445 SLCT WA 291445 AIRMET TANGO UPDT 2 FOR TURB AND STG SFC WNDS VALID UNTIL 292100 AIRMET TURB...WY CO FROM 30NNW LAR TO CYS TO 20N DEN TO 60SSW DEN TO 40ESE DBL TO 50W LAR TO 30NNW LAR MOD TURB BLW FL180. CONDS ENDG 15-18Z. OTLK VALID 2100-0300Z AREA 1...TURB ID MT WA OR BOUNDED BY 60SSW YDC-40NW GEG-40N MLP-50W GTF-40SSW DLN-20SE BOI- 30NNE REO-70SSW YKM-20ESE SEA-60SSW YDC MOD TURB BTN FL180 AND FL260. CONDS CONTG THRU 03Z. AREA 2...TURB ID MT WA OR BOUNDED BY 20SE FCA-30NW DLN-40SW DNJ-20SSW PDT-20SW GEG-20NNW MLP-20SE FCA MOD TURB BLW 140. CONDS CONTG THRU 03Z. AREA 3...TURB WY UT CO BOUNDED BY 40ESE CZI-40N CYS-30N DEN-50SSW DEN-20E HBU-30W HBU- 20WNW JNC-40ESE MTU-40ESE CZI MOD TURB BLW FL180. CONDS DVLPG 00-03Z. CONDS CONTG THRU 03Z. AREA 4...TURB ID MT WY NV UT CO BOUNDED BY 60WSW YQL-60W HVR-40ESE GTF-50SSE LWT-40E SHR-40ESE CZI-40ESE MTU-30NW HVE-30S DTA-50W BVL-40SW DNJ-30NW DLN-60WSW YQL MOD TURB BLW 160. CONDS CONTG THRU 03Z.",
      "valid_time_from": "2024-04-29T14:45:00Z",
      "valid_time_to": "2024-04-29T21:00:00Z",
      "altitude": {
        "min_ft_msl": "0",
        "max_ft_msl": "18000"
      },
      "hazard": {
        "type": "TURB",
        "severity": "MOD"
      },
      "airsigmet_type": "AIRMET",
      "area": [
        {
          "point": {
            "longitude": "-105.9782",
            "latitude": "41.7945"
          }
        },
        {
          "point": {
            "longitude": "-104.77",
            "latitude": "41.21"
          }
        },
        {
          "point": {
            "longitude": "-104.66",
            "latitude": "40.1424"
          }
        },
        {
          "point": {
            "longitude": "-105.1502",
            "latitude": "38.8877"
          }
        },
        {
          "point": {
            "longitude": "-106.1077",
            "latitude": "39.1829"
          }
        },
        {
          "point": {
            "longitude": "-106.8325",
            "latitude": "41.3246"
          }
        },
        {
          "point": {
            "longitude": "-105.9782",
            "latitude": "41.7945"
          }
        }
      ]
    },
    {
      "raw_text": "WAUS45 KKCI 291445 SLCT WA 291445 AIRMET TANGO UPDT 2 FOR TURB AND STG SFC WNDS VALID UNTIL 292100 AIRMET STG SFC WNDS...WY FROM 40WNW BOY TO 60S BOY TO 20S OCS TO 30SE JAC TO 40WNW BOY SUSTAINED SURFACE WINDS GTR THAN 30KT EXP. CONDS DVLPG 18-21Z. CONDS CONTG BYD 21Z ENDG 21-00Z. OTLK VALID 2100-0300Z AREA 1...TURB ID MT WA OR BOUNDED BY 60SSW YDC-40NW GEG-40N MLP-50W GTF-40SSW DLN-20SE BOI- 30NNE REO-70SSW YKM-20ESE SEA-60SSW YDC MOD TURB BTN FL180 AND FL260. CONDS CONTG THRU 03Z. AREA 2...TURB ID MT WA OR BOUNDED BY 20SE FCA-30NW DLN-40SW DNJ-20SSW PDT-20SW GEG-20NNW MLP-20SE FCA MOD TURB BLW 140. CONDS CONTG THRU 03Z. AREA 3...TURB WY UT CO BOUNDED BY 40ESE CZI-40N CYS-30N DEN-50SSW DEN-20E HBU-30W HBU- 20WNW JNC-40ESE MTU-40ESE CZI MOD TURB BLW FL180. CONDS DVLPG 00-03Z. CONDS CONTG THRU 03Z. AREA 4...TURB ID MT WY NV UT CO BOUNDED BY 60WSW YQL-60W HVR-40ESE GTF-50SSE LWT-40E SHR-40ESE CZI-40ESE MTU-30NW HVE-30S DTA-50W BVL-40SW DNJ-30NW DLN-60WSW YQL MOD TURB BLW 160. CONDS CONTG THRU 03Z.",
      "valid_time_from": "2024-04-29T14:45:00Z",
      "valid_time_to": "2024-04-29T21:00:00Z",
      "hazard": {
        "type": "TURB",
        "severity": "0"
      },
      "airsigmet_type": "AIRMET",
      "area": [
        {
          "point": {
            "longitude": "-109.1497",
            "latitude": "43.7113"
          }
        },
        {
          "point": {
            "longitude": "-108.3",
            "latitude": "42.4629"
          }
        },
        {
          "point": {
            "longitude": "-109.02",
            "latitude": "41.2576"
          }
        },
        {
          "point": {
            "longitude": "-110.2415",
            "latitude": "43.2632"
          }
        },
        {
          "point": {
            "longitude": "-109.1497",
            "latitude": "43.7113"
          }
        }
      ],
      "altitude": {
      }
    },
    {
      "raw_text": "WAUS45 KKCI 291445 SLCT WA 291445 AIRMET TANGO UPDT 2 FOR TURB AND STG SFC WNDS VALID UNTIL 292100 AIRMET STG SFC WNDS...ID MT FROM 20NNE DLN TO 30SSE DBS TO 30NW PIH TO 60N TWF TO 30WNW LKT TO 20NNE DLN SUSTAINED SURFACE WINDS GTR THAN 30KT EXP. CONDS DVLPG 18-21Z. CONDS CONTG BYD 21Z THRU 03Z. OTLK VALID 2100-0300Z AREA 1...TURB ID MT WA OR BOUNDED BY 60SSW YDC-40NW GEG-40N MLP-50W GTF-40SSW DLN-20SE BOI- 30NNE REO-70SSW YKM-20ESE SEA-60SSW YDC MOD TURB BTN FL180 AND FL260. CONDS CONTG THRU 03Z. AREA 2...TURB ID MT WA OR BOUNDED BY 20SE FCA-30NW DLN-40SW DNJ-20SSW PDT-20SW GEG-20NNW MLP-20SE FCA MOD TURB BLW 140. CONDS CONTG THRU 03Z. AREA 3...TURB WY UT CO BOUNDED BY 40ESE CZI-40N CYS-30N DEN-50SSW DEN-20E HBU-30W HBU- 20WNW JNC-40ESE MTU-40ESE CZI MOD TURB BLW FL180. CONDS DVLPG 00-03Z. CONDS CONTG THRU 03Z. AREA 4...TURB ID MT WY NV UT CO BOUNDED BY 60WSW YQL-60W HVR-40ESE GTF-50SSE LWT-40E SHR-40ESE CZI-40ESE MTU-30NW HVE-30S DTA-50W BVL-40SW DNJ-30NW DLN-60WSW YQL MOD TURB BLW 160. CONDS CONTG THRU 03Z.",
      "valid_time_from": "2024-04-29T14:45:00Z",
      "valid_time_to": "2024-04-29T21:00:00Z",
      "hazard": {
        "type": "TURB",
        "severity": "0"
      },
      "airsigmet_type": "AIRMET",
      "area": [
        {
          "point": {
            "longitude": "-112.3683",
            "latitude": "45.5569"
          }
        },
        {
          "point": {
            "longitude": "-111.9441",
            "latitude": "43.6249"
          }
        },
        {
          "point": {
            "longitude": "-113.1382",
            "latitude": "43.2247"
          }
        },
        {
          "point": {
            "longitude": "-114.49",
            "latitude": "43.4771"
          }
        },
        {
          "point": {
            "longitude": "-114.7397",
            "latitude": "45.2106"
          }
        },
        {
          "point": {
            "longitude": "-112.3683",
            "latitude": "45.5569"
          }
        }
      ],
      "altitude": {
      }
    },
    {
      "raw_text": "WAUS45 KKCI 291445 SLCT WA 291445 AIRMET TANGO UPDT 2 FOR TURB AND STG SFC WNDS VALID UNTIL 292100 AIRMET STG SFC WNDS...NV UT FROM 40SSE TWF TO 30WSW BVL TO 40ENE ELY TO 20SE ELY TO 40SE BAM TO 50NNE BAM TO 40SSE TWF SUSTAINED SURFACE WINDS GTR THAN 30KT EXP. CONDS DVLPG 18-21Z. CONDS CONTG BYD 21Z ENDG 00-03Z. OTLK VALID 2100-0300Z AREA 1...TURB ID MT WA OR BOUNDED BY 60SSW YDC-40NW GEG-40N MLP-50W GTF-40SSW DLN-20SE BOI- 30NNE REO-70SSW YKM-20ESE SEA-60SSW YDC MOD TURB BTN FL180 AND FL260. CONDS CONTG THRU 03Z. AREA 2...TURB ID MT WA OR BOUNDED BY 20SE FCA-30NW DLN-40SW DNJ-20SSW PDT-20SW GEG-20NNW MLP-20SE FCA MOD TURB BLW 140. CONDS CONTG THRU 03Z. AREA 3...TURB WY UT CO BOUNDED BY 40ESE CZI-40N CYS-30N DEN-50SSW DEN-20E HBU-30W HBU- 20WNW JNC-40ESE MTU-40ESE CZI MOD TURB BLW FL180. CONDS DVLPG 00-03Z. CONDS CONTG THRU 03Z. AREA 4...TURB ID MT WY NV UT CO BOUNDED BY 60WSW YQL-60W HVR-40ESE GTF-50SSE LWT-40E SHR-40ESE CZI-40ESE MTU-30NW HVE-30S DTA-50W BVL-40SW DNJ-30NW DLN-60WSW YQL MOD TURB BLW 160. CONDS CONTG THRU 03Z.",
      "valid_time_from": "2024-04-29T14:45:00Z",
      "valid_time_to": "2024-04-29T21:00:00Z",
      "hazard": {
        "type": "TURB",
        "severity": "0"
      },
      "airsigmet_type": "AIRMET",
      "area": [
        {
          "point": {
            "longitude": "-114.1484",
            "latitude": "41.8653"
          }
        },
        {
          "point": {
            "longitude": "-114.3715",
            "latitude": "40.5359"
          }
        },
        {
          "point": {
            "longitude": "-114.0535",
            "latitude": "39.5517"
          }
        },
        {
          "point": {
            "longitude": "-114.5473",
            "latitude": "39.0646"
          }
        },
        {
          "point": {
            "longitude": "-116.3055",
            "latitude": "40.0983"
          }
        },
        {
          "point": {
            "longitude": "-116.4942",
            "latitude": "41.3411"
          }
        },
        {
          "point": {
            "longitude": "-114.1484",
            "latitude": "41.8653"
          }
        }
      ],
      "altitude": {
      }
    },
    {
      "raw_text": "WAUS46 KKCI 291445 SFOT WA 291445 AIRMET TANGO UPDT 2 FOR TURB AND STG SFC WNDS VALID UNTIL 292100 AIRMET TURB...WA OR AND CSTL WTRS FROM 30S YDC TO 40NW LKT TO 30ENE REO TO 70SW BKE TO 50SE EUG TO 50SSW ONP TO 110WNW ONP TO 140W TOU TO 30S YDC MOD TURB BTN FL180 AND FL260. CONDS CONTG BYD 21Z THRU 03Z. OTLK VALID 2100-0300Z AREA 1...TURB WA OR ID MT BOUNDED BY 60SSW YDC-40NW GEG-40N MLP-50W GTF-40SSW DLN-20SE BOI- 30NNE REO-70SSW YKM-20ESE SEA-60SSW YDC MOD TURB BTN FL180 AND FL260. CONDS CONTG THRU 03Z. AREA 2...TURB CA AND CSTL WTRS BOUNDED BY 50NE EHF-50SSW BTY-40NE TRM-20SE LAX-70WSW RZS-60NW RZS-50NE EHF MOD TURB BLW 120. CONDS DVLPG 21-00Z. CONDS CONTG THRU 03Z. AREA 3...TURB WA OR ID MT BOUNDED BY 20SE FCA-30NW DLN-40SW DNJ-20SSW PDT-20SW GEG-20NNW MLP-20SE FCA MOD TURB BLW 140. CONDS CONTG THRU 03Z.",
      "valid_time_from": "2024-04-29T14:45:00Z",
      "valid_time_to": "2024-04-29T21:00:00Z",
      "altitude": {
        "min_ft_msl": "18000",
        "max_ft_msl": "26000"
      },
      "hazard": {
        "type": "TURB",
        "severity": "MOD"
      },
      "airsigmet_type": "AIRMET",
      "area": [
        {
          "point": {
            "longitude": "-120.52",
            "latitude": "48.9669"
          }
        },
        {
          "point": {
            "longitude": "-114.7505",
            "latitude": "45.4881"
          }
        },
        {
          "point": {
            "longitude": "-117.2368",
            "latitude": "42.7808"
          }
        },
        {
          "point": {
            "longitude": "-118.9581",
            "latitude": "44.0084"
          }
        },
        {
          "point": {
            "longitude": "-122.4053",
            "latitude": "43.5263"
          }
        },
        {
          "point": {
            "longitude": "-124.503",
            "latitude": "43.8073"
          }
        },
        {
          "point": {
            "longitude": "-126.4654",
            "latitude": "45.2562"
          }
        },
        {
          "point": {
            "longitude": "-128.1251",
            "latitude": "48.247"
          }
        },
        {
          "point": {
            "longitude": "-120.52",
            "latitude": "48.9669"
          }
        }
      ]
    },
    {
      "raw_text": "WAUS46 KKCI 291445 SFOT WA 291445 AIRMET TANGO UPDT 2 FOR TURB AND STG SFC WNDS VALID UNTIL 292100 AIRMET TURB...WA OR FROM 20SE SEA TO 20SW EPH TO 40ESE DSD TO 30WNW LKV TO 20NNE OED TO 30SSE EUG TO 20SE SEA MOD TURB BLW 160. CONDS ENDG 18-21Z. OTLK VALID 2100-0300Z AREA 1...TURB WA OR ID MT BOUNDED BY 60SSW YDC-40NW GEG-40N MLP-50W GTF-40SSW DLN-20SE BOI- 30NNE REO-70SSW YKM-20ESE SEA-60SSW YDC MOD TURB BTN FL180 AND FL260. CONDS CONTG THRU 03Z. AREA 2...TURB CA AND CSTL WTRS BOUNDED BY 50NE EHF-50SSW BTY-40NE TRM-20SE LAX-70WSW RZS-60NW RZS-50NE EHF MOD TURB BLW 120. CONDS DVLPG 21-00Z. CONDS CONTG THRU 03Z. AREA 3...TURB WA OR ID MT BOUNDED BY 20SE FCA-30NW DLN-40SW DNJ-20SSW PDT-20SW GEG-20NNW MLP-20SE FCA MOD TURB BLW 140. CONDS CONTG THRU 03Z.",
      "valid_time_from": "2024-04-29T14:45:00Z",
      "valid_time_to": "2024-04-29T21:00:00Z",
      "altitude": {
        "min_ft_msl": "0",
        "max_ft_msl": "16000"
      },
      "hazard": {
        "type": "TURB",
        "severity": "MOD"
      },
      "airsigmet_type": "AIRMET",
      "area": [
        {
          "point": {
            "longitude": "-121.9641",
            "latitude": "47.2045"
          }
        },
        {
          "point": {
            "longitude": "-119.7655",
            "latitude": "47.1445"
          }
        },
        {
          "point": {
            "longitude": "-120.4463",
            "latitude": "43.9924"
          }
        },
        {
          "point": {
            "longitude": "-121.1422",
            "latitude": "42.6808"
          }
        },
        {
          "point": {
            "longitude": "-122.7367",
            "latitude": "42.7869"
          }
        },
        {
          "point": {
            "longitude": "-122.9539",
            "latitude": "43.6549"
          }
        },
        {
          "point": {
            "longitude": "-121.9641",
            "latitude": "47.2045"
          }
        }
      ]
    },
    {
      "raw_text": "WAUS46 KKCI 291445 SFOT WA 291445 AIRMET TANGO UPDT 2 FOR TURB AND STG SFC WNDS VALID UNTIL 292100 AIRMET TURB...WA OR FROM 30SE GEG TO 60NNE DNJ TO 30ESE BKE TO 20S PDT TO 40NNE PDT TO 30SE GEG MOD TURB BLW 140. CONDS DVLPG 18-21Z. CONDS CONTG BYD 21Z THRU 03Z. OTLK VALID 2100-0300Z AREA 1...TURB WA OR ID MT BOUNDED BY 60SSW YDC-40NW GEG-40N MLP-50W GTF-40SSW DLN-20SE BOI- 30NNE REO-70SSW YKM-20ESE SEA-60SSW YDC MOD TURB BTN FL180 AND FL260. CONDS CONTG THRU 03Z. AREA 2...TURB CA AND CSTL WTRS BOUNDED BY 50NE EHF-50SSW BTY-40NE TRM-20SE LAX-70WSW RZS-60NW RZS-50NE EHF MOD TURB BLW 120. CONDS DVLPG 21-00Z. CONDS CONTG THRU 03Z. AREA 3...TURB WA OR ID MT BOUNDED BY 20SE FCA-30NW DLN-40SW DNJ-20SSW PDT-20SW GEG-20NNW MLP-20SE FCA MOD TURB BLW 140. CONDS CONTG THRU 03Z.",
      "valid_time_from": "2024-04-29T14:45:00Z",
      "valid_time_to": "2024-04-29T21:00:00Z",
      "altitude": {
        "min_ft_msl": "0",
        "max_ft_msl": "14000"
      },
      "hazard": {
        "type": "TURB",
        "severity": "MOD"
      },
      "airsigmet_type": "AIRMET",
      "area": [
        {
          "point": {
            "longitude": "-117.1064",
            "latitude": "47.2031"
          }
        },
        {
          "point": {
            "longitude": "-115.6638",
            "latitude": "45.6899"
          }
        },
        {
          "point": {
            "longitude": "-117.1567",
            "latitude": "44.6456"
          }
        },
        {
          "point": {
            "longitude": "-118.94",
            "latitude": "45.3676"
          }
        },
        {
          "point": {
            "longitude": "-118.5717",
            "latitude": "46.3136"
          }
        },
        {
          "point": {
            "longitude": "-117.1064",
            "latitude": "47.2031"
          }
        }
      ]
    },
    {
      "raw_text": "WAUS46 KKCI 291445 SFOT WA 291445 AIRMET TANGO UPDT 2 FOR TURB AND STG SFC WNDS VALID UNTIL 292100 AIRMET STG SFC WNDS...CA AND CSTL WTRS FROM 20NW PYE TO 70NW RZS TO 150SW RZS TO 120SW PYE TO 60W PYE TO 20NW PYE SUSTAINED SURFACE WINDS GTR THAN 30KT EXP. CONDS CONTG BYD 21Z THRU 03Z. OTLK VALID 2100-0300Z AREA 1...TURB WA OR ID MT BOUNDED BY 60SSW YDC-40NW GEG-40N MLP-50W GTF-40SSW DLN-20SE BOI- 30NNE REO-70SSW YKM-20ESE SEA-60SSW YDC MOD TURB BTN FL180 AND FL260. CONDS CONTG THRU 03Z. AREA 2...TURB CA AND CSTL WTRS BOUNDED BY 50NE EHF-50SSW BTY-40NE TRM-20SE LAX-70WSW RZS-60NW RZS-50NE EHF MOD TURB BLW 120. CONDS DVLPG 21-00Z. CONDS CONTG THRU 03Z. AREA 3...TURB WA OR ID MT BOUNDED BY 20SE FCA-30NW DLN-40SW DNJ-20SSW PDT-20SW GEG-20NNW MLP-20SE FCA MOD TURB BLW 140. CONDS CONTG THRU 03Z.",
      "valid_time_from": "2024-04-29T14:45:00Z",
      "valid_time_to": "2024-04-29T21:00:00Z",
      "hazard": {
        "type": "TURB",
        "severity": "0"
      },
      "airsigmet_type": "AIRMET",
      "area": [
        {
          "point": {
            "longitude": "-123.1695",
            "latitude": "38.3146"
          }
        },
        {
          "point": {
            "longitude": "-120.7822",
            "latitude": "35.3316"
          }
        },
        {
          "point": {
            "longitude": "-121.8689",
            "latitude": "32.7261"
          }
        },
        {
          "point": {
            "longitude": "-124.6277",
            "latitude": "36.6566"
          }
        },
        {
          "point": {
            "longitude": "-124.1367",
            "latitude": "38.0732"
          }
        },
        {
          "point": {
            "longitude": "-123.1695",
            "latitude": "38.3146"
          }
        }
      ],
      "altitude": {
      }
    },
    {
      "raw_text": "WAUS42 KKCI 291445 MIAS WA 291445 AIRMET SIERRA UPDT 3 FOR IFR VALID UNTIL 292100 AIRMET NO SGFNT IFR EXP OUTSIDE OF CNVTV ACT. ",
      "valid_time_from": "2024-04-29T14:45:00Z",
      "valid_time_to": "2024-04-29T20:45:00Z",
      "hazard": {
        "type": "IFR"
      },
      "airsigmet_type": "AIRMET",
      "area": [

      ],
      "altitude": {
      }
    },
    {
      "raw_text": "WAUS45 KKCI 291445 SLCS WA 291445 AIRMET SIERRA UPDT 2 FOR IFR AND MTN OBSCN VALID UNTIL 292100 AIRMET NO SGFNT IFR EXP OUTSIDE OF CNVTV ACT. ",
      "valid_time_from": "2024-04-29T14:45:00Z",
      "valid_time_to": "2024-04-29T20:45:00Z",
      "hazard": {
        "type": "IFR"
      },
      "airsigmet_type": "AIRMET",
      "area": [

      ],
      "altitude": {
      }
    },
    {
      "raw_text": "WAUS41 KKCI 291445 BOSS WA 291445 AIRMET SIERRA UPDT 3 FOR IFR AND MTN OBSCN VALID UNTIL 292100 AIRMET NO SGFNT IFR EXP OUTSIDE OF CNVTV ACT. ",
      "valid_time_from": "2024-04-29T14:45:00Z",
      "valid_time_to": "2024-04-29T20:45:00Z",
      "hazard": {
        "type": "IFR"
      },
      "airsigmet_type": "AIRMET",
      "area": [

      ],
      "altitude": {
      }
    },
    {
      "raw_text": "WAUS45 KKCI 291445 SLCS WA 291445 AIRMET SIERRA UPDT 2 FOR IFR AND MTN OBSCN VALID UNTIL 292100 AIRMET MTN OBSCN...ID MT WY WA OR CA FROM 30S YQL TO 30SW LWT TO 30WSW BIL TO 60NE JAC TO 20SSE JAC TO 20ESE PIH TO 30SSW BOI TO 50WNW REO TO 50WSW LKV TO 20W FOT TO 70WNW OED TO ONP TO 20NNW HQM TO 20WNW TOU TO HUH TO 30S YQL MTNS OBSC BY CLDS/PCPN. CONDS CONTG BYD 21Z THRU 03Z.",
      "valid_time_from": "2024-04-29T14:45:00Z",
      "valid_time_to": "2024-04-29T20:45:00Z",
      "hazard": {
        "type": "MTN OBSCN",
        "severity": "LT-MOD"
      },
      "airsigmet_type": "AIRMET",
      "area": [
        {
          "point": {
            "longitude": "-112.8",
            "latitude": "49.1269"
          }
        },
        {
          "point": {
            "longitude": "-110.1286",
            "latitude": "46.6931"
          }
        },
        {
          "point": {
            "longitude": "-109.2945",
            "latitude": "45.6156"
          }
        },
        {
          "point": {
            "longitude": "-109.7445",
            "latitude": "44.3209"
          }
        },
        {
          "point": {
            "longitude": "-110.5552",
            "latitude": "43.3128"
          }
        },
        {
          "point": {
            "longitude": "-112.2319",
            "latitude": "42.742"
          }
        },
        {
          "point": {
            "longitude": "-116.4536",
            "latitude": "43.0849"
          }
        },
        {
          "point": {
            "longitude": "-118.9237",
            "latitude": "42.9049"
          }
        },
        {
          "point": {
            "longitude": "-121.5513",
            "latitude": "42.1656"
          }
        },
        {
          "point": {
            "longitude": "-124.6682",
            "latitude": "40.6692"
          }
        },
        {
          "point": {
            "longitude": "-124.3833",
            "latitude": "42.9175"
          }
        },
        {
          "point": {
            "longitude": "-124.06",
            "latitude": "44.58"
          }
        },
        {
          "point": {
            "longitude": "-124.3374",
            "latitude": "47.2569"
          }
        },
        {
          "point": {
            "longitude": "-125.0928",
            "latitude": "48.4263"
          }
        },
        {
          "point": {
            "longitude": "-122.58",
            "latitude": "48.95"
          }
        },
        {
          "point": {
            "longitude": "-112.8",
            "latitude": "49.1269"
          }
        }
      ],
      "altitude": {
      }
    },
    {
      "raw_text": "WAUS44 KKCI 291445 DFWS WA 291445 AIRMET SIERRA UPDT 3 FOR IFR VALID UNTIL 292100 AIRMET IFR...OK TX AR FROM 20ESE SGF TO 70ESE RZC TO 30SE FSM TO GGG TO 40NW LFK TO 50NW IAH TO 60ESE SAT TO 30WNW LRD TO 40NW DLF TO 20SW JCT TO 50SE ABI TO SPS TO 20SSE OKC TO 20ESE SGF CIG BLW 010/VIS BLW 3SM BR/FG. CONDS ENDG 15-18Z.",
      "valid_time_from": "2024-04-29T14:45:00Z",
      "valid_time_to": "2024-04-29T21:00:00Z",
      "altitude": {
        "min_ft_msl": "0",
        "max_ft_msl": "1000"
      },
      "hazard": {
        "type": "IFR",
        "severity": "LT-MOD"
      },
      "airsigmet_type": "AIRMET",
      "area": [
        {
          "point": {
            "longitude": "-92.9443",
            "latitude": "37.2322"
          }
        },
        {
          "point": {
            "longitude": "-92.7898",
            "latitude": "35.7957"
          }
        },
        {
          "point": {
            "longitude": "-93.8356",
            "latitude": "35.0235"
          }
        },
        {
          "point": {
            "longitude": "-94.75",
            "latitude": "32.42"
          }
        },
        {
          "point": {
            "longitude": "-95.272",
            "latitude": "31.6289"
          }
        },
        {
          "point": {
            "longitude": "-96.0359",
            "latitude": "30.549"
          }
        },
        {
          "point": {
            "longitude": "-97.4041",
            "latitude": "29.2542"
          }
        },
        {
          "point": {
            "longitude": "-99.9448",
            "latitude": "27.6715"
          }
        },
        {
          "point": {
            "longitude": "-101.3118",
            "latitude": "29.829"
          }
        },
        {
          "point": {
            "longitude": "-100.0924",
            "latitude": "30.3647"
          }
        },
        {
          "point": {
            "longitude": "-99.1643",
            "latitude": "31.8873"
          }
        },
        {
          "point": {
            "longitude": "-98.59",
            "latitude": "33.99"
          }
        },
        {
          "point": {
            "longitude": "-97.4546",
            "latitude": "35.0528"
          }
        },
        {
          "point": {
            "longitude": "-92.9443",
            "latitude": "37.2322"
          }
        }
      ]
    },
    {
      "raw_text": "WAUS41 KKCI 291445 BOSS WA 291445 AIRMET SIERRA UPDT 3 FOR IFR AND MTN OBSCN VALID UNTIL 292100 AIRMET MTN OBSCN...ME NH VT MA NY FROM 70NW PQI TO 20NNW MLT TO 30N CON TO 50S ALB TO 20SW SYR TO 30SE YOW TO 80S YQB TO 70NW PQI MTNS OBSC BY CLDS/PCPN. CONDS CONTG BYD 21Z THRU 03Z.",
      "valid_time_from": "2024-04-29T14:45:00Z",
      "valid_time_to": "2024-04-29T20:45:00Z",
      "hazard": {
        "type": "MTN OBSCN",
        "severity": "LT-MOD"
      },
      "airsigmet_type": "AIRMET",
      "area": [
        {
          "point": {
            "longitude": "-69.3144",
            "latitude": "47.5893"
          }
        },
        {
          "point": {
            "longitude": "-68.7027",
            "latitude": "45.8869"
          }
        },
        {
          "point": {
            "longitude": "-71.58",
            "latitude": "43.7231"
          }
        },
        {
          "point": {
            "longitude": "-73.8",
            "latitude": "41.9146"
          }
        },
        {
          "point": {
            "longitude": "-76.521",
            "latitude": "42.9245"
          }
        },
        {
          "point": {
            "longitude": "-75.1673",
            "latitude": "44.9632"
          }
        },
        {
          "point": {
            "longitude": "-71.38",
            "latitude": "45.4705"
          }
        },
        {
          "point": {
            "longitude": "-69.3144",
            "latitude": "47.5893"
          }
        }
      ],
      "altitude": {
      }
    },
    {
      "raw_text": "WAUS43 KKCI 291445 CHIS WA 291445 AIRMET SIERRA UPDT 3 FOR IFR VALID UNTIL 292100 AIRMET IFR...ND SD NE MN IA WI LM LS MI LH FROM 50N ISN TO 60WNW INL TO 70WSW YQT TO 40E YQT TO SSM TO 50WNW YVV TO 30ESE ECK TO 30S GRR TO 20NE DBQ TO 70SE FSD TO 20ESE RAP TO 50SW ISN TO 50N ISN CIG BLW 010/VIS BLW 3SM PCPN/BR. CONDS CONTG BYD 21Z THRU 03Z.",
      "valid_time_from": "2024-04-29T14:45:00Z",
      "valid_time_to": "2024-04-29T21:00:00Z",
      "altitude": {
        "min_ft_msl": "0",
        "max_ft_msl": "1000"
      },
      "hazard": {
        "type": "IFR",
        "severity": "LT-MOD"
      },
      "airsigmet_type": "AIRMET",
      "area": [
        {
          "point": {
            "longitude": "-103.63",
            "latitude": "49.0154"
          }
        },
        {
          "point": {
            "longitude": "-94.8027",
            "latitude": "48.9431"
          }
        },
        {
          "point": {
            "longitude": "-90.9298",
            "latitude": "47.9118"
          }
        },
        {
          "point": {
            "longitude": "-88.3194",
            "latitude": "48.3657"
          }
        },
        {
          "point": {
            "longitude": "-84.31",
            "latitude": "46.41"
          }
        },
        {
          "point": {
            "longitude": "-82.1928",
            "latitude": "45.0645"
          }
        },
        {
          "point": {
            "longitude": "-82.0838",
            "latitude": "43.0657"
          }
        },
        {
          "point": {
            "longitude": "-85.5",
            "latitude": "42.2869"
          }
        },
        {
          "point": {
            "longitude": "-90.3905",
            "latitude": "42.6346"
          }
        },
        {
          "point": {
            "longitude": "-95.6542",
            "latitude": "42.8187"
          }
        },
        {
          "point": {
            "longitude": "-102.5842",
            "latitude": "43.852"
          }
        },
        {
          "point": {
            "longitude": "-104.5058",
            "latitude": "47.5859"
          }
        },
        {
          "point": {
            "longitude": "-103.63",
            "latitude": "49.0154"
          }
        }
      ]
    },
    {
      "raw_text": "WAUS44 KKCI 291445 DFWS WA 291445 AIRMET SIERRA UPDT 3 FOR IFR VALID UNTIL 292100 AIRMET IFR...OK TX AR LA AND CSTL WTRS FROM 30NNE ELD TO 30NE MLU TO 60SSW LSU TO 40WSW LCH TO 20S PSX TO 50S CRP TO 60S SAT TO 60SSE CWK TO 60WSW LFK TO GGG TO 20WNW TXK TO 30NNE ELD CIG BLW 010/VIS BLW 3SM PCPN/BR/FG. CONDS ENDG 15-18Z.",
      "valid_time_from": "2024-04-29T14:45:00Z",
      "valid_time_to": "2024-04-29T21:00:00Z",
      "altitude": {
        "min_ft_msl": "0",
        "max_ft_msl": "1000"
      },
      "hazard": {
        "type": "IFR",
        "severity": "LT-MOD"
      },
      "airsigmet_type": "AIRMET",
      "area": [
        {
          "point": {
            "longitude": "-92.5085",
            "latitude": "33.7245"
          }
        },
        {
          "point": {
            "longitude": "-91.6065",
            "latitude": "32.875"
          }
        },
        {
          "point": {
            "longitude": "-91.7387",
            "latitude": "29.558"
          }
        },
        {
          "point": {
            "longitude": "-93.8183",
            "latitude": "29.8837"
          }
        },
        {
          "point": {
            "longitude": "-96.31",
            "latitude": "28.4276"
          }
        },
        {
          "point": {
            "longitude": "-97.45",
            "latitude": "27.0646"
          }
        },
        {
          "point": {
            "longitude": "-98.46",
            "latitude": "28.6429"
          }
        },
        {
          "point": {
            "longitude": "-97.0918",
            "latitude": "29.458"
          }
        },
        {
          "point": {
            "longitude": "-95.7922",
            "latitude": "30.774"
          }
        },
        {
          "point": {
            "longitude": "-94.75",
            "latitude": "32.42"
          }
        },
        {
          "point": {
            "longitude": "-94.4388",
            "latitude": "33.6366"
          }
        },
        {
          "point": {
            "longitude": "-92.5085",
            "latitude": "33.7245"
          }
        }
      ]
    },
    {
      "raw_text": "WAUS43 KKCI 291445 CHIS WA 291445 AIRMET SIERRA UPDT 3 FOR IFR VALID UNTIL 292100 AIRMET IFR...IA MO IL IN FROM 20SSE ORD TO 20S BVT TO 30SSW TTH TO 40W PXV TO 30SW FAM TO 50ENE SGF TO COU TO 30E IRK TO 40W BDF TO 20SSE ORD CIG BLW 010/VIS BLW 3SM PCPN/BR. CONDS ENDG 15-18Z.",
      "valid_time_from": "2024-04-29T14:45:00Z",
      "valid_time_to": "2024-04-29T21:00:00Z",
      "altitude": {
        "min_ft_msl": "0",
        "max_ft_msl": "1000"
      },
      "hazard": {
        "type": "IFR",
        "severity": "LT-MOD"
      },
      "airsigmet_type": "AIRMET",
      "area": [
        {
          "point": {
            "longitude": "-87.7297",
            "latitude": "41.6728"
          }
        },
        {
          "point": {
            "longitude": "-87.07",
            "latitude": "40.2276"
          }
        },
        {
          "point": {
            "longitude": "-87.4978",
            "latitude": "39.025"
          }
        },
        {
          "point": {
            "longitude": "-88.6028",
            "latitude": "37.927"
          }
        },
        {
          "point": {
            "longitude": "-90.6773",
            "latitude": "37.3134"
          }
        },
        {
          "point": {
            "longitude": "-92.3548",
            "latitude": "37.6757"
          }
        },
        {
          "point": {
            "longitude": "-92.22",
            "latitude": "38.82"
          }
        },
        {
          "point": {
            "longitude": "-91.932",
            "latitude": "40.1381"
          }
        },
        {
          "point": {
            "longitude": "-90.4729",
            "latitude": "41.1566"
          }
        },
        {
          "point": {
            "longitude": "-87.7297",
            "latitude": "41.6728"
          }
        }
      ]
    },
    {
      "raw_text": "WAUS44 KKCI 291445 DFWS WA 291445 AIRMET SIERRA UPDT 3 FOR IFR VALID UNTIL 292100 AIRMET IFR...TX LA AND CSTL WTRS FROM 40WSW LCH TO 60SSW LSU TO 120SSE LCH TO 130ESE PSX TO 120SSE PSX TO 80E BRO TO BRO TO 30SSE CRP TO 20S PSX TO 50SSE IAH TO 40WSW LCH CIG BLW 010. CONDS DVLPG 15-18Z. CONDS CONTG BYD 21Z THRU 03Z.",
      "valid_time_from": "2024-04-29T14:45:00Z",
      "valid_time_to": "2024-04-29T21:00:00Z",
      "altitude": {
        "min_ft_msl": "0",
        "max_ft_msl": "1000"
      },
      "hazard": {
        "type": "IFR",
        "severity": "LT-MOD"
      },
      "airsigmet_type": "AIRMET",
      "area": [
        {
          "point": {
            "longitude": "-93.8183",
            "latitude": "29.8837"
          }
        },
        {
          "point": {
            "longitude": "-91.7387",
            "latitude": "29.558"
          }
        },
        {
          "point": {
            "longitude": "-92.2434",
            "latitude": "28.2947"
          }
        },
        {
          "point": {
            "longitude": "-94.0465",
            "latitude": "27.9127"
          }
        },
        {
          "point": {
            "longitude": "-95.4543",
            "latitude": "26.9149"
          }
        },
        {
          "point": {
            "longitude": "-95.9019",
            "latitude": "25.9125"
          }
        },
        {
          "point": {
            "longitude": "-97.38",
            "latitude": "25.92"
          }
        },
        {
          "point": {
            "longitude": "-97.2331",
            "latitude": "27.4351"
          }
        },
        {
          "point": {
            "longitude": "-96.31",
            "latitude": "28.4276"
          }
        },
        {
          "point": {
            "longitude": "-94.9838",
            "latitude": "29.1877"
          }
        },
        {
          "point": {
            "longitude": "-93.8183",
            "latitude": "29.8837"
          }
        }
      ]
    },
    {
      "raw_text": "WAUS46 KKCI 291445 SFOS WA 291445 AIRMET SIERRA UPDT 3 FOR IFR AND MTN OBSCN VALID UNTIL 292100 AIRMET IFR...CA AND CSTL WTRS FROM 20N LAX TO 30ESE MZB TO 90SW MZB TO 70S RZS TO 20N LAX CIG BLW 010/VIS BLW 3SM BR/FG. CONDS ENDG 15-18Z.",
      "valid_time_from": "2024-04-29T14:45:00Z",
      "valid_time_to": "2024-04-29T21:00:00Z",
      "altitude": {
        "min_ft_msl": "0",
        "max_ft_msl": "1000"
      },
      "hazard": {
        "type": "IFR",
        "severity": "LT-MOD"
      },
      "airsigmet_type": "AIRMET",
      "area": [
        {
          "point": {
            "longitude": "-118.43",
            "latitude": "34.2624"
          }
        },
        {
          "point": {
            "longitude": "-116.6784",
            "latitude": "32.5863"
          }
        },
        {
          "point": {
            "longitude": "-118.4769",
            "latitude": "31.713"
          }
        },
        {
          "point": {
            "longitude": "-119.77",
            "latitude": "33.3422"
          }
        },
        {
          "point": {
            "longitude": "-118.43",
            "latitude": "34.2624"
          }
        }
      ]
    },
    {
      "raw_text": "WAUS46 KKCI 291445 SFOS WA 291445 AIRMET SIERRA UPDT 3 FOR IFR AND MTN OBSCN VALID UNTIL 292100 AIRMET MTN OBSCN...WA OR CA ID MT WY FROM 30S YQL TO 30SW LWT TO 30WSW BIL TO 60NE JAC TO 20SSE JAC TO 20ESE PIH TO 30SSW BOI TO 50WNW REO TO 50WSW LKV TO 20W FOT TO 70WNW OED TO ONP TO 20NNW HQM TO 20WNW TOU TO HUH TO 30S YQL MTNS OBSC BY CLDS/PCPN. CONDS CONTG BYD 21Z THRU 03Z.",
      "valid_time_from": "2024-04-29T14:45:00Z",
      "valid_time_to": "2024-04-29T21:00:00Z",
      "hazard": {
        "type": "MTN OBSCN",
        "severity": "LT-MOD"
      },
      "airsigmet_type": "AIRMET",
      "area": [
        {
          "point": {
            "longitude": "-112.8",
            "latitude": "49.1269"
          }
        },
        {
          "point": {
            "longitude": "-110.1286",
            "latitude": "46.6931"
          }
        },
        {
          "point": {
            "longitude": "-109.2945",
            "latitude": "45.6156"
          }
        },
        {
          "point": {
            "longitude": "-109.7445",
            "latitude": "44.3209"
          }
        },
        {
          "point": {
            "longitude": "-110.5552",
            "latitude": "43.3128"
          }
        },
        {
          "point": {
            "longitude": "-112.2319",
            "latitude": "42.742"
          }
        },
        {
          "point": {
            "longitude": "-116.4536",
            "latitude": "43.0849"
          }
        },
        {
          "point": {
            "longitude": "-118.9237",
            "latitude": "42.9049"
          }
        },
        {
          "point": {
            "longitude": "-121.5513",
            "latitude": "42.1656"
          }
        },
        {
          "point": {
            "longitude": "-124.6682",
            "latitude": "40.6692"
          }
        },
        {
          "point": {
            "longitude": "-124.3833",
            "latitude": "42.9175"
          }
        },
        {
          "point": {
            "longitude": "-124.06",
            "latitude": "44.58"
          }
        },
        {
          "point": {
            "longitude": "-124.3374",
            "latitude": "47.2569"
          }
        },
        {
          "point": {
            "longitude": "-125.0928",
            "latitude": "48.4263"
          }
        },
        {
          "point": {
            "longitude": "-122.58",
            "latitude": "48.95"
          }
        },
        {
          "point": {
            "longitude": "-112.8",
            "latitude": "49.1269"
          }
        }
      ],
      "altitude": {
      }
    },
    {
      "raw_text": "WAUS42 KKCI 291445 MIAZ WA 291445 AIRMET ZULU UPDT 2 FOR ICE AND FRZLVL VALID UNTIL 292100 AIRMET NO SGFNT ICE EXP OUTSIDE OF CNVTV ACT. FRZLVL...RANGING FROM 125-150 ACRS AREA",
      "valid_time_from": "2024-04-29T14:45:00Z",
      "valid_time_to": "2024-04-29T20:45:00Z",
      "hazard": {
        "type": "ICE"
      },
      "airsigmet_type": "AIRMET",
      "area": [

      ],
      "altitude": {
      }
    },
    {
      "raw_text": "WAUS41 KKCI 291445 BOST WA 291445 AIRMET TANGO UPDT 2 FOR TURB VALID UNTIL 292100 AIRMET TURB...NY LO PA OH LE WV FROM 30WSW BUF TO 30NNE EKN TO 40S HNN TO HNN TO CVG TO FWA TO 30ESE DXO TO 50W ERI TO 30WSW BUF MOD TURB BTN FL200 AND FL430. CONDS CONTG BYD 21Z THRU 03Z. OTLK VALID 2100-0300Z...TURB VT MA CT NY LO NJ PA OH LE WV MD DC DE VA BOUNDED BY 30ESE YOW-50NNW MPV-20S BDL-40ESE EMI-40SW CSN-20S BKW-CVG-FWA-30NW CLE-20W BUF-YYZ-40NNW SYR-30ESE YOW MOD TURB BTN FL280 AND FL430. CONDS CONTG THRU 03Z.",
      "valid_time_from": "2024-04-29T14:45:00Z",
      "valid_time_to": "2024-04-29T21:00:00Z",
      "altitude": {
        "min_ft_msl": "20000",
        "max_ft_msl": "43000"
      },
      "hazard": {
        "type": "TURB",
        "severity": "MOD"
      },
      "airsigmet_type": "AIRMET",
      "area": [
        {
          "point": {
            "longitude": "-79.2828",
            "latitude": "42.7357"
          }
        },
        {
          "point": {
            "longitude": "-79.8509",
            "latitude": "39.3845"
          }
        },
        {
          "point": {
            "longitude": "-82.03",
            "latitude": "38.0852"
          }
        },
        {
          "point": {
            "longitude": "-82.03",
            "latitude": "38.75"
          }
        },
        {
          "point": {
            "longitude": "-84.7",
            "latitude": "39.02"
          }
        },
        {
          "point": {
            "longitude": "-85.19",
            "latitude": "40.98"
          }
        },
        {
          "point": {
            "longitude": "-82.7444",
            "latitude": "42.0158"
          }
        },
        {
          "point": {
            "longitude": "-81.4245",
            "latitude": "42.0145"
          }
        },
        {
          "point": {
            "longitude": "-79.2828",
            "latitude": "42.7357"
          }
        }
      ]
    },
    {
      "raw_text": "WAUS42 KKCI 291445 MIAT WA 291445 AIRMET TANGO UPDT 2 FOR TURB VALID UNTIL 292100 AIRMET TURB...NC GA FROM 40E VXV TO 50SSE LGC TO GQO TO 40E VXV MOD TURB BTN FL200 AND FL430. CONDS ENDG BY 21Z.",
      "valid_time_from": "2024-04-29T14:45:00Z",
      "valid_time_to": "2024-04-29T21:00:00Z",
      "altitude": {
        "min_ft_msl": "20000",
        "max_ft_msl": "43000"
      },
      "hazard": {
        "type": "TURB",
        "severity": "MOD"
      },
      "airsigmet_type": "AIRMET",
      "area": [
        {
          "point": {
            "longitude": "-83.0694",
            "latitude": "35.8972"
          }
        },
        {
          "point": {
            "longitude": "-84.8319",
            "latitude": "32.2776"
          }
        },
        {
          "point": {
            "longitude": "-85.15",
            "latitude": "34.96"
          }
        },
        {
          "point": {
            "longitude": "-83.0694",
            "latitude": "35.8972"
          }
        }
      ]
    },
    {
      "raw_text": "WAUS45 KKCI 291445 SLCT WA 291445 AIRMET TANGO UPDT 2 FOR TURB AND STG SFC WNDS VALID UNTIL 292100 AIRMET TURB...ID MT WY FROM 30ESE HLN TO 20SSW BIL TO BOY TO 30NNE OCS TO 40ENE BOI TO 30ESE HLN MOD TURB BLW 160. CONDS DVLPG 18-21Z. CONDS CONTG BYD 21Z THRU 03Z. OTLK VALID 2100-0300Z AREA 1...TURB ID MT WA OR BOUNDED BY 60SSW YDC-40NW GEG-40N MLP-50W GTF-40SSW DLN-20SE BOI- 30NNE REO-70SSW YKM-20ESE SEA-60SSW YDC MOD TURB BTN FL180 AND FL260. CONDS CONTG THRU 03Z. AREA 2...TURB ID MT WA OR BOUNDED BY 20SE FCA-30NW DLN-40SW DNJ-20SSW PDT-20SW GEG-20NNW MLP-20SE FCA MOD TURB BLW 140. CONDS CONTG THRU 03Z. AREA 3...TURB WY UT CO BOUNDED BY 40ESE CZI-40N CYS-30N DEN-50SSW DEN-20E HBU-30W HBU- 20WNW JNC-40ESE MTU-40ESE CZI MOD TURB BLW FL180. CONDS DVLPG 00-03Z. CONDS CONTG THRU 03Z. AREA 4...TURB ID MT WY NV UT CO BOUNDED BY 60WSW YQL-60W HVR-40ESE GTF-50SSE LWT-40E SHR-40ESE CZI-40ESE MTU-30NW HVE-30S DTA-50W BVL-40SW DNJ-30NW DLN-60WSW YQL MOD TURB BLW 160. CONDS CONTG THRU 03Z.",
      "valid_time_from": "2024-04-29T14:45:00Z",
      "valid_time_to": "2024-04-29T21:00:00Z",
      "altitude": {
        "min_ft_msl": "0",
        "max_ft_msl": "16000"
      },
      "hazard": {
        "type": "TURB",
        "severity": "MOD"
      },
      "airsigmet_type": "AIRMET",
      "area": [
        {
          "point": {
            "longitude": "-111.2759",
            "latitude": "46.4155"
          }
        },
        {
          "point": {
            "longitude": "-108.8115",
            "latitude": "45.5028"
          }
        },
        {
          "point": {
            "longitude": "-108.3",
            "latitude": "43.46"
          }
        },
        {
          "point": {
            "longitude": "-108.7607",
            "latitude": "42.0545"
          }
        },
        {
          "point": {
            "longitude": "-115.3391",
            "latitude": "43.8012"
          }
        },
        {
          "point": {
            "longitude": "-111.2759",
            "latitude": "46.4155"
          }
        }
      ]
    },
    {
      "raw_text": "WAUS43 KKCI 291522 AAA CHIT WA 291522 AMD AIRMET TANGO UPDT 4 FOR TURB VALID UNTIL 292100 AIRMET TURB...MN IA MO WI LM LS MI LH IL IN KY FROM 40ENE YQT TO 70NW YVV TO 40NE ECK TO 30ESE DXO TO FWA TO CVG TO HNN TO 40S HNN TO 30WNW DSM TO 20SSW MCW TO 60WSW YQT TO 40ENE YQT MOD TURB BTN FL200 AND FL430. CONDS CONTG BYD 21Z THRU 03Z. OTLK VALID 2100-0300Z...TURB KS IA MO IL IN KY OK AR TN LA MS AL BOUNDED BY 40ESE DSM-CVG-20SSE BKW-40NW HMV-60W VXV-30SE MSL- 40NE HRV-20S LSU-20ESE TXK-20NW FSM-20ESE OSW-40NE MCI-30W IRK- 40ESE DSM MOD TURB BTN FL200 AND FL430. CONDS CONTG THRU 03Z.",
      "valid_time_from": "2024-04-29T15:22:00Z",
      "valid_time_to": "2024-04-29T21:00:00Z",
      "altitude": {
        "min_ft_msl": "20000",
        "max_ft_msl": "43000"
      },
      "hazard": {
        "type": "TURB",
        "severity": "MOD"
      },
      "airsigmet_type": "AIRMET",
      "area": [
        {
          "point": {
            "longitude": "-88.3909",
            "latitude": "48.6207"
          }
        },
        {
          "point": {
            "longitude": "-82.2796",
            "latitude": "45.5698"
          }
        },
        {
          "point": {
            "longitude": "-82.0695",
            "latitude": "43.7282"
          }
        },
        {
          "point": {
            "longitude": "-82.7444",
            "latitude": "42.0158"
          }
        },
        {
          "point": {
            "longitude": "-85.19",
            "latitude": "40.98"
          }
        },
        {
          "point": {
            "longitude": "-84.7",
            "latitude": "39.02"
          }
        },
        {
          "point": {
            "longitude": "-82.03",
            "latitude": "38.75"
          }
        },
        {
          "point": {
            "longitude": "-82.03",
            "latitude": "38.0852"
          }
        },
        {
          "point": {
            "longitude": "-94.2718",
            "latitude": "41.6308"
          }
        },
        {
          "point": {
            "longitude": "-93.5033",
            "latitude": "42.7828"
          }
        },
        {
          "point": {
            "longitude": "-90.6963",
            "latitude": "47.9802"
          }
        },
        {
          "point": {
            "longitude": "-88.3909",
            "latitude": "48.6207"
          }
        }
      ]
    },
    {
      "raw_text": "WAUS43 KKCI 291522 AAA CHIT WA 291522 AMD AIRMET TANGO UPDT 4 FOR TURB VALID UNTIL 292100 AIRMET TURB...NE KS IA MO IL IN KY OK TX AR TN LA MS AL FROM 30WNW DSM TO 40S HNN TO 40E VXV TO GQO TO 50SSE LGC TO 20W TLH TO SJI TO 40SSE IGB TO 40NE MLU TO 50E CWK TO 60ENE TTT TO 50ESE SLN TO 30WNW DSM MOD TURB BTN FL200 AND FL430. CONDS CONTG BYD 21Z THRU 03Z. OTLK VALID 2100-0300Z...TURB KS IA MO IL IN KY OK AR TN LA MS AL BOUNDED BY 40ESE DSM-CVG-20SSE BKW-40NW HMV-60W VXV-30SE MSL- 40NE HRV-20S LSU-20ESE TXK-20NW FSM-20ESE OSW-40NE MCI-30W IRK- 40ESE DSM MOD TURB BTN FL200 AND FL430. CONDS CONTG THRU 03Z.",
      "valid_time_from": "2024-04-29T15:22:00Z",
      "valid_time_to": "2024-04-29T21:00:00Z",
      "altitude": {
        "min_ft_msl": "20000",
        "max_ft_msl": "43000"
      },
      "hazard": {
        "type": "TURB",
        "severity": "MOD"
      },
      "airsigmet_type": "AIRMET",
      "area": [
        {
          "point": {
            "longitude": "-94.2718",
            "latitude": "41.6308"
          }
        },
        {
          "point": {
            "longitude": "-82.03",
            "latitude": "38.0852"
          }
        },
        {
          "point": {
            "longitude": "-83.0694",
            "latitude": "35.8972"
          }
        },
        {
          "point": {
            "longitude": "-85.15",
            "latitude": "34.96"
          }
        },
        {
          "point": {
            "longitude": "-84.8319",
            "latitude": "32.2776"
          }
        },
        {
          "point": {
            "longitude": "-84.756",
            "latitude": "30.5594"
          }
        },
        {
          "point": {
            "longitude": "-88.36",
            "latitude": "30.73"
          }
        },
        {
          "point": {
            "longitude": "-88.2171",
            "latitude": "32.8655"
          }
        },
        {
          "point": {
            "longitude": "-91.4696",
            "latitude": "32.9888"
          }
        },
        {
          "point": {
            "longitude": "-96.5616",
            "latitude": "30.3764"
          }
        },
        {
          "point": {
            "longitude": "-95.9385",
            "latitude": "33.2468"
          }
        },
        {
          "point": {
            "longitude": "-96.6323",
            "latitude": "38.6061"
          }
        },
        {
          "point": {
            "longitude": "-94.2718",
            "latitude": "41.6308"
          }
        }
      ]
    },
    {
      "raw_text": "WAUS45 KKCI 291716 AAB SLCZ WA 291716 AMD AIRMET ZULU UPDT 4 FOR ICE AND FRZLVL VALID UNTIL 292100 AIRMET ICE...ID MT WY NV UT CO WA OR CA AND CSTL WTRS...UPDT FROM 70ESE YDC TO 50NNE GGW TO 30SW ISN TO 70SW RAP TO 30NNW BFF TO 30SSE HBU TO 20WSW DVC TO 20NNE BCE TO 50NE FOT TO 50SE EPH TO 70ESE YDC MOD ICE BTN FRZLVL AND 160. FRZLVL 040-090. CONDS CONTG BYD 21Z THRU 03Z. FRZLVL...RANGING FROM 040-145 ACRS AREA 080 ALG 50NNW FMG-80W BAM-30WNW TWF-60SSE LKT-MLS-100SE MLS 120 ALG 40W LAS-30SSW DRK-70SW SJN-30ESE DMN-30WNW INK-INK",
      "valid_time_from": "2024-04-29T17:16:00Z",
      "valid_time_to": "2024-04-29T21:00:00Z",
      "altitude": {
        "min_ft_msl": "4000",
        "max_ft_msl": "16000"
      },
      "hazard": {
        "type": "ICE",
        "severity": "MOD"
      },
      "airsigmet_type": "AIRMET",
      "area": [
        {
          "point": {
            "longitude": "-118.875",
            "latitude": "49.0114"
          }
        },
        {
          "point": {
            "longitude": "-106.1428",
            "latitude": "48.9908"
          }
        },
        {
          "point": {
            "longitude": "-104.1598",
            "latitude": "47.8231"
          }
        },
        {
          "point": {
            "longitude": "-104.1418",
            "latitude": "43.1486"
          }
        },
        {
          "point": {
            "longitude": "-103.7405",
            "latitude": "42.3545"
          }
        },
        {
          "point": {
            "longitude": "-106.7958",
            "latitude": "37.985"
          }
        },
        {
          "point": {
            "longitude": "-109.318",
            "latitude": "37.6822"
          }
        },
        {
          "point": {
            "longitude": "-112.1386",
            "latitude": "37.997"
          }
        },
        {
          "point": {
            "longitude": "-123.4442",
            "latitude": "41.2581"
          }
        },
        {
          "point": {
            "longitude": "-118.5573",
            "latitude": "46.786"
          }
        },
        {
          "point": {
            "longitude": "-118.875",
            "latitude": "49.0114"
          }
        }
      ]
    },
    {
      "raw_text": "WAUS41 KKCI 291716 AAB BOSZ WA 291716 AMD AIRMET ZULU UPDT 4 FOR ICE AND FRZLVL VALID UNTIL 292100 AIRMET ICE...ME NH VT MA RI CT NY LO AND CSTL WTRS...UPDT FROM 90SW YQB TO 20W MLT TO 160ENE ACK TO 100E ACK TO 20W HTO TO 20NNW ALB TO 50NNW SYR TO 20ESE YOW TO 90SW YQB MOD ICE BTN FRZLVL AND FL210. FRZLVL 080-120. CONDS CONTG BYD 21Z ENDG 00-03Z. OTLK VALID 2100-0300Z...ICE NY LO PA OH LE BOUNDED BY 50W YYZ-BUF-20SSW ERI-30S APE-60W HNN-CVG-FWA-30SE ECK-50W YYZ MOD ICE BTN FRZLVL AND FL200. FRZLVL 090-130. CONDS CONTG THRU 03Z. FRZLVL...RANGING FROM 020-135 ACRS AREA MULT FRZLVL 020-110 BOUNDED BY 80NW PQI-50NE PQI-60WSW YSJ- 40ENE MPV-30ENE MSS-80S YQB-80NW PQI 040 ALG 50SSE YQB-PQI-40E PQI 080 ALG 50WSW YOW-20N MPV-50WSW YSJ 120 ALG 40S FWA-60SW DXO-20ENE DXO 120 ALG 40WSW YYZ-40W ALB-20NNW ACK-70ESE ACK-140SSE ACK- 190SSE ACK",
      "valid_time_from": "2024-04-29T17:16:00Z",
      "valid_time_to": "2024-04-29T21:00:00Z",
      "altitude": {
        "min_ft_msl": "8000",
        "max_ft_msl": "21000"
      },
      "hazard": {
        "type": "ICE",
        "severity": "MOD"
      },
      "airsigmet_type": "AIRMET",
      "area": [
        {
          "point": {
            "longitude": "-72.8996",
            "latitude": "45.729"
          }
        },
        {
          "point": {
            "longitude": "-68.9949",
            "latitude": "45.579"
          }
        },
        {
          "point": {
            "longitude": "-66.7106",
            "latitude": "42.2503"
          }
        },
        {
          "point": {
            "longitude": "-67.819",
            "latitude": "41.2588"
          }
        },
        {
          "point": {
            "longitude": "-72.7599",
            "latitude": "40.9192"
          }
        },
        {
          "point": {
            "longitude": "-73.9741",
            "latitude": "43.0569"
          }
        },
        {
          "point": {
            "longitude": "-76.6439",
            "latitude": "43.931"
          }
        },
        {
          "point": {
            "longitude": "-75.2343",
            "latitude": "45.192"
          }
        },
        {
          "point": {
            "longitude": "-72.8996",
            "latitude": "45.729"
          }
        }
      ]
    },
    {
      "raw_text": "WAUS43 KKCI 291716 AAA CHIZ WA 291716 AMD AIRMET ZULU UPDT 3 FOR ICE AND FRZLVL VALID UNTIL 292100 AIRMET ICE...ND SD NE MN IA WI LM LS MI FROM 30N INL TO YQT TO 60ESE EAU TO 20NNW FOD TO 70S FSD TO 40NE ANW TO 30WNW PIR TO 50SE DIK TO 60NE ISN TO 30N INL MOD ICE BTN FRZLVL AND 170. FRZLVL 010-080. CONDS CONTG BYD 21Z THRU 03Z. OTLK VALID 2100-0300Z...ICE MO MI LH IL IN KY AR TN MS BOUNDED BY 20NNE SSM-50NW YVV-60SSW YVV-30SE ECK-FWA-CVG-60W HNN-40E BWG-50ESE MEM-50SSW ARG-40N ARG-50S AXC-20N MBS-30ENE TVC-20NNE SSM MOD ICE BTN FRZLVL AND FL200. FRZLVL 090-130. CONDS CONTG THRU 03Z. FRZLVL...RANGING FROM 015-135 ACRS AREA MULT FRZLVL 020-090 BOUNDED BY 40NW INL-YQT-90ESE YQT-20NNE DLH-70S DLH-20ESE EAU-20WNW RHI-30NW GRB-20SSW DLL-30WSW DBQ-50W DSM-30SE ONL-50NW ANW-50S DPR-30NE ISN-50NE MOT- 50N ABR-30S FAR-20N FAR-40NW INL 040 ALG 70NE MOT-30ENE BIS-40WSW ABR-60S ABR-30NNW FSD-20NE DLH-70N SAW 080 ALG 100SE MLS-30NE OBH-50SSW FOD-30NE RHI-20WSW SAW-70SE SSM-60NNE ASP 120 ALG 30WNW BNA-20N BWG-40S FWA",
      "valid_time_from": "2024-04-29T17:16:00Z",
      "valid_time_to": "2024-04-29T21:00:00Z",
      "altitude": {
        "min_ft_msl": "1000",
        "max_ft_msl": "17000"
      },
      "hazard": {
        "type": "ICE",
        "severity": "MOD"
      },
      "airsigmet_type": "AIRMET",
      "area": [
        {
          "point": {
            "longitude": "-93.4",
            "latitude": "49.0731"
          }
        },
        {
          "point": {
            "longitude": "-89.32",
            "latitude": "48.37"
          }
        },
        {
          "point": {
            "longitude": "-90.1881",
            "latitude": "44.5111"
          }
        },
        {
          "point": {
            "longitude": "-94.4637",
            "latitude": "42.9169"
          }
        },
        {
          "point": {
            "longitude": "-96.78",
            "latitude": "42.4822"
          }
        },
        {
          "point": {
            "longitude": "-99.3469",
            "latitude": "43.0383"
          }
        },
        {
          "point": {
            "longitude": "-100.8226",
            "latitude": "44.5907"
          }
        },
        {
          "point": {
            "longitude": "-101.9155",
            "latitude": "46.2661"
          }
        },
        {
          "point": {
            "longitude": "-102.5579",
            "latitude": "48.8801"
          }
        },
        {
          "point": {
            "longitude": "-93.4",
            "latitude": "49.0731"
          }
        }
      ]
    },
    {
      "raw_text": "WAUS44 KKCI 291716 AAA DFWZ WA 291716 AMD AIRMET ZULU UPDT 3 FOR ICE AND FRZLVL VALID UNTIL 292100 AIRMET ICE...AR TN MO WI LM LS MI LH IL IN KY...UPDT FROM YQT TO 70ESE YQT TO SSM TO YVV TO 40ESE ECK TO FWA TO 20N CVG TO 50NNW MSL TO 50E MEM TO MEM TO 20S ARG TO 60WSW FAM TO 20S BDF TO 30E DLL TO 60ESE EAU TO YQT MOD ICE BTN FRZLVL AND FL200. FRZLVL 090-130. CONDS CONTG BYD 21Z THRU 03Z. OTLK VALID 2100-0300Z...ICE AR TN MS MO MI LH IL IN KY BOUNDED BY 20NNE SSM-50NW YVV-60SSW YVV-30SE ECK-FWA-CVG-60W HNN-40E BWG-50ESE MEM-50SSW ARG-40N ARG-50S AXC-20N MBS-30ENE TVC-20NNE SSM MOD ICE BTN FRZLVL AND FL200. FRZLVL 090-130. CONDS CONTG THRU 03Z. FRZLVL...RANGING FROM 105-155 ACRS AREA 120 ALG INK-40E SJT-ACT-40NW TXK-50SSE MEM-50NNW MSL-30WNW BNA",
      "valid_time_from": "2024-04-29T17:16:00Z",
      "valid_time_to": "2024-04-29T21:00:00Z",
      "altitude": {
        "min_ft_msl": "9000",
        "max_ft_msl": "20000"
      },
      "hazard": {
        "type": "ICE",
        "severity": "MOD"
      },
      "airsigmet_type": "AIRMET",
      "area": [
        {
          "point": {
            "longitude": "-89.32",
            "latitude": "48.37"
          }
        },
        {
          "point": {
            "longitude": "-87.7102",
            "latitude": "47.9118"
          }
        },
        {
          "point": {
            "longitude": "-84.31",
            "latitude": "46.41"
          }
        },
        {
          "point": {
            "longitude": "-81.1",
            "latitude": "44.75"
          }
        },
        {
          "point": {
            "longitude": "-81.8802",
            "latitude": "43.0025"
          }
        },
        {
          "point": {
            "longitude": "-85.19",
            "latitude": "40.98"
          }
        },
        {
          "point": {
            "longitude": "-84.7",
            "latitude": "39.3524"
          }
        },
        {
          "point": {
            "longitude": "-87.8726",
            "latitude": "35.4712"
          }
        },
        {
          "point": {
            "longitude": "-88.9594",
            "latitude": "35.0557"
          }
        },
        {
          "point": {
            "longitude": "-89.98",
            "latitude": "35.06"
          }
        },
        {
          "point": {
            "longitude": "-90.95",
            "latitude": "35.7776"
          }
        },
        {
          "point": {
            "longitude": "-91.3878",
            "latitude": "37.2827"
          }
        },
        {
          "point": {
            "longitude": "-89.59",
            "latitude": "40.8276"
          }
        },
        {
          "point": {
            "longitude": "-89.0659",
            "latitude": "43.5479"
          }
        },
        {
          "point": {
            "longitude": "-90.1881",
            "latitude": "44.5111"
          }
        },
        {
          "point": {
            "longitude": "-89.32",
            "latitude": "48.37"
          }
        }
      ]
    },
    {
      "raw_text": "WAUS46 KKCI 291716 AAB SFOZ WA 291716 AMD AIRMET ZULU UPDT 4 FOR ICE AND FRZLVL VALID UNTIL 292100 AIRMET ICE...WA OR CA AND CSTL WTRS...UPDT FROM 40NE HUH TO 70ESE YDC TO 50SE EPH TO 50NE FOT TO 70NW FOT TO 140W OED TO 160W HQM TO 140W TOU TO 40NE HUH MOD ICE BTN FRZLVL AND 120. FRZLVL 030-050. CONDS CONTG BYD 21Z THRU 03Z. FRZLVL...RANGING FROM SFC-150 ACRS AREA MULT FRZLVL 040-080 BOUNDED BY 140WNW FOT-20NNW FOT-60ENE FOT- 30SW RBL-50WNW ENI-130WSW ENI-140WSW FOT-140WNW FOT 040 ALG 140WNW FOT-80NW FOT-30W OED-50S EPH-60NW GEG-80E YDC 080 ALG 140SW FOT-50NNW FMG 120 ALG 140WSW SNS-30W SNS-50WSW BTY-40W LAS",
      "valid_time_from": "2024-04-29T17:16:00Z",
      "valid_time_to": "2024-04-29T21:00:00Z",
      "altitude": {
        "min_ft_msl": "3000",
        "max_ft_msl": "12000"
      },
      "hazard": {
        "type": "ICE",
        "severity": "MOD"
      },
      "airsigmet_type": "AIRMET",
      "area": [
        {
          "point": {
            "longitude": "-121.8574",
            "latitude": "49.4178"
          }
        },
        {
          "point": {
            "longitude": "-118.875",
            "latitude": "49.0114"
          }
        },
        {
          "point": {
            "longitude": "-118.5573",
            "latitude": "46.786"
          }
        },
        {
          "point": {
            "longitude": "-123.4442",
            "latitude": "41.2581"
          }
        },
        {
          "point": {
            "longitude": "-125.3324",
            "latitude": "41.4906"
          }
        },
        {
          "point": {
            "longitude": "-126.0633",
            "latitude": "42.4368"
          }
        },
        {
          "point": {
            "longitude": "-128.042",
            "latitude": "46.884"
          }
        },
        {
          "point": {
            "longitude": "-128.1251",
            "latitude": "48.247"
          }
        },
        {
          "point": {
            "longitude": "-121.8574",
            "latitude": "49.4178"
          }
        }
      ]
    },
    {
      "raw_text": "WAUS41 KKCI 291716 AAB BOSZ WA 291716 AMD AIRMET ZULU UPDT 4 FOR ICE AND FRZLVL VALID UNTIL 292100 AIRMET ICE...OH LE...UPDT FROM 40ESE ECK TO 30SE DXO TO 30NE ROD TO 20N CVG TO FWA TO 40ESE ECK MOD ICE BTN FRZLVL AND FL200. FRZLVL 090-130. CONDS DVLPG AFT 15Z. CONDS CONTG BYD 21Z THRU 03Z. OTLK VALID 2100-0300Z...ICE NY LO PA OH LE BOUNDED BY 50W YYZ-BUF-20SSW ERI-30S APE-60W HNN-CVG-FWA-30SE ECK-50W YYZ MOD ICE BTN FRZLVL AND FL200. FRZLVL 090-130. CONDS CONTG THRU 03Z. FRZLVL...RANGING FROM 020-135 ACRS AREA MULT FRZLVL 020-110 BOUNDED BY 80NW PQI-50NE PQI-60WSW YSJ- 40ENE MPV-30ENE MSS-80S YQB-80NW PQI 040 ALG 50SSE YQB-PQI-40E PQI 080 ALG 50WSW YOW-20N MPV-50WSW YSJ 120 ALG 40S FWA-60SW DXO-20ENE DXO 120 ALG 40WSW YYZ-40W ALB-20NNW ACK-70ESE ACK-140SSE ACK- 190SSE ACK",
      "valid_time_from": "2024-04-29T17:16:00Z",
      "valid_time_to": "2024-04-29T21:00:00Z",
      "altitude": {
        "min_ft_msl": "9000",
        "max_ft_msl": "20000"
      },
      "hazard": {
        "type": "ICE",
        "severity": "MOD"
      },
      "airsigmet_type": "AIRMET",
      "area": [
        {
          "point": {
            "longitude": "-81.8802",
            "latitude": "43.0025"
          }
        },
        {
          "point": {
            "longitude": "-82.8924",
            "latitude": "41.8533"
          }
        },
        {
          "point": {
            "longitude": "-83.5712",
            "latitude": "40.6448"
          }
        },
        {
          "point": {
            "longitude": "-84.7",
            "latitude": "39.3524"
          }
        },
        {
          "point": {
            "longitude": "-85.19",
            "latitude": "40.98"
          }
        },
        {
          "point": {
            "longitude": "-81.8802",
            "latitude": "43.0025"
          }
        }
      ]
    },
    {
      "raw_text": "WAUS43 KKCI 291716 AAA CHIZ WA 291716 AMD AIRMET ZULU UPDT 3 FOR ICE AND FRZLVL VALID UNTIL 292100 AIRMET ICE...ND SD NE...UPDT FROM 30SW ISN TO DIK TO 20WNW DPR TO 20ESE RAP TO 30NNW BFF TO 70SW RAP TO 30SW ISN MOD ICE BTN FRZLVL AND 160. FRZLVL 040-090. CONDS DVLPG AFT 18Z. CONDS CONTG BYD 21Z THRU 03Z. OTLK VALID 2100-0300Z...ICE MO MI LH IL IN KY AR TN MS BOUNDED BY 20NNE SSM-50NW YVV-60SSW YVV-30SE ECK-FWA-CVG-60W HNN-40E BWG-50ESE MEM-50SSW ARG-40N ARG-50S AXC-20N MBS-30ENE TVC-20NNE SSM MOD ICE BTN FRZLVL AND FL200. FRZLVL 090-130. CONDS CONTG THRU 03Z. FRZLVL...RANGING FROM 015-135 ACRS AREA MULT FRZLVL 020-090 BOUNDED BY 40NW INL-YQT-90ESE YQT-20NNE DLH-70S DLH-20ESE EAU-20WNW RHI-30NW GRB-20SSW DLL-30WSW DBQ-50W DSM-30SE ONL-50NW ANW-50S DPR-30NE ISN-50NE MOT- 50N ABR-30S FAR-20N FAR-40NW INL 040 ALG 70NE MOT-30ENE BIS-40WSW ABR-60S ABR-30NNW FSD-20NE DLH-70N SAW 080 ALG 100SE MLS-30NE OBH-50SSW FOD-30NE RHI-20WSW SAW-70SE SSM-60NNE ASP 120 ALG 30WNW BNA-20N BWG-40S FWA",
      "valid_time_from": "2024-04-29T17:16:00Z",
      "valid_time_to": "2024-04-29T21:00:00Z",
      "altitude": {
        "min_ft_msl": "4000",
        "max_ft_msl": "16000"
      },
      "hazard": {
        "type": "ICE",
        "severity": "MOD"
      },
      "airsigmet_type": "AIRMET",
      "area": [
        {
          "point": {
            "longitude": "-104.1598",
            "latitude": "47.8231"
          }
        },
        {
          "point": {
            "longitude": "-102.77",
            "latitude": "46.86"
          }
        },
        {
          "point": {
            "longitude": "-102.1558",
            "latitude": "45.2064"
          }
        },
        {
          "point": {
            "longitude": "-102.5842",
            "latitude": "43.852"
          }
        },
        {
          "point": {
            "longitude": "-103.7405",
            "latitude": "42.3545"
          }
        },
        {
          "point": {
            "longitude": "-104.1418",
            "latitude": "43.1486"
          }
        },
        {
          "point": {
            "longitude": "-104.1598",
            "latitude": "47.8231"
          }
        }
      ]
    },
    {
      "raw_text": "WAUS46 KKCI 291716 AAB SFOZ WA 291716 AMD AIRMET ZULU UPDT 4 FOR ICE AND FRZLVL VALID UNTIL 292100 AIRMET ICE...WA OR CA ID MT WY NV UT CO AND CSTL WTRS...UPDT FROM 70ESE YDC TO 50NNE GGW TO 30SW ISN TO 70SW RAP TO 30NNW BFF TO 30SSE HBU TO 20WSW DVC TO 20NNE BCE TO 50NE FOT TO 50SE EPH TO 70ESE YDC MOD ICE BTN FRZLVL AND 160. FRZLVL 040-090. CONDS CONTG BYD 21Z THRU 03Z. FRZLVL...RANGING FROM SFC-150 ACRS AREA MULT FRZLVL 040-080 BOUNDED BY 140WNW FOT-20NNW FOT-60ENE FOT- 30SW RBL-50WNW ENI-130WSW ENI-140WSW FOT-140WNW FOT 040 ALG 140WNW FOT-80NW FOT-30W OED-50S EPH-60NW GEG-80E YDC 080 ALG 140SW FOT-50NNW FMG 120 ALG 140WSW SNS-30W SNS-50WSW BTY-40W LAS",
      "valid_time_from": "2024-04-29T17:16:00Z",
      "valid_time_to": "2024-04-29T21:00:00Z",
      "altitude": {
        "min_ft_msl": "4000",
        "max_ft_msl": "16000"
      },
      "hazard": {
        "type": "ICE",
        "severity": "MOD"
      },
      "airsigmet_type": "AIRMET",
      "area": [
        {
          "point": {
            "longitude": "-118.875",
            "latitude": "49.0114"
          }
        },
        {
          "point": {
            "longitude": "-106.1428",
            "latitude": "48.9908"
          }
        },
        {
          "point": {
            "longitude": "-104.1598",
            "latitude": "47.8231"
          }
        },
        {
          "point": {
            "longitude": "-104.1418",
            "latitude": "43.1486"
          }
        },
        {
          "point": {
            "longitude": "-103.7405",
            "latitude": "42.3545"
          }
        },
        {
          "point": {
            "longitude": "-106.7958",
            "latitude": "37.985"
          }
        },
        {
          "point": {
            "longitude": "-109.318",
            "latitude": "37.6822"
          }
        },
        {
          "point": {
            "longitude": "-112.1386",
            "latitude": "37.997"
          }
        },
        {
          "point": {
            "longitude": "-123.4442",
            "latitude": "41.2581"
          }
        },
        {
          "point": {
            "longitude": "-118.5573",
            "latitude": "46.786"
          }
        },
        {
          "point": {
            "longitude": "-118.875",
            "latitude": "49.0114"
          }
        }
      ]
    },
    {
      "raw_text": "WAUS43 KKCI 291716 AAA CHIZ WA 291716 AMD AIRMET ZULU UPDT 3 FOR ICE AND FRZLVL VALID UNTIL 292100 AIRMET ICE...MO WI LM LS MI LH IL IN KY AR TN...UPDT FROM YQT TO 70ESE YQT TO SSM TO YVV TO 40ESE ECK TO FWA TO 20N CVG TO 50NNW MSL TO 50E MEM TO MEM TO 20S ARG TO 60WSW FAM TO 20S BDF TO 30E DLL TO 60ESE EAU TO YQT MOD ICE BTN FRZLVL AND FL200. FRZLVL 090-130. CONDS CONTG BYD 21Z THRU 03Z. OTLK VALID 2100-0300Z...ICE MO MI LH IL IN KY AR TN MS BOUNDED BY 20NNE SSM-50NW YVV-60SSW YVV-30SE ECK-FWA-CVG-60W HNN-40E BWG-50ESE MEM-50SSW ARG-40N ARG-50S AXC-20N MBS-30ENE TVC-20NNE SSM MOD ICE BTN FRZLVL AND FL200. FRZLVL 090-130. CONDS CONTG THRU 03Z. FRZLVL...RANGING FROM 015-135 ACRS AREA MULT FRZLVL 020-090 BOUNDED BY 40NW INL-YQT-90ESE YQT-20NNE DLH-70S DLH-20ESE EAU-20WNW RHI-30NW GRB-20SSW DLL-30WSW DBQ-50W DSM-30SE ONL-50NW ANW-50S DPR-30NE ISN-50NE MOT- 50N ABR-30S FAR-20N FAR-40NW INL 040 ALG 70NE MOT-30ENE BIS-40WSW ABR-60S ABR-30NNW FSD-20NE DLH-70N SAW 080 ALG 100SE MLS-30NE OBH-50SSW FOD-30NE RHI-20WSW SAW-70SE SSM-60NNE ASP 120 ALG 30WNW BNA-20N BWG-40S FWA",
      "valid_time_from": "2024-04-29T17:16:00Z",
      "valid_time_to": "2024-04-29T21:00:00Z",
      "altitude": {
        "min_ft_msl": "9000",
        "max_ft_msl": "20000"
      },
      "hazard": {
        "type": "ICE",
        "severity": "MOD"
      },
      "airsigmet_type": "AIRMET",
      "area": [
        {
          "point": {
            "longitude": "-89.32",
            "latitude": "48.37"
          }
        },
        {
          "point": {
            "longitude": "-87.7102",
            "latitude": "47.9118"
          }
        },
        {
          "point": {
            "longitude": "-84.31",
            "latitude": "46.41"
          }
        },
        {
          "point": {
            "longitude": "-81.1",
            "latitude": "44.75"
          }
        },
        {
          "point": {
            "longitude": "-81.8802",
            "latitude": "43.0025"
          }
        },
        {
          "point": {
            "longitude": "-85.19",
            "latitude": "40.98"
          }
        },
        {
          "point": {
            "longitude": "-84.7",
            "latitude": "39.3524"
          }
        },
        {
          "point": {
            "longitude": "-87.8726",
            "latitude": "35.4712"
          }
        },
        {
          "point": {
            "longitude": "-88.9594",
            "latitude": "35.0557"
          }
        },
        {
          "point": {
            "longitude": "-89.98",
            "latitude": "35.06"
          }
        },
        {
          "point": {
            "longitude": "-90.95",
            "latitude": "35.7776"
          }
        },
        {
          "point": {
            "longitude": "-91.3878",
            "latitude": "37.2827"
          }
        },
        {
          "point": {
            "longitude": "-89.59",
            "latitude": "40.8276"
          }
        },
        {
          "point": {
            "longitude": "-89.0659",
            "latitude": "43.5479"
          }
        },
        {
          "point": {
            "longitude": "-90.1881",
            "latitude": "44.5111"
          }
        },
        {
          "point": {
            "longitude": "-89.32",
            "latitude": "48.37"
          }
        }
      ]
    }
  ]
}