{
  "source": {
    "name": "Airframes Project",
    "url": "https://github.com/airframesio",
    "email": "kevin@airframes.io"
  },
  "attribution": {
    "name": "NOAA NWS Aviation Weather Center",
    "url": "https://www.aviationweather.gov/adds/dataserver_current/current/airsigmets.cache.xml"
  },
  "resource_type": "airsigmets",
  "count": 32,
  "airsigmets": [
    {
      "raw_text": "WAUS46 KKCI 140245 SFOT WA 140245 AIRMET TANGO FOR TURB AND STG SFC WNDS VALID UNTIL 140900 AIRMET STG SFC WNDS...OR CA CSTL WTRS FROM 80W OED TO 20WSW FOT TO 30WSW PYE TO 110WSW PYE TO 100W FOT TO 80W OED SUSTAINED SURFACE WINDS GTR THAN 30KT EXP. CONDS CONTG BYD 09Z THRU 15Z.",
      "valid_time_from": "2021-05-14T02:45:00Z",
      "valid_time_to": "2021-05-14T09:00:00Z",
      "altitude": {
        "min_ft_msl": "0"
      },
      "hazard": {
        "type": "TURB"
      },
      "airsigmet_type": "AIRMET",
      "area": [
        {
          "point": {
            "longitude": "-124.7124",
            "latitude": "42.4659"
          }
        },
        {
          "point": {
            "longitude": "-124.6341",
            "latitude": "40.5421"
          }
        },
        {
          "point": {
            "longitude": "-123.4589",
            "latitude": "37.886"
          }
        },
        {
          "point": {
            "longitude": "-125.0002",
            "latitude": "37.3594"
          }
        },
        {
          "point": {
            "longitude": "-126.4206",
            "latitude": "40.6493"
          }
        },
        {
          "point": {
            "longitude": "-124.7124",
            "latitude": "42.4659"
          }
        }
      ]
    },
    {
      "raw_text": "WSUS32 KKCI 140255 SIGC OUTLOOK VALID 140455-140855 FROM GFK-50NE RWF-50ESE SLN-70E GCK-40ESE SNY-30W FSD-60NNW ABR-GFK WST ISSUANCES POSS. REFER TO MOST RECENT ACUS01 KWNS FROM STORM PREDICTION CENTER FOR SYNOPSIS AND METEOROLOGICAL DETAILS.",
      "valid_time_from": "2021-05-14T04:55:00Z",
      "valid_time_to": "2021-05-14T08:55:00Z",
      "hazard": {
        "type": "CONVECTIVE"
      },
      "airsigmet_type": "OUTLOOK",
      "area": [
        {
          "point": {
            "longitude": "-97.19",
            "latitude": "47.95"
          }
        },
        {
          "point": {
            "longitude": "-94.2937",
            "latitude": "45.0577"
          }
        },
        {
          "point": {
            "longitude": "-96.6323",
            "latitude": "38.6061"
          }
        },
        {
          "point": {
            "longitude": "-99.2498",
            "latitude": "37.9107"
          }
        },
        {
          "point": {
            "longitude": "-102.1682",
            "latitude": "40.8428"
          }
        },
        {
          "point": {
            "longitude": "-97.4752",
            "latitude": "43.6479"
          }
        },
        {
          "point": {
            "longitude": "-98.9227",
            "latitude": "46.3399"
          }
        },
        {
          "point": {
            "longitude": "-97.19",
            "latitude": "47.95"
          }
        }
      ],
      "altitude": {
      }
    },
    {
      "raw_text": "WAUS44 KKCI 140245 DFWT WA 140245 AIRMET TANGO FOR TURB AND LLWS VALID UNTIL 140900 AIRMET TURB...OK TX LA MS AND CSTL WTRS FROM 40N CDS TO 40SE HRV TO 110SSE LCH TO SAT TO 20S DLF TO ELP TO INK TO TXO TO 40N CDS MOD TURB BTN FL280 AND FL410. CONDS CONTG BYD 09Z THRU 15Z. LLWS POTENTIAL...OK TX NE KS BOUNDED BY 60W ANW-30SSW OBH-20WSW SLN-MMB-60ESE CIM-30ESE TBE- 50W LBL-GLD-40SSE SNY-60W ANW LLWS EXP. CONDS CONTG BYD 09Z ENDG 12-15Z. OTLK VALID 0900-1500Z AREA 1...TURB OK AR TN MS AL SD NE KS MN IA MO WI LM MI IL IN KY BOUNDED BY 40SW RHI-GRR-20SE VXV-GQO-20WNW PZD-50SSW VUZ-SLN-FSD- 20NNW RWF-40SW RHI MOD TURB BTN FL290 AND FL390. CONDS CONTG THRU 15Z. AREA 2...TURB OK TX AR LA MS AL AND CSTL WTRS BOUNDED BY 30WSW OKC-40NNW ELD-40E SJI-120ESE LEV-110SSE LCH- 30NNW DLF-INK-40NNW CDS-30WSW OKC MOD TURB BTN FL280 AND FL410. CONDS CONTG THRU 15Z.",
      "valid_time_from": "2021-05-14T02:45:00Z",
      "valid_time_to": "2021-05-14T09:00:00Z",
      "altitude": {
        "min_ft_msl": "28000",
        "max_ft_msl": "41000"
      },
      "hazard": {
        "type": "TURB",
        "severity": "MOD"
      },
      "airsigmet_type": "AIRMET",
      "area": [
        {
          "point": {
            "longitude": "-100.28",
            "latitude": "35.0348"
          }
        },
        {
          "point": {
            "longitude": "-89.4606",
            "latitude": "29.3789"
          }
        },
        {
          "point": {
            "longitude": "-92.3125",
            "latitude": "28.4445"
          }
        },
        {
          "point": {
            "longitude": "-98.46",
            "latitude": "29.64"
          }
        },
        {
          "point": {
            "longitude": "-100.77",
            "latitude": "29.0276"
          }
        },
        {
          "point": {
            "longitude": "-106.28",
            "latitude": "31.82"
          }
        },
        {
          "point": {
            "longitude": "-103.24",
            "latitude": "31.87"
          }
        },
        {
          "point": {
            "longitude": "-102.84",
            "latitude": "34.5"
          }
        },
        {
          "point": {
            "longitude": "-100.28",
            "latitude": "35.0348"
          }
        }
      ]
    },
    {
      "raw_text": "WAUS46 KKCI 140245 SFOT WA 140245 AIRMET TANGO FOR TURB AND STG SFC WNDS VALID UNTIL 140900 AIRMET TURB...CA AND CSTL WTRS FROM LAS TO 60SSE TRM TO MZB TO LAX TO 40W RZS TO 20W EHF TO LAS MOD TURB BLW 120. CONDS ENDG 03-06Z.",
      "valid_time_from": "2021-05-14T02:45:00Z",
      "valid_time_to": "2021-05-14T09:00:00Z",
      "altitude": {
        "min_ft_msl": "0",
        "max_ft_msl": "12000"
      },
      "hazard": {
        "type": "TURB",
        "severity": "MOD"
      },
      "airsigmet_type": "AIRMET",
      "area": [
        {
          "point": {
            "longitude": "-115.16",
            "latitude": "36.08"
          }
        },
        {
          "point": {
            "longitude": "-115.7065",
            "latitude": "32.7079"
          }
        },
        {
          "point": {
            "longitude": "-117.23",
            "latitude": "32.78"
          }
        },
        {
          "point": {
            "longitude": "-118.43",
            "latitude": "33.93"
          }
        },
        {
          "point": {
            "longitude": "-120.5767",
            "latitude": "34.5073"
          }
        },
        {
          "point": {
            "longitude": "-119.5082",
            "latitude": "35.4793"
          }
        },
        {
          "point": {
            "longitude": "-115.16",
            "latitude": "36.08"
          }
        }
      ]
    },
    {
      "raw_text": "WSUS32 KKCI 140255 SIGC CONVECTIVE SIGMET 15C VALID UNTIL 0455Z KS FROM 20SE GLD-50SE HLC-10E GCK-50NW GCK-20SE GLD AREA SEV TS MOV FROM 32020KT. TOPS TO FL390. HAIL TO 1 IN...WIND GUSTS TO 55KT POSS. OUTLOOK VALID 140455-140855 FROM GFK-50NE RWF-50ESE SLN-70E GCK-40ESE SNY-30W FSD-60NNW ABR-GFK WST ISSUANCES POSS. REFER TO MOST RECENT ACUS01 KWNS FROM STORM PREDICTION CENTER FOR SYNOPSIS AND METEOROLOGICAL DETAILS.",
      "valid_time_from": "2021-05-14T02:55:00Z",
      "valid_time_to": "2021-05-14T04:55:00Z",
      "altitude": {
        "max_ft_msl": "39000"
      },
      "movement_dir_degrees": "320",
      "movement_speed_kt": "20",
      "hazard": {
        "type": "CONVECTIVE",
        "severity": "LT-MOD"
      },
      "airsigmet_type": "SIGMET",
      "area": [
        {
          "point": {
            "longitude": "-101.3869",
            "latitude": "39.1546"
          }
        },
        {
          "point": {
            "longitude": "-99.4734",
            "latitude": "38.6668"
          }
        },
        {
          "point": {
            "longitude": "-100.5136",
            "latitude": "37.9198"
          }
        },
        {
          "point": {
            "longitude": "-101.4849",
            "latitude": "38.5083"
          }
        },
        {
          "point": {
            "longitude": "-101.3869",
            "latitude": "39.1546"
          }
        }
      ]
    },
    {
      "raw_text": "WSUS32 KKCI 140255 SIGC CONVECTIVE SIGMET 16C VALID UNTIL 0455Z KS NE FROM 40WNW OBH-30ENE OBH-60E HLC-20S MCK-40WNW OBH AREA TS MOV FROM 29020KT. TOPS TO FL350. OUTLOOK VALID 140455-140855 FROM GFK-50NE RWF-50ESE SLN-70E GCK-40ESE SNY-30W FSD-60NNW ABR-GFK WST ISSUANCES POSS. REFER TO MOST RECENT ACUS01 KWNS FROM STORM PREDICTION CENTER FOR SYNOPSIS AND METEOROLOGICAL DETAILS.",
      "valid_time_from": "2021-05-14T02:55:00Z",
      "valid_time_to": "2021-05-14T04:55:00Z",
      "altitude": {
        "max_ft_msl": "35000"
      },
      "movement_dir_degrees": "290",
      "movement_speed_kt": "20",
      "hazard": {
        "type": "CONVECTIVE",
        "severity": "LT-MOD"
      },
      "airsigmet_type": "SIGMET",
      "area": [
        {
          "point": {
            "longitude": "-99.1717",
            "latitude": "41.6315"
          }
        },
        {
          "point": {
            "longitude": "-97.7288",
            "latitude": "41.5708"
          }
        },
        {
          "point": {
            "longitude": "-98.9423",
            "latitude": "39.2529"
          }
        },
        {
          "point": {
            "longitude": "-100.59",
            "latitude": "39.8676"
          }
        },
        {
          "point": {
            "longitude": "-99.1717",
            "latitude": "41.6315"
          }
        }
      ]
    },
    {
      "raw_text": "WSUS32 KKCI 140255 SIGC CONVECTIVE SIGMET 13C VALID UNTIL 0455Z MN SD ND FROM 20W FAR-60S FAR-20ESE ABR-60N ABR-20W FAR AREA TS MOV FROM 25010KT. TOPS TO FL320. OUTLOOK VALID 140455-140855 FROM GFK-50NE RWF-50ESE SLN-70E GCK-40ESE SNY-30W FSD-60NNW ABR-GFK WST ISSUANCES POSS. REFER TO MOST RECENT ACUS01 KWNS FROM STORM PREDICTION CENTER FOR SYNOPSIS AND METEOROLOGICAL DETAILS.",
      "valid_time_from": "2021-05-14T02:55:00Z",
      "valid_time_to": "2021-05-14T04:55:00Z",
      "altitude": {
        "max_ft_msl": "32000"
      },
      "movement_dir_degrees": "250",
      "movement_speed_kt": "10",
      "hazard": {
        "type": "CONVECTIVE",
        "severity": "LT-MOD"
      },
      "airsigmet_type": "SIGMET",
      "area": [
        {
          "point": {
            "longitude": "-97.3351",
            "latitude": "46.749"
          }
        },
        {
          "point": {
            "longitude": "-96.85",
            "latitude": "45.7529"
          }
        },
        {
          "point": {
            "longitude": "-97.9335",
            "latitude": "45.292"
          }
        },
        {
          "point": {
            "longitude": "-98.37",
            "latitude": "46.4171"
          }
        },
        {
          "point": {
            "longitude": "-97.3351",
            "latitude": "46.749"
          }
        }
      ]
    },
    {
      "raw_text": "WSUS32 KKCI 140255 SIGC CONVECTIVE SIGMET 14C VALID UNTIL 0455Z SD FROM 20SE ABR-40N FSD-30WSW FSD-50S ABR-20SE ABR AREA TS MOV FROM 26010KT. TOPS TO FL280. OUTLOOK VALID 140455-140855 FROM GFK-50NE RWF-50ESE SLN-70E GCK-40ESE SNY-30W FSD-60NNW ABR-GFK WST ISSUANCES POSS. REFER TO MOST RECENT ACUS01 KWNS FROM STORM PREDICTION CENTER FOR SYNOPSIS AND METEOROLOGICAL DETAILS.",
      "valid_time_from": "2021-05-14T02:55:00Z",
      "valid_time_to": "2021-05-14T04:55:00Z",
      "altitude": {
        "max_ft_msl": "28000"
      },
      "movement_dir_degrees": "260",
      "movement_speed_kt": "10",
      "hazard": {
        "type": "CONVECTIVE",
        "severity": "LT-MOD"
      },
      "airsigmet_type": "SIGMET",
      "area": [
        {
          "point": {
            "longitude": "-98.0365",
            "latitude": "45.1845"
          }
        },
        {
          "point": {
            "longitude": "-96.78",
            "latitude": "44.3148"
          }
        },
        {
          "point": {
            "longitude": "-97.4203",
            "latitude": "43.4557"
          }
        },
        {
          "point": {
            "longitude": "-98.37",
            "latitude": "44.5846"
          }
        },
        {
          "point": {
            "longitude": "-98.0365",
            "latitude": "45.1845"
          }
        }
      ]
    },
    {
      "raw_text": "WSUS31 KKCI 140255 SIGE OUTLOOK VALID 140455-140855 FROM 100SE ILM-130SE ILM-140SSE ILM-160E PBI-30NE PBI-60NNE TRV-100SE CHS-100SE ILM WST ISSUANCES POSS. REFER TO MOST RECENT ACUS01 KWNS FROM STORM PREDICTION CENTER FOR SYNOPSIS AND METEOROLOGICAL DETAILS.",
      "valid_time_from": "2021-05-14T04:55:00Z",
      "valid_time_to": "2021-05-14T08:55:00Z",
      "hazard": {
        "type": "CONVECTIVE"
      },
      "airsigmet_type": "OUTLOOK",
      "area": [
        {
          "point": {
            "longitude": "-76.4662",
            "latitude": "33.1668"
          }
        },
        {
          "point": {
            "longitude": "-76.0488",
            "latitude": "32.8056"
          }
        },
        {
          "point": {
            "longitude": "-76.8181",
            "latitude": "32.1959"
          }
        },
        {
          "point": {
            "longitude": "-77.1147",
            "latitude": "26.649"
          }
        },
        {
          "point": {
            "longitude": "-79.6906",
            "latitude": "27.0352"
          }
        },
        {
          "point": {
            "longitude": "-80.0554",
            "latitude": "28.6005"
          }
        },
        {
          "point": {
            "longitude": "-78.6588",
            "latitude": "31.7073"
          }
        },
        {
          "point": {
            "longitude": "-76.4662",
            "latitude": "33.1668"
          }
        }
      ],
      "altitude": {
      }
    },
    {
      "raw_text": "WSUS31 KKCI 140255 SIGE CONVECTIVE SIGMET 6E VALID UNTIL 0455Z FL CSTL WTRS FROM 100NE TRV-90ENE PBI-30ENE PBI-30ENE TRV-100NE TRV AREA TS MOV FROM 29015KT. TOPS TO FL260. OUTLOOK VALID 140455-140855 FROM 100SE ILM-130SE ILM-140SSE ILM-160E PBI-30NE PBI-60NNE TRV-100SE CHS-100SE ILM WST ISSUANCES POSS. REFER TO MOST RECENT ACUS01 KWNS FROM STORM PREDICTION CENTER FOR SYNOPSIS AND METEOROLOGICAL DETAILS.",
      "valid_time_from": "2021-05-14T02:55:00Z",
      "valid_time_to": "2021-05-14T04:55:00Z",
      "altitude": {
        "max_ft_msl": "26000"
      },
      "movement_dir_degrees": "290",
      "movement_speed_kt": "15",
      "hazard": {
        "type": "CONVECTIVE",
        "severity": "LT-MOD"
      },
      "airsigmet_type": "SIGMET",
      "area": [
        {
          "point": {
            "longitude": "-79.1484",
            "latitude": "28.8487"
          }
        },
        {
          "point": {
            "longitude": "-78.531",
            "latitude": "27.2456"
          }
        },
        {
          "point": {
            "longitude": "-79.569",
            "latitude": "26.8716"
          }
        },
        {
          "point": {
            "longitude": "-79.9642",
            "latitude": "27.8715"
          }
        },
        {
          "point": {
            "longitude": "-79.1484",
            "latitude": "28.8487"
          }
        }
      ]
    },
    {
      "raw_text": "WSUS32 KKCI 140255 SIGC CONVECTIVE SIGMET 17C VALID UNTIL 0455Z TX NM FROM 60NE ELP-70ENE ELP-40ENE ELP-40NE ELP-60NE ELP AREA TS MOV FROM 30010KT. TOPS TO FL370. OUTLOOK VALID 140455-140855 FROM GFK-50NE RWF-50ESE SLN-70E GCK-40ESE SNY-30W FSD-60NNW ABR-GFK WST ISSUANCES POSS. REFER TO MOST RECENT ACUS01 KWNS FROM STORM PREDICTION CENTER FOR SYNOPSIS AND METEOROLOGICAL DETAILS.",
      "valid_time_from": "2021-05-14T02:55:00Z",
      "valid_time_to": "2021-05-14T04:55:00Z",
      "altitude": {
        "max_ft_msl": "37000"
      },
      "movement_dir_degrees": "300",
      "movement_speed_kt": "10",
      "hazard": {
        "type": "CONVECTIVE",
        "severity": "LT-MOD"
      },
      "airsigmet_type": "SIGMET",
      "area": [
        {
          "point": {
            "longitude": "-105.4438",
            "latitude": "32.5223"
          }
        },
        {
          "point": {
            "longitude": "-105.0041",
            "latitude": "32.2605"
          }
        },
        {
          "point": {
            "longitude": "-105.5552",
            "latitude": "32.0723"
          }
        },
        {
          "point": {
            "longitude": "-105.724",
            "latitude": "32.2888"
          }
        },
        {
          "point": {
            "longitude": "-105.4438",
            "latitude": "32.5223"
          }
        }
      ]
    },
    {
      "raw_text": "WSUS32 KKCI 140255 SIGC CONVECTIVE SIGMET 18C VALID UNTIL 0455Z NE FROM 50NW LBF-50E LBF-20ENE MCK-40E SNY-50NW LBF AREA TS MOV FROM 32030KT. TOPS TO FL440. OUTLOOK VALID 140455-140855 FROM GFK-50NE RWF-50ESE SLN-70E GCK-40ESE SNY-30W FSD-60NNW ABR-GFK WST ISSUANCES POSS. REFER TO MOST RECENT ACUS01 KWNS FROM STORM PREDICTION CENTER FOR SYNOPSIS AND METEOROLOGICAL DETAILS.",
      "valid_time_from": "2021-05-14T02:55:00Z",
      "valid_time_to": "2021-05-14T04:55:00Z",
      "altitude": {
        "max_ft_msl": "44000"
      },
      "movement_dir_degrees": "320",
      "movement_speed_kt": "30",
      "hazard": {
        "type": "CONVECTIVE",
        "severity": "LT-MOD"
      },
      "airsigmet_type": "SIGMET",
      "area": [
        {
          "point": {
            "longitude": "-101.5114",
            "latitude": "41.718"
          }
        },
        {
          "point": {
            "longitude": "-99.6109",
            "latitude": "41.1247"
          }
        },
        {
          "point": {
            "longitude": "-100.1872",
            "latitude": "40.3265"
          }
        },
        {
          "point": {
            "longitude": "-102.0979",
            "latitude": "41.0966"
          }
        },
        {
          "point": {
            "longitude": "-101.5114",
            "latitude": "41.718"
          }
        }
      ]
    },
    {
      "raw_text": "WSUS33 KKCI 140255 SIGW CONVECTIVE SIGMET 7W VALID UNTIL 0455Z NV CA FROM 80N FMG-60E FMG-40SE FMG-60NW FMG-80N FMG AREA TS MOV FROM 26005KT. TOPS TO FL330. OUTLOOK VALID 140455-140855 TS ARE NOT EXPD TO REQUIRE WST ISSUANCES.",
      "valid_time_from": "2021-05-14T02:55:00Z",
      "valid_time_to": "2021-05-14T04:55:00Z",
      "altitude": {
        "max_ft_msl": "33000"
      },
      "movement_dir_degrees": "260",
      "movement_speed_kt": "5",
      "hazard": {
        "type": "CONVECTIVE",
        "severity": "LT-MOD"
      },
      "airsigmet_type": "SIGMET",
      "area": [
        {
          "point": {
            "longitude": "-119.66",
            "latitude": "40.8595"
          }
        },
        {
          "point": {
            "longitude": "-118.3673",
            "latitude": "39.5228"
          }
        },
        {
          "point": {
            "longitude": "-119.0547",
            "latitude": "39.0584"
          }
        },
        {
          "point": {
            "longitude": "-120.5835",
            "latitude": "40.2314"
          }
        },
        {
          "point": {
            "longitude": "-119.66",
            "latitude": "40.8595"
          }
        }
      ]
    },
    {
      "raw_text": "WSUS33 KKCI 140255 SIGW CONVECTIVE SIGMET 6W VALID UNTIL 0455Z MT FROM 40WNW HVR-10NNW HVR-20SW HVR-40WSW HVR-40WNW HVR AREA TS MOV FROM 31020KT. TOPS TO FL330. OUTLOOK VALID 140455-140855 TS ARE NOT EXPD TO REQUIRE WST ISSUANCES.",
      "valid_time_from": "2021-05-14T02:55:00Z",
      "valid_time_to": "2021-05-14T04:55:00Z",
      "altitude": {
        "max_ft_msl": "33000"
      },
      "movement_dir_degrees": "310",
      "movement_speed_kt": "20",
      "hazard": {
        "type": "CONVECTIVE",
        "severity": "LT-MOD"
      },
      "airsigmet_type": "SIGMET",
      "area": [
        {
          "point": {
            "longitude": "-110.7022",
            "latitude": "48.7906"
          }
        },
        {
          "point": {
            "longitude": "-109.869",
            "latitude": "48.6976"
          }
        },
        {
          "point": {
            "longitude": "-110.1233",
            "latitude": "48.3044"
          }
        },
        {
          "point": {
            "longitude": "-110.6929",
            "latitude": "48.2819"
          }
        },
        {
          "point": {
            "longitude": "-110.7022",
            "latitude": "48.7906"
          }
        }
      ]
    },
    {
      "raw_text": "WSUS31 KKCI 140255 SIGE CONVECTIVE SIGMET 7E VALID UNTIL 0455Z FL AND CSTL WTRS FROM 60E PBI-80SE MIA-60SE MIA-20NNE MIA-60E PBI DMSHG AREA TS MOV FROM 25010KT. TOPS TO FL290. OUTLOOK VALID 140455-140855 FROM 100SE ILM-130SE ILM-140SSE ILM-160E PBI-30NE PBI-60NNE TRV-100SE CHS-100SE ILM WST ISSUANCES POSS. REFER TO MOST RECENT ACUS01 KWNS FROM STORM PREDICTION CENTER FOR SYNOPSIS AND METEOROLOGICAL DETAILS.",
      "valid_time_from": "2021-05-14T02:55:00Z",
      "valid_time_to": "2021-05-14T04:55:00Z",
      "altitude": {
        "max_ft_msl": "29000"
      },
      "movement_dir_degrees": "250",
      "movement_speed_kt": "10",
      "hazard": {
        "type": "CONVECTIVE",
        "severity": "LT-MOD"
      },
      "airsigmet_type": "SIGMET",
      "area": [
        {
          "point": {
            "longitude": "-78.9741",
            "latitude": "26.6756"
          }
        },
        {
          "point": {
            "longitude": "-79.264",
            "latitude": "24.8562"
          }
        },
        {
          "point": {
            "longitude": "-79.5215",
            "latitude": "25.0929"
          }
        },
        {
          "point": {
            "longitude": "-80.1584",
            "latitude": "26.107"
          }
        },
        {
          "point": {
            "longitude": "-78.9741",
            "latitude": "26.6756"
          }
        }
      ]
    },
    {
      "raw_text": "WAUS43 KKCI 140245 CHIS WA 140245 AIRMET SIERRA FOR IFR VALID UNTIL 140900 AIRMET IFR...NE FROM 30N ONL TO 40NE OBH TO 60S OBH TO 20SSE LBF TO 60NW LBF TO 30NW ANW TO 30N ONL CIG BLW 010/VIS BLW 3SM PCPN/BR. CONDS DVLPG 03-06Z. CONDS CONTG BYD 09Z THRU 15Z. OTLK VALID 0900-1500Z...IFR SD NE KS BOUNDED BY 60NW ANW-30NNW ONL-20NNW OBH-20SW PWE-60ENE ICT-20S SLN-MCK-50NE SNY-60NW ANW CIG BLW 010/VIS BLW 3SM PCPN/BR. CONDS CONTG THRU 15Z.",
      "valid_time_from": "2021-05-14T02:45:00Z",
      "valid_time_to": "2021-05-14T09:00:00Z",
      "altitude": {
        "min_ft_msl": "0",
        "max_ft_msl": "1000"
      },
      "hazard": {
        "type": "IFR"
      },
      "airsigmet_type": "AIRMET",
      "area": [
        {
          "point": {
            "longitude": "-98.69",
            "latitude": "42.9731"
          }
        },
        {
          "point": {
            "longitude": "-97.719",
            "latitude": "41.8483"
          }
        },
        {
          "point": {
            "longitude": "-98.35",
            "latitude": "40.3829"
          }
        },
        {
          "point": {
            "longitude": "-100.5519",
            "latitude": "40.8228"
          }
        },
        {
          "point": {
            "longitude": "-101.6663",
            "latitude": "41.8312"
          }
        },
        {
          "point": {
            "longitude": "-100.4758",
            "latitude": "42.9247"
          }
        },
        {
          "point": {
            "longitude": "-98.69",
            "latitude": "42.9731"
          }
        }
      ]
    },
    {
      "raw_text": "WAUS46 KKCI 140245 SFOS WA 140245 AIRMET SIERRA FOR IFR AND MTN OBSCN VALID UNTIL 140900 AIRMET IFR...OR CA AND CSTL WTRS FROM 50WNW OED TO 30NE FOT TO 40NW ENI TO 20E OAK TO 60SSE SNS TO 20ENE RZS TO 50NE LAX TO 40WNW TRM TO 40ESE MZB TO 220SW MZB TO 140WSW FOT TO 130WNW FOT TO 50WNW OED CIG BLW 010/VIS BLW 3SM BR/FG. CONDS CONTG BYD 09Z THRU 15Z. OTLK VALID 0900-1500Z...IFR OR CA AND CSTL WTRS BOUNDED BY 50WNW OED-40NW ENI-30ESE OAK-50SSE SNS-20NNE RZS-50NE LAX-40WNW TRM-40E MZB-220SW MZB-140WSW FOT-130WNW FOT-50WNW OED CIG BLW 010/VIS BLW 3SM BR/FG. CONDS CONTG THRU 15Z.",
      "valid_time_from": "2021-05-14T02:45:00Z",
      "valid_time_to": "2021-05-14T09:00:00Z",
      "altitude": {
        "min_ft_msl": "0",
        "max_ft_msl": "1000"
      },
      "hazard": {
        "type": "IFR"
      },
      "airsigmet_type": "AIRMET",
      "area": [
        {
          "point": {
            "longitude": "-123.9619",
            "latitude": "42.7949"
          }
        },
        {
          "point": {
            "longitude": "-123.7585",
            "latitude": "41.0248"
          }
        },
        {
          "point": {
            "longitude": "-123.8793",
            "latitude": "39.5185"
          }
        },
        {
          "point": {
            "longitude": "-121.7998",
            "latitude": "37.7293"
          }
        },
        {
          "point": {
            "longitude": "-121.1299",
            "latitude": "35.7378"
          }
        },
        {
          "point": {
            "longitude": "-119.3968",
            "latitude": "34.6366"
          }
        },
        {
          "point": {
            "longitude": "-117.713",
            "latitude": "34.5187"
          }
        },
        {
          "point": {
            "longitude": "-116.8998",
            "latitude": "33.8822"
          }
        },
        {
          "point": {
            "longitude": "-116.5016",
            "latitude": "32.5235"
          }
        },
        {
          "point": {
            "longitude": "-120.2194",
            "latitude": "30.1591"
          }
        },
        {
          "point": {
            "longitude": "-127.026",
            "latitude": "39.7457"
          }
        },
        {
          "point": {
            "longitude": "-126.8996",
            "latitude": "41.4679"
          }
        },
        {
          "point": {
            "longitude": "-123.9619",
            "latitude": "42.7949"
          }
        }
      ]
    },
    {
      "raw_text": "WAUS46 KKCI 140245 SFOS WA 140245 AIRMET SIERRA FOR IFR AND MTN OBSCN VALID UNTIL 140900 AIRMET MTN OBSCN...WA OR FROM TOU TO 40WSW SEA TO 50SW BTG TO 20ESE EUG TO 20SSW OED TO 70WSW OED TO 70SW EUG TO ONP TO HQM TO TOU MTNS OBSC BY CLDS/BR. CONDS CONTG BYD 09Z THRU 15Z. OTLK VALID 0900-1500Z...IFR OR CA AND CSTL WTRS BOUNDED BY 50WNW OED-40NW ENI-30ESE OAK-50SSE SNS-20NNE RZS-50NE LAX-40WNW TRM-40E MZB-220SW MZB-140WSW FOT-130WNW FOT-50WNW OED CIG BLW 010/VIS BLW 3SM BR/FG. CONDS CONTG THRU 15Z.",
      "valid_time_from": "2021-05-14T02:45:00Z",
      "valid_time_to": "2021-05-14T09:00:00Z",
      "hazard": {
        "type": "MTN OBSCN"
      },
      "airsigmet_type": "AIRMET",
      "area": [
        {
          "point": {
            "longitude": "-124.63",
            "latitude": "48.3"
          }
        },
        {
          "point": {
            "longitude": "-123.2136",
            "latitude": "47.182"
          }
        },
        {
          "point": {
            "longitude": "-123.4277",
            "latitude": "45.1562"
          }
        },
        {
          "point": {
            "longitude": "-122.7932",
            "latitude": "43.992"
          }
        },
        {
          "point": {
            "longitude": "-123.0816",
            "latitude": "42.1728"
          }
        },
        {
          "point": {
            "longitude": "-124.3624",
            "latitude": "42.0239"
          }
        },
        {
          "point": {
            "longitude": "-124.3544",
            "latitude": "43.2886"
          }
        },
        {
          "point": {
            "longitude": "-124.06",
            "latitude": "44.58"
          }
        },
        {
          "point": {
            "longitude": "-124.15",
            "latitude": "46.95"
          }
        },
        {
          "point": {
            "longitude": "-124.63",
            "latitude": "48.3"
          }
        }
      ],
      "altitude": {
      }
    },
    {
      "raw_text": "WAUS46 KKCI 140245 SFOS WA 140245 AIRMET SIERRA FOR IFR AND MTN OBSCN VALID UNTIL 140900 AIRMET IFR...WA OR CA AND CSTL WTRS FROM 20N TOU TO 50SE TOU TO 60SSE HQM TO 30NE ONP TO 50WNW OED TO 130WNW FOT TO 110WNW ONP TO 140W TOU TO 20N TOU CIG BLW 010/VIS BLW 3SM BR/FG. CONDS CONTG BYD 09Z THRU 15Z. OTLK VALID 0900-1500Z...IFR OR CA AND CSTL WTRS BOUNDED BY 50WNW OED-40NW ENI-30ESE OAK-50SSE SNS-20NNE RZS-50NE LAX-40WNW TRM-40E MZB-220SW MZB-140WSW FOT-130WNW FOT-50WNW OED CIG BLW 010/VIS BLW 3SM BR/FG. CONDS CONTG THRU 15Z.",
      "valid_time_from": "2021-05-14T02:45:00Z",
      "valid_time_to": "2021-05-14T09:00:00Z",
      "altitude": {
        "min_ft_msl": "0",
        "max_ft_msl": "1000"
      },
      "hazard": {
        "type": "IFR"
      },
      "airsigmet_type": "AIRMET",
      "area": [
        {
          "point": {
            "longitude": "-124.63",
            "latitude": "48.6324"
          }
        },
        {
          "point": {
            "longitude": "-123.7521",
            "latitude": "47.7059"
          }
        },
        {
          "point": {
            "longitude": "-123.6004",
            "latitude": "46.0274"
          }
        },
        {
          "point": {
            "longitude": "-123.5575",
            "latitude": "44.9346"
          }
        },
        {
          "point": {
            "longitude": "-123.9619",
            "latitude": "42.7949"
          }
        },
        {
          "point": {
            "longitude": "-126.8996",
            "latitude": "41.4679"
          }
        },
        {
          "point": {
            "longitude": "-126.4654",
            "latitude": "45.2562"
          }
        },
        {
          "point": {
            "longitude": "-128.1251",
            "latitude": "48.247"
          }
        },
        {
          "point": {
            "longitude": "-124.63",
            "latitude": "48.6324"
          }
        }
      ]
    },
    {
      "raw_text": "WAUS42 KKCI 140245 MIAZ WA 140245 AIRMET ZULU FOR ICE AND FRZLVL VALID UNTIL 140900 AIRMET ICE...NC SC GA PA WV MD DC VA FROM 20ESE PSB TO 40E DCA TO 50SSE DCA TO 30NNW RDU TO 20WSW SPA TO 20NW ATL TO 30S VXV TO 40W HMV TO 20NE BKW TO 40ESE EWC TO 20ESE PSB MOD ICE BTN 070 AND 140. CONDS CONTG BYD 09Z THRU 15Z. FRZLVL...RANGING FROM 060-145 ACRS AREA 080 ALG 40S GQO-50S ILM-120ESE ILM-170SE ECG 120 ALG 40W CEW-50WSW TLH-30NE CTY-220SE CHS",
      "valid_time_from": "2021-05-14T02:45:00Z",
      "valid_time_to": "2021-05-14T09:00:00Z",
      "altitude": {
        "min_ft_msl": "7000",
        "max_ft_msl": "14000"
      },
      "hazard": {
        "type": "ICE",
        "severity": "MOD"
      },
      "airsigmet_type": "AIRMET",
      "area": [
        {
          "point": {
            "longitude": "-77.5844",
            "latitude": "40.7921"
          }
        },
        {
          "point": {
            "longitude": "-76.1863",
            "latitude": "38.8569"
          }
        },
        {
          "point": {
            "longitude": "-76.6338",
            "latitude": "38.0875"
          }
        },
        {
          "point": {
            "longitude": "-79.019",
            "latitude": "36.3345"
          }
        },
        {
          "point": {
            "longitude": "-82.3044",
            "latitude": "34.9022"
          }
        },
        {
          "point": {
            "longitude": "-84.723",
            "latitude": "33.8647"
          }
        },
        {
          "point": {
            "longitude": "-83.89",
            "latitude": "35.3969"
          }
        },
        {
          "point": {
            "longitude": "-82.9563",
            "latitude": "36.4372"
          }
        },
        {
          "point": {
            "longitude": "-80.8217",
            "latitude": "38.0147"
          }
        },
        {
          "point": {
            "longitude": "-79.4015",
            "latitude": "40.5728"
          }
        },
        {
          "point": {
            "longitude": "-77.5844",
            "latitude": "40.7921"
          }
        }
      ]
    },
    {
      "raw_text": "WAUS43 KKCI 140245 CHIZ WA 140245 AIRMET ZULU FOR ICE AND FRZLVL VALID UNTIL 140900 AIRMET ICE...ND SD MN IA FROM 50NNE MOT TO 80SE YWG TO 20NNE BRD TO 50SW DSM TO 20S ABR TO 60ESE BIS TO 50NNE MOT MOD ICE BTN 070 AND 160. CONDS DVLPG 03-06Z. CONDS CONTG BYD 09Z THRU 15Z. OTLK VALID 0900-1500Z AREA 1...ICE ND SD BOUNDED BY 50NNW ISN-60SSE DIK-70ESE MLS-50NNW ISN MOD ICE BTN 090 AND FL190. CONDS DVLPG AFT 15Z. CONDS ENDG BY 15Z. AREA 2...ICE ND SD MN IA WI BOUNDED BY 60NNE MOT-30E INL-40SSW DLH-30SE FOD-50SW DSM-40E ABR-70E BIS-60NNE MOT MOD ICE BTN 080 AND 160. CONDS CONTG THRU 15Z. AREA 3...ICE SD NE KS MN IA MO OK BOUNDED BY 40E ABR-50SW DSM-30ESE FOD-40S COU-30SSW SGF-50WSW TUL-40SE GCK-20SE MCK-60E MCK-30SSW ONL-50SW PIR-40SW ABR-40E ABR MOD ICE BTN FRZLVL AND FL190. FRZLVL 080-120. CONDS CONTG THRU 15Z. AREA 4...ICE KY BOUNDED BY 20WNW BKW-HMV-20SSE VXV-40SSW LOZ-20WNW BKW MOD ICE BTN 070 AND 160. CONDS DVLPG AFT 12Z. CONDS CONTG THRU 15Z. FRZLVL...RANGING FROM 060-130 ACRS AREA 080 ALG 100WSW YWG-30SSW GFK-40SSW FOD-30W IRK-50SSW IRK-20SE SGF-70W ARG 120 ALG 40E AKO-30SW HLC-50NNE MMB",
      "valid_time_from": "2021-05-14T02:45:00Z",
      "valid_time_to": "2021-05-14T09:00:00Z",
      "altitude": {
        "min_ft_msl": "7000",
        "max_ft_msl": "16000"
      },
      "hazard": {
        "type": "ICE",
        "severity": "MOD"
      },
      "airsigmet_type": "AIRMET",
      "area": [
        {
          "point": {
            "longitude": "-100.8024",
            "latitude": "49.0308"
          }
        },
        {
          "point": {
            "longitude": "-95.7984",
            "latitude": "48.951"
          }
        },
        {
          "point": {
            "longitude": "-93.8447",
            "latitude": "46.6569"
          }
        },
        {
          "point": {
            "longitude": "-94.4309",
            "latitude": "40.8466"
          }
        },
        {
          "point": {
            "longitude": "-98.37",
            "latitude": "45.0876"
          }
        },
        {
          "point": {
            "longitude": "-99.3346",
            "latitude": "46.3806"
          }
        },
        {
          "point": {
            "longitude": "-100.8024",
            "latitude": "49.0308"
          }
        }
      ]
    },
    {
      "raw_text": "WAUS46 KKCI 140245 SFOS WA 140245 AIRMET SIERRA FOR IFR AND MTN OBSCN VALID UNTIL 140900 AIRMET MTN OBSCN...CA FROM 20SSW ENI TO 30WNW SAC TO 20NE SNS TO 30S SNS TO 20SSW ENI MTNS OBSC BY CLDS/BR. CONDS DVLPG AFT 03Z. CONDS CONTG BYD 09Z THRU 15Z. OTLK VALID 0900-1500Z...IFR OR CA AND CSTL WTRS BOUNDED BY 50WNW OED-40NW ENI-30ESE OAK-50SSE SNS-20NNE RZS-50NE LAX-40WNW TRM-40E MZB-220SW MZB-140WSW FOT-130WNW FOT-50WNW OED CIG BLW 010/VIS BLW 3SM BR/FG. CONDS CONTG THRU 15Z.",
      "valid_time_from": "2021-05-14T02:45:00Z",
      "valid_time_to": "2021-05-14T09:00:00Z",
      "hazard": {
        "type": "MTN OBSCN"
      },
      "airsigmet_type": "AIRMET",
      "area": [
        {
          "point": {
            "longitude": "-123.4331",
            "latitude": "38.7428"
          }
        },
        {
          "point": {
            "longitude": "-122.145",
            "latitude": "38.631"
          }
        },
        {
          "point": {
            "longitude": "-121.3061",
            "latitude": "36.8947"
          }
        },
        {
          "point": {
            "longitude": "-121.6",
            "latitude": "36.1569"
          }
        },
        {
          "point": {
            "longitude": "-123.4331",
            "latitude": "38.7428"
          }
        }
      ],
      "altitude": {
      }
    },
    {
      "raw_text": "WAUS46 KKCI 140245 SFOS WA 140245 AIRMET SIERRA FOR IFR AND MTN OBSCN VALID UNTIL 140900 AIRMET MTN OBSCN...CA FROM 40S SNS TO 20NNE RZS TO 40SW HEC TO 60S TRM TO MZB TO LAX TO 40W RZS TO 40S SNS MTNS OBSC BY CLDS/BR. CONDS CONTG BYD 09Z THRU 15Z. OTLK VALID 0900-1500Z...IFR OR CA AND CSTL WTRS BOUNDED BY 50WNW OED-40NW ENI-30ESE OAK-50SSE SNS-20NNE RZS-50NE LAX-40WNW TRM-40E MZB-220SW MZB-140WSW FOT-130WNW FOT-50WNW OED CIG BLW 010/VIS BLW 3SM BR/FG. CONDS CONTG THRU 15Z.",
      "valid_time_from": "2021-05-14T02:45:00Z",
      "valid_time_to": "2021-05-14T09:00:00Z",
      "hazard": {
        "type": "MTN OBSCN"
      },
      "airsigmet_type": "AIRMET",
      "area": [
        {
          "point": {
            "longitude": "-121.6",
            "latitude": "35.9952"
          }
        },
        {
          "point": {
            "longitude": "-119.6151",
            "latitude": "34.817"
          }
        },
        {
          "point": {
            "longitude": "-117.0292",
            "latitude": "34.3286"
          }
        },
        {
          "point": {
            "longitude": "-116.16",
            "latitude": "32.6329"
          }
        },
        {
          "point": {
            "longitude": "-117.23",
            "latitude": "32.78"
          }
        },
        {
          "point": {
            "longitude": "-118.43",
            "latitude": "33.93"
          }
        },
        {
          "point": {
            "longitude": "-120.5767",
            "latitude": "34.5073"
          }
        },
        {
          "point": {
            "longitude": "-121.6",
            "latitude": "35.9952"
          }
        }
      ],
      "altitude": {
      }
    },
    {
      "raw_text": "WAUS41 KKCI 140245 BOSZ WA 140245 AIRMET ZULU FOR ICE AND FRZLVL VALID UNTIL 140900 AIRMET ICE...PA WV MD DC VA NC SC GA FROM 20ESE PSB TO 40E DCA TO 50SSE DCA TO 30NNW RDU TO 20WSW SPA TO 20NW ATL TO 30S VXV TO 40W HMV TO 20NE BKW TO 40ESE EWC TO 20ESE PSB MOD ICE BTN 070 AND 140. CONDS CONTG BYD 09Z THRU 15Z. FRZLVL...RANGING FROM 045-075 ACRS AREA",
      "valid_time_from": "2021-05-14T02:45:00Z",
      "valid_time_to": "2021-05-14T09:00:00Z",
      "altitude": {
        "min_ft_msl": "7000",
        "max_ft_msl": "14000"
      },
      "hazard": {
        "type": "ICE",
        "severity": "MOD"
      },
      "airsigmet_type": "AIRMET",
      "area": [
        {
          "point": {
            "longitude": "-77.5844",
            "latitude": "40.7921"
          }
        },
        {
          "point": {
            "longitude": "-76.1863",
            "latitude": "38.8569"
          }
        },
        {
          "point": {
            "longitude": "-76.6338",
            "latitude": "38.0875"
          }
        },
        {
          "point": {
            "longitude": "-79.019",
            "latitude": "36.3345"
          }
        },
        {
          "point": {
            "longitude": "-82.3044",
            "latitude": "34.9022"
          }
        },
        {
          "point": {
            "longitude": "-84.723",
            "latitude": "33.8647"
          }
        },
        {
          "point": {
            "longitude": "-83.89",
            "latitude": "35.3969"
          }
        },
        {
          "point": {
            "longitude": "-82.9563",
            "latitude": "36.4372"
          }
        },
        {
          "point": {
            "longitude": "-80.8217",
            "latitude": "38.0147"
          }
        },
        {
          "point": {
            "longitude": "-79.4015",
            "latitude": "40.5728"
          }
        },
        {
          "point": {
            "longitude": "-77.5844",
            "latitude": "40.7921"
          }
        }
      ]
    },
    {
      "raw_text": "WAUS45 KKCI 140245 SLCZ WA 140245 AIRMET ZULU FOR ICE AND FRZLVL VALID UNTIL 140900 AIRMET ICE...MT FROM 60N ISN TO 50W DIK TO 80SE MLS TO 30NNW BIL TO 20ENE FCA TO 50SE YXC TO 60N ISN MOD ICE BTN 090 AND 160. CONDS DVLPG 03-06Z. CONDS CONTG BYD 09Z THRU 15Z. OTLK VALID 0900-1500Z...ICE ID MT WY UT BOUNDED BY 70E DLN-60E SHR-20SSW SNY-30SW LAR-50ENE SLC-20SE TWF-70E DLN MOD ICE BTN FRZLVL AND FL190. FRZLVL 100-120. CONDS CONTG THRU 15Z. FRZLVL...RANGING FROM 080-145 ACRS AREA 120 ALG 40WSW BOI-50WNW PIH-70SW DDY-40E AKO",
      "valid_time_from": "2021-05-14T02:45:00Z",
      "valid_time_to": "2021-05-14T09:00:00Z",
      "altitude": {
        "min_ft_msl": "9000",
        "max_ft_msl": "16000"
      },
      "hazard": {
        "type": "ICE",
        "severity": "MOD"
      },
      "airsigmet_type": "AIRMET",
      "area": [
        {
          "point": {
            "longitude": "-103.63",
            "latitude": "49.1771"
          }
        },
        {
          "point": {
            "longitude": "-103.9917",
            "latitude": "46.8535"
          }
        },
        {
          "point": {
            "longitude": "-104.6104",
            "latitude": "45.432"
          }
        },
        {
          "point": {
            "longitude": "-108.9085",
            "latitude": "46.2744"
          }
        },
        {
          "point": {
            "longitude": "-113.7181",
            "latitude": "48.3363"
          }
        },
        {
          "point": {
            "longitude": "-114.8795",
            "latitude": "49.0057"
          }
        },
        {
          "point": {
            "longitude": "-103.63",
            "latitude": "49.1771"
          }
        }
      ]
    },
    {
      "raw_text": "WAUS45 KKCI 140245 SLCZ WA 140245 AIRMET ZULU FOR ICE AND FRZLVL VALID UNTIL 140900 AIRMET ICE...ID MT WY UT FROM 80E DLN TO 20E SHR TO 30SSW OCS TO 20SSE TWF TO 80E DLN MOD ICE BTN FRZLVL AND FL190. FRZLVL 100-120. CONDS DVLPG 06-09Z. CONDS CONTG BYD 09Z THRU 15Z. OTLK VALID 0900-1500Z...ICE ID MT WY UT BOUNDED BY 70E DLN-60E SHR-20SSW SNY-30SW LAR-50ENE SLC-20SE TWF-70E DLN MOD ICE BTN FRZLVL AND FL190. FRZLVL 100-120. CONDS CONTG THRU 15Z. FRZLVL...RANGING FROM 080-145 ACRS AREA 120 ALG 40WSW BOI-50WNW PIH-70SW DDY-40E AKO",
      "valid_time_from": "2021-05-14T02:45:00Z",
      "valid_time_to": "2021-05-14T09:00:00Z",
      "altitude": {
        "min_ft_msl": "10000",
        "max_ft_msl": "19000"
      },
      "hazard": {
        "type": "ICE",
        "severity": "MOD"
      },
      "airsigmet_type": "AIRMET",
      "area": [
        {
          "point": {
            "longitude": "-110.6619",
            "latitude": "45.2344"
          }
        },
        {
          "point": {
            "longitude": "-106.5913",
            "latitude": "44.839"
          }
        },
        {
          "point": {
            "longitude": "-109.2756",
            "latitude": "41.125"
          }
        },
        {
          "point": {
            "longitude": "-114.3184",
            "latitude": "42.1728"
          }
        },
        {
          "point": {
            "longitude": "-110.6619",
            "latitude": "45.2344"
          }
        }
      ]
    },
    {
      "raw_text": "WAUS44 KKCI 140245 DFWT WA 140245 AIRMET TANGO FOR TURB AND LLWS VALID UNTIL 140900 AIRMET TURB...OK AR TN SD NE KS MN IA MO WI IL IN KY FROM 60ENE DPR TO MSP TO 30NW DLL TO TTH TO MEM TO 60ENE ICT TO 60E MCK TO 60ENE DPR MOD TURB BTN FL290 AND FL390. CONDS CONTG BYD 09Z THRU 15Z. OTLK VALID 0900-1500Z AREA 1...TURB OK AR TN MS AL SD NE KS MN IA MO WI LM MI IL IN KY BOUNDED BY 40SW RHI-GRR-20SE VXV-GQO-20WNW PZD-50SSW VUZ-SLN-FSD- 20NNW RWF-40SW RHI MOD TURB BTN FL290 AND FL390. CONDS CONTG THRU 15Z. AREA 2...TURB OK TX AR LA MS AL AND CSTL WTRS BOUNDED BY 30WSW OKC-40NNW ELD-40E SJI-120ESE LEV-110SSE LCH- 30NNW DLF-INK-40NNW CDS-30WSW OKC MOD TURB BTN FL280 AND FL410. CONDS CONTG THRU 15Z.",
      "valid_time_from": "2021-05-14T02:45:00Z",
      "valid_time_to": "2021-05-14T09:00:00Z",
      "altitude": {
        "min_ft_msl": "29000",
        "max_ft_msl": "39000"
      },
      "hazard": {
        "type": "TURB",
        "severity": "MOD"
      },
      "airsigmet_type": "AIRMET",
      "area": [
        {
          "point": {
            "longitude": "-100.4067",
            "latitude": "45.4541"
          }
        },
        {
          "point": {
            "longitude": "-93.23",
            "latitude": "44.88"
          }
        },
        {
          "point": {
            "longitude": "-90.2537",
            "latitude": "43.9047"
          }
        },
        {
          "point": {
            "longitude": "-87.25",
            "latitude": "39.49"
          }
        },
        {
          "point": {
            "longitude": "-89.98",
            "latitude": "35.06"
          }
        },
        {
          "point": {
            "longitude": "-96.4089",
            "latitude": "38.1258"
          }
        },
        {
          "point": {
            "longitude": "-99.2846",
            "latitude": "40.1927"
          }
        },
        {
          "point": {
            "longitude": "-100.4067",
            "latitude": "45.4541"
          }
        }
      ]
    },
    {
      "raw_text": "WAUS43 KKCI 140245 CHIZ WA 140245 AIRMET ZULU FOR ICE AND FRZLVL VALID UNTIL 140900 AIRMET ICE...ND SD NE KS MN IA MO FROM 50W DIK TO 60SW BIS TO 30N PIR TO 20S ABR TO 50SW DSM TO 50WSW BUM TO 50SSE HLC TO 50E MCK TO 30NNW LBF TO 30NNE RAP TO 80SE MLS TO 50W DIK MOD ICE BTN FRZLVL AND FL190. FRZLVL 080-110. CONDS CONTG BYD 09Z THRU 15Z. OTLK VALID 0900-1500Z AREA 1...ICE ND SD BOUNDED BY 50NNW ISN-60SSE DIK-70ESE MLS-50NNW ISN MOD ICE BTN 090 AND FL190. CONDS DVLPG AFT 15Z. CONDS ENDG BY 15Z. AREA 2...ICE ND SD MN IA WI BOUNDED BY 60NNE MOT-30E INL-40SSW DLH-30SE FOD-50SW DSM-40E ABR-70E BIS-60NNE MOT MOD ICE BTN 080 AND 160. CONDS CONTG THRU 15Z. AREA 3...ICE SD NE KS MN IA MO OK BOUNDED BY 40E ABR-50SW DSM-30ESE FOD-40S COU-30SSW SGF-50WSW TUL-40SE GCK-20SE MCK-60E MCK-30SSW ONL-50SW PIR-40SW ABR-40E ABR MOD ICE BTN FRZLVL AND FL190. FRZLVL 080-120. CONDS CONTG THRU 15Z. AREA 4...ICE KY BOUNDED BY 20WNW BKW-HMV-20SSE VXV-40SSW LOZ-20WNW BKW MOD ICE BTN 070 AND 160. CONDS DVLPG AFT 12Z. CONDS CONTG THRU 15Z. FRZLVL...RANGING FROM 060-130 ACRS AREA 080 ALG 100WSW YWG-30SSW GFK-40SSW FOD-30W IRK-50SSW IRK-20SE SGF-70W ARG 120 ALG 40E AKO-30SW HLC-50NNE MMB",
      "valid_time_from": "2021-05-14T02:45:00Z",
      "valid_time_to": "2021-05-14T09:00:00Z",
      "altitude": {
        "min_ft_msl": "8000",
        "max_ft_msl": "19000"
      },
      "hazard": {
        "type": "ICE",
        "severity": "MOD"
      },
      "airsigmet_type": "AIRMET",
      "area": [
        {
          "point": {
            "longitude": "-103.9917",
            "latitude": "46.8535"
          }
        },
        {
          "point": {
            "longitude": "-101.6861",
            "latitude": "46.0604"
          }
        },
        {
          "point": {
            "longitude": "-100.17",
            "latitude": "44.9031"
          }
        },
        {
          "point": {
            "longitude": "-98.37",
            "latitude": "45.0876"
          }
        },
        {
          "point": {
            "longitude": "-94.4309",
            "latitude": "40.8466"
          }
        },
        {
          "point": {
            "longitude": "-95.4688",
            "latitude": "37.9462"
          }
        },
        {
          "point": {
            "longitude": "-99.8216",
            "latitude": "38.4874"
          }
        },
        {
          "point": {
            "longitude": "-99.4963",
            "latitude": "40.1949"
          }
        },
        {
          "point": {
            "longitude": "-100.9774",
            "latitude": "41.5945"
          }
        },
        {
          "point": {
            "longitude": "-102.7404",
            "latitude": "44.4444"
          }
        },
        {
          "point": {
            "longitude": "-104.6104",
            "latitude": "45.432"
          }
        },
        {
          "point": {
            "longitude": "-103.9917",
            "latitude": "46.8535"
          }
        }
      ]
    },
    {
      "raw_text": "WAUS43 KKCI 140245 CHIT WA 140245 AIRMET TANGO FOR TURB AND LLWS VALID UNTIL 140900 AIRMET TURB...SD NE KS MN IA MO WI IL IN KY OK AR TN FROM 60ENE DPR TO MSP TO 30NW DLL TO TTH TO MEM TO 60ENE ICT TO 60E MCK TO 60ENE DPR MOD TURB BTN FL290 AND FL390. CONDS CONTG BYD 09Z THRU 15Z. LLWS POTENTIAL...NE KS OK TX BOUNDED BY 60W ANW-30SSW OBH-20WSW SLN-MMB-60ESE CIM-30ESE TBE- 50W LBL-GLD-40SSE SNY-60W ANW LLWS EXP. CONDS CONTG BYD 09Z ENDG 12-15Z. OTLK VALID 0900-1500Z...TURB SD NE KS MN IA MO WI LM MI IL IN KY OK AR TN MS AL BOUNDED BY 40SW RHI-GRR-20SE VXV-GQO-20WNW PZD-50SSW VUZ-SLN-FSD- 20NNW RWF-40SW RHI MOD TURB BTN FL290 AND FL390. CONDS CONTG THRU 15Z.",
      "valid_time_from": "2021-05-14T02:45:00Z",
      "valid_time_to": "2021-05-14T09:00:00Z",
      "altitude": {
        "min_ft_msl": "29000",
        "max_ft_msl": "39000"
      },
      "hazard": {
        "type": "TURB",
        "severity": "MOD"
      },
      "airsigmet_type": "AIRMET",
      "area": [
        {
          "point": {
            "longitude": "-100.4067",
            "latitude": "45.4541"
          }
        },
        {
          "point": {
            "longitude": "-93.23",
            "latitude": "44.88"
          }
        },
        {
          "point": {
            "longitude": "-90.2537",
            "latitude": "43.9047"
          }
        },
        {
          "point": {
            "longitude": "-87.25",
            "latitude": "39.49"
          }
        },
        {
          "point": {
            "longitude": "-89.98",
            "latitude": "35.06"
          }
        },
        {
          "point": {
            "longitude": "-96.4089",
            "latitude": "38.1258"
          }
        },
        {
          "point": {
            "longitude": "-99.2846",
            "latitude": "40.1927"
          }
        },
        {
          "point": {
            "longitude": "-100.4067",
            "latitude": "45.4541"
          }
        }
      ]
    },
    {
      "raw_text": "WAUS44 KKCI 140245 DFWT WA 140245 AIRMET TANGO FOR TURB AND LLWS VALID UNTIL 140900 AIRMET TURB...LA MS AL AND CSTL WTRS FROM CEW TO 130ESE LEV TO 70SW LEV TO CEW MOD TURB BTN FL280 AND FL410. CONDS ENDG BY 06Z. OTLK VALID 0900-1500Z AREA 1...TURB OK AR TN MS AL SD NE KS MN IA MO WI LM MI IL IN KY BOUNDED BY 40SW RHI-GRR-20SE VXV-GQO-20WNW PZD-50SSW VUZ-SLN-FSD- 20NNW RWF-40SW RHI MOD TURB BTN FL290 AND FL390. CONDS CONTG THRU 15Z. AREA 2...TURB OK TX AR LA MS AL AND CSTL WTRS BOUNDED BY 30WSW OKC-40NNW ELD-40E SJI-120ESE LEV-110SSE LCH- 30NNW DLF-INK-40NNW CDS-30WSW OKC MOD TURB BTN FL280 AND FL410. CONDS CONTG THRU 15Z.",
      "valid_time_from": "2021-05-14T02:45:00Z",
      "valid_time_to": "2021-05-14T09:00:00Z",
      "altitude": {
        "min_ft_msl": "28000",
        "max_ft_msl": "41000"
      },
      "hazard": {
        "type": "TURB",
        "severity": "MOD"
      },
      "airsigmet_type": "AIRMET",
      "area": [
        {
          "point": {
            "longitude": "-86.68",
            "latitude": "30.83"
          }
        },
        {
          "point": {
            "longitude": "-87.8276",
            "latitude": "28.3323"
          }
        },
        {
          "point": {
            "longitude": "-91.0383",
            "latitude": "28.351"
          }
        },
        {
          "point": {
            "longitude": "-86.68",
            "latitude": "30.83"
          }
        }
      ]
    },
    {
      "raw_text": "WAUS42 KKCI 140245 MIAT WA 140245 AIRMET TANGO FOR TURB VALID UNTIL 140900 AIRMET TURB...NC SC GA FL AND CSTL WTRS FROM 140SSE ILM TO 220ENE TRV TO 30SSE TRV TO 30SE SRQ TO 130ESE LEV TO CEW TO 40S SAV TO 140SSE ILM MOD TURB BTN FL280 AND FL410. CONDS CONTG BYD 09Z THRU 15Z. OTLK VALID 0900-1500Z AREA 1...TURB NC GA BOUNDED BY 20SE VXV-ODF-20WNW PZD-GQO-20SE VXV MOD TURB BTN FL290 AND FL390. CONDS DVLPG AFT 12Z. CONDS CONTG THRU 15Z. AREA 2...TURB FL AND CSTL WTRS BOUNDED BY 40E SJI-80WSW CTY-180S CEW-120ESE LEV-40E SJI MOD TURB BTN FL280 AND FL410. CONDS DVLPG AFT 12Z. CONDS CONTG THRU 15Z.",
      "valid_time_from": "2021-05-14T02:45:00Z",
      "valid_time_to": "2021-05-14T09:00:00Z",
      "altitude": {
        "min_ft_msl": "28000",
        "max_ft_msl": "41000"
      },
      "hazard": {
        "type": "TURB",
        "severity": "MOD"
      },
      "airsigmet_type": "AIRMET",
      "area": [
        {
          "point": {
            "longitude": "-76.8181",
            "latitude": "32.1959"
          }
        },
        {
          "point": {
            "longitude": "-76.6267",
            "latitude": "29.0254"
          }
        },
        {
          "point": {
            "longitude": "-80.2735",
            "latitude": "27.2151"
          }
        },
        {
          "point": {
            "longitude": "-82.1506",
            "latitude": "27.0437"
          }
        },
        {
          "point": {
            "longitude": "-87.8276",
            "latitude": "28.3323"
          }
        },
        {
          "point": {
            "longitude": "-86.68",
            "latitude": "30.83"
          }
        },
        {
          "point": {
            "longitude": "-81.11",
            "latitude": "31.4952"
          }
        },
        {
          "point": {
            "longitude": "-76.8181",
            "latitude": "32.1959"
          }
        }
      ]
    },
    {
      "raw_text": "WAUS45 KKCI 140245 SLCT WA 140245 AIRMET TANGO FOR TURB AND LLWS VALID UNTIL 140900 AIRMET TURB...NM FROM TXO TO INK TO ELP TO 70SSE ABQ TO TXO MOD TURB BTN FL280 AND FL410. CONDS ENDG BY 09Z. LLWS POTENTIAL...CO NM BOUNDED BY 40E AKO-GLD-50W LBL-30ESE TBE-60ESE CIM-30ENE PUB-40E AKO LLWS EXP. CONDS DVLPG AFT 03Z. CONDS CONTG BYD 09Z ENDG BY 12Z.",
      "valid_time_from": "2021-05-14T02:45:00Z",
      "valid_time_to": "2021-05-14T09:00:00Z",
      "altitude": {
        "min_ft_msl": "28000",
        "max_ft_msl": "41000"
      },
      "hazard": {
        "type": "TURB",
        "severity": "MOD"
      },
      "airsigmet_type": "AIRMET",
      "area": [
        {
          "point": {
            "longitude": "-102.84",
            "latitude": "34.5"
          }
        },
        {
          "point": {
            "longitude": "-103.24",
            "latitude": "31.87"
          }
        },
        {
          "point": {
            "longitude": "-106.28",
            "latitude": "31.82"
          }
        },
        {
          "point": {
            "longitude": "-106.2812",
            "latitude": "33.9599"
          }
        },
        {
          "point": {
            "longitude": "-102.84",
            "latitude": "34.5"
          }
        }
      ]
    }
  ]
}